Workbook

Sheet Introduction
B3: STM OCE-P to Vault CRM Migration - Calls
B5: WIP v0.1
B8: Reviewer | C8: Role
B9: Aline Machado | C9: BO
B10: Aleksandra Bujwid | C10: Core BA

Sheet Data_Models
B1: Veeva Account and Call Data Model | K1: OCE-P Call Data Model

Sheet SRC - OCE-P Objects
A1: Object | B1: Object Label | C1: Object Description | D1: Ownership
A2: OCE__Call__c | B2: Interactions | C2: The Call object stores all data pertaining to Calls Reps have logged using the Log a Call module.
A3: OCE__CallDetail__c | B3: Interaction Details | C3: The object stores data related to Details during the Call | D3: Sutapa/Swaroop
A4: OCE__CallDiscussion__c | B4: Call Discussions | C4: The object stores data related to Discussions about products, during the Call | D4: Sutapa/Swaroop
A5: OCE__CallMessage__c | B5: Call Messages | C5: The object stores data related to messages/reactions during the Call | D5: Sutapa/Swaroop
A6: OCE__CallEmployeeAttendee__c | B6: Call Employee Attendees | C6: Junction object which contains users which are added as attendees to call.
A7: OCE__CallItem__c | B7: Call Items | C7: The object stores data related to Items during the Call
A8: OCE__CallPresentation__c | B8: Call Presentations | C8: The object stores data related to Presentations shown from Call, Meeting, etc.
A9: OCE__CallDialogue__c | B9: Interaction Dialogues | C9: Contains surveys passed on LogACall.
A10: OCE__CallSampleOrder__c | B10: Call Sample Orders | C10: The object stores data related to Sample Orders during the Call
A11: OCE__CallStudy__c | B11: Interaction clinical trials | C11: Studies which were done during call.
A12: OCE__CallToDo__c | B12: Interaction To-Dos | C12: Junction object between Call and To-Do objects
A13: OCE__CallAccountTactic__c | B13: Interaction Tactics | C13: Junction object to connect Call to Tactics.
A14: OCE__CallSample__c | B14: Call Samples | C14: The object stores data related to Samples during the Call
A15: OCE__CallPlan__c | B15: Call Plans | C15: A strategic plan that is focused on reach and frequency.
A16: OCE__CallExpense__c | B16: Call Expenses | C16: The object stores data related to Expenses during the Call

Sheet TGT - Vault CRM Objects
A1: Object | B1: Object Label | C1: Object Description
A2: call2__v | B2: Call | C2: This object stores the main call header information. There is one call row for every account or contact on the call. A group call with 3 doctors will produce 4 call rows.
A3: call2_detail__v | B3: Call Detail | C3: This object stores all product details data recorded on any call.
A4: call2_discussion__v | B4: Call Discussion | C4: This object stores all product discussions data recorded on any call, as well as allows for creating different product discussions layouts
A5: call2_expense__v | B5: Call Expense | C5: This object stores all expense data recorded on a call
A6: call2_key_message__v | B6: Call Key Message | C6: This object stores all Key Messages recorded on a call
A7: call2_sample__v | B7: Call Sample | C7: Samples and Promotional Items itemized on Call Reports
A8: call2_sample_cancel__v | B8: Call Sample Cancel | C8: The Call Sample Cancel object provides the ability to Cancel the delivery of a Sample Send request for a physician.
A9: call_clickstream__v | B9: Call Clickstream | C9: Object containing clickstream data received from CLM system.
A10: call_cycle_entry__v | B10: Call Cycle Entry | C10: Call Cycle Entries store information about a rep's weekly route. They only store account name, the default address for each account is used when the call cycle is applied to a day. Call cycles (and their titles) are only editable on VMobile. However, r
A11: call_error__v | B11: Call Error | C11: This is a temporary holding object for failed synchronization messages from the mobile client. The messages will be accepted or rejected by an administrator.
A12: call_followup_task__v | B12: Call Followup Task | C12: This is the user task object that stores records for call follow up activities.
... A14: call_objective__v | B14: Call Objective | C14: Call Objective can be accessed through Call Report

Sheet SRC - OCE-P Object Fields
A1: _ | B1: EntityDefinition | C1: EntityDefinition.QualifiedApiName | D1: DurableId | E1: Label | F1: QualifiedApiName | G1: DataType | H1: RelationshipName | I1: ExtraTypeInfo | J1: Length | K1: Precision | L1: ValueTypeId | M1: IsIndexed | N1: IsNillable | O1: IsCompound | P1: IsHighScaleNumber | Q1: IsHtmlFormatted | R1: IsCalculated | S1: Description
A2: [FieldDefinition] | B2: [EntityDefinition] | C2: OCE__CallItem__c | D2: 01I3X000001zXyY.UserRecordAccess | E2: Object Access Level | F2: UserRecordAccessId | G2: Lookup(User Record Access) | H2: UserRecordAccess | J2: 18 | K2: 0 | L2: id | M2: false | N2: true | O2: false | P2: false | Q2: false | R2: false
A3: [FieldDefinition] | B3: [EntityDefinition] | C3: OCE__CallItem__c | D3: 01I3X000001zXyY.SystemModstamp | E3: System Modstamp | F3: SystemModstamp | G3: Date/Time | J3: 0 | K3: 0 | L3: datetime | M3: true | N3: false | O3: false | P3: false | Q3: false | R3: false
A4: [FieldDefinition] | B4: [EntityDefinition] | C4: OCE__CallItem__c | D4: 01I3X000001zXyY.Owner | E4: Owner | F4: OwnerId | G4: Lookup(User,Group) | H4: Owner | J4: 18 | K4: 0 | L4: id | M4: true | N4: false | O4: false | P4: false | Q4: false | R4: false
A5: [FieldDefinition] | B5: [EntityDefinition] | C5: OCE__CallItem__c | D5: 01I3X000001zXyY.Name | E5: Interaction Item Name | F5: Name | G5: Auto Number | J5: 80 | K5: 0 | L5: string | M5: true | N5: false | O5: false | P5: false | Q5: false | R5: false
A6: [FieldDefinition] | B6: [EntityDefinition] | C6: OCE__CallItem__c | D6: 01I3X000001zXyY.LastModifiedDate | E6: Last Modified Date | F6: LastModifiedDate | G6: Date/Time | J6: 0 | K6: 0 | L6: datetime | M6: false | N6: false | O6: false | P6: false | Q6: false | R6: false
A7: [FieldDefinition] | B7: [EntityDefinition] | C7: OCE__CallItem__c | D7: 01I3X000001zXyY.LastModifiedBy | E7: Last Modified By | F7: LastModifiedById | G7: Lookup(User) | H7: LastModifiedBy | J7: 18 | K7: 0 | L7: id | M7: false | N7: false | O7: false | P7: false | Q7: false | R7: false
A8: [FieldDefinition] | B8: [EntityDefinition] | C8: OCE__CallItem__c | D8: 01I3X000001zXyY.LastActivityDate | E8: Last Activity Date | F8: LastActivityDate | G8: Date | J8: 0 | K8: 0 | L8: date | M8: false | N8: true | O8: false | P8: false | Q8: false | R8: false
A9: [FieldDefinition] | B9: [EntityDefinition] | C9: OCE__CallItem__c | D9: 01I3X000001zXyY.IsDeleted | E9: Deleted | F9: IsDeleted | G9: Checkbox | J9: 0 | K9: 0 | L9: boolean | M9: true | N9: false | O9: false | P9: false | Q9: false | R9: false
A10: [FieldDefinition] | B10: [EntityDefinition] | C10: OCE__CallItem__c | D10: 01I3X000001zXyY.Id | E10: Record ID | F10: Id | G10: Lookup() | J10: 18 | K10: 0 | L10: id | M10: true | N10: false | O10: false | P10: false | Q10: false | R10: false
A11: [FieldDefinition] | B11: [EntityDefinition] | C11: OCE__CallItem__c | D11: 01I3X000001zXyY.CurrencyIsoCode | E11: Currency | F11: CurrencyIsoCode | G11: Picklist | J11: 3 | K11: 0 | L11: string | M11: false | N11: true | O11: false | P11: false | Q11: false | R11: false
A12: [FieldDefinition] | B12: [EntityDefinition] | C12: OCE__CallItem__c | D12: 01I3X000001zXyY.CreatedDate | E12: Created Date | F12: CreatedDate | G12: Date/Time | J12: 0 | K12: 0 | L12: datetime | M12: true | N12: false | O12: false | P12: false | Q12: false | R12: false
A13: [FieldDefinition] | B13: [EntityDefinition] | C13: OCE__CallItem__c | D13: 01I3X000001zXyY.CreatedBy | E13: Created By | F13: CreatedById | G13: Lookup(User) | H13: CreatedBy | J13: 18 | K13: 0 | L13: id | M13: false | N13: false | O13: false | P13: false | Q13: false | R13: false
A14: [FieldDefinition] | B14: [EntityDefinition] | C14: OCE__CallItem__c | D14: 01I3X000001zXyY.00N3X00000ML0H8 | E14: Value | F14: Value__c | G14: Number(16, 2) | J14: 0 | K14: 18 | L14: double | M14: false | N14: true | O14: false | P14: false | Q14: false | R14: false
A15: [FieldDefinition] | B15: [EntityDefinition] | C15: OCE__CallItem__c | D15: 01I3X000001zXyY.00N3X00000ML0H7 | E15: Interaction Status | F15: RCH_Call_Status__c | G15: Formula (Text) | J15: 1300 | K15: 0 | L15: string | M15: false | N15: true | O15: false | P15: false | Q15: false | R15: true | S15: Status of the Parent Call
A16: [FieldDefinition] | B16: [EntityDefinition] | C16: OCE__CallItem__c | D16: 01I3X000001zXyY.00N3X00000JUTxF | E16: Unique Integration ID | F16: OCE__UniqueIntegrationID__c | G16: Text(100) (External ID) (Unique Case Sensitive) | J16: 100 | K16: 0 | L16: string | M16: true | N16: true | O16: false | P16: false | Q16: false | R16: false | S16: Unique External ID which is used for data loading only.
A17: [FieldDefinition] | B17: [EntityDefinition] | C17: OCE__CallItem__c | D17: 01I3X000001zXyY.00N3X00000JUTxE | E17: Qty | F17: OCE__Quantity__c | G17: Number(18, 0) | J17: 0 | K17: 18 | L17: double | M17: false | N17: false | O17: false | P17: false | Q17: false | R17: false | S17: The number of Promotional Items disbursed
A18: [FieldDefinition] | B18: [EntityDefinition] | C18: OCE__CallItem__c | D18: 01I3X000001zXyY.00N3X00000JUTxD | E18: Product | F18: OCE__Product__c | G18: Lookup(Product) | H18: OCE__Product__r | J18: 18 | K18: 0 | L18: id | M18: true | N18: true | O18: false | P18: false | Q18: false | R18: false | S18: The Product associated with the CallItem
A19: [FieldDefinition] | B19: [EntityDefinition] | C19: OCE__CallItem__c | D19: 01I3X000001zXyY.00N3X00000JUTxC | E19: Product Ref Data | F19: OCE__ProductRefData__c | G19: Text(255) | J19: 255 | K19: 0 | L19: string | M19: false | N19: true | O19: false | P19: false | Q19: false | R19: false | S19: Denormalized product name.
A20: [FieldDefinition] | B20: [EntityDefinition] | C20: OCE__CallItem__c | D20: 01I3X000001zXyY.00N3X00000JUTxB | E20: Offline Unique Id | F20: OCE__OfflineUniqueId__c | G20: Text(255) (External ID) | J20: 255 | K20: 0 | L20: string | M20: true | N20: true | O20: false | P20: false | Q20: false | R20: false | S20: Globally unique string that identifies an offline created record.
A21: [FieldDefinition] | B21: [EntityDefinition] | C21: OCE__CallItem__c | D21: 01I3X000001zXyY.00N3X00000JUTxA | E21: Offline Last Modified Date | F21: OCE__OfflineLastModifiedDate__c | G21: Date/Time | J21: 0 | K21: 0 | L21: datetime | M21: false | N21: true | O21: false | P21: false | Q21: false | R21: false | S21: Offline Last Modified Date
A22: [FieldDefinition] | B22: [EntityDefinition] | C22: OCE__CallItem__c | D22: 01I3X000001zXyY.00N3X00000JUTx9 | E22: Offline Last Modified By Id | F22: OCE__OfflineLastModifiedByID__c | G22: Lookup(User) | H22: OCE__OfflineLastModifiedByID__r | J22: 18 | K22: 0 | L22: id | M22: true | N22: true | O22: false | P22: false | Q22: false | R22: false | S22: Offline Last Modified By ID
A23: [FieldDefinition] | B23: [EntityDefinition] | C23: OCE__CallItem__c | D23: 01I3X000001zXyY.00N3X00000JUTx8 | E23: Offline Created Date | F23: OCE__OfflineCreatedDate__c | G23: Date/Time | J23: 0 | K23: 0 | L23: datetime | M23: false | N23: true | O23: false | P23: false | Q23: false | R23: false | S23: Offline Created Date
A24: [FieldDefinition] | B24: [EntityDefinition] | C24: OCE__CallItem__c | D24: 01I3X000001zXyY.00N3X00000JUTx7 | E24: Offline Created By Id | F24: OCE__OfflineCreatedByID__c | G24: Lookup(User) | H24: OCE__OfflineCreatedByID__r | J24: 18 | K24: 0 | L24: id | M24: true | N24: true | O24: false | P24: false | Q24: false | R24: false | S24: Offline Created By ID
A25: [FieldDefinition] | B25: [EntityDefinition] | C25: OCE__CallItem__c | D25: 01I3X000001zXyY.00N3X00000JUTx6 | E25: Item | F25: OCE__Item__c | G25: Lookup(Product) | H25: OCE__Item__r | J25: 18 | K25: 0 | L25: id | M25: true | N25: true | O25: false | P25: false | Q25: false | R25: false | S25: The name of the Product for which Item being disbursed. This is used to link a Product to a Call Item.
A26: [FieldDefinition] | B26: [EntityDefinition] | C26: OCE__CallItem__c | D26: 01I3X000001zXyY.00N3X00000JUTx5 | E26: Item Ref Data | F26: OCE__ItemRefData__c | G26: Text(255) | J26: 255 | K26: 0 | L26: string | M26: false | N26: true | O26: false | P26: false | Q26: false | R26: false | S26: Denormalized product name.
A27: [FieldDefinition] | B27: [EntityDefinition] | C27: OCE__CallItem__c | D27: 01I3X000001zXyY.00N3X00000JUTx4 | E27: Is Signature Captured? | F27: OCE__IsSignatureCaptured__c | G27: Checkbox | J27: 0 | K27: 0 | L27: boolean | M27: false | N27: false | O27: false | P27: false | Q27: false | R27: false | S27: Track if record was on call on sign.
A28: [FieldDefinition] | B28: [EntityDefinition] | C28: OCE__CallItem__c | D28: 01I3X000001zXyY.00N3X00000JUTx3 | E28: Integration Id | F28: OCE__IntegrationId__c | G28: Text(100) | J28: 100 | K28: 0 | L28: string | M28: false | N28: true | O28: false | P28: false | Q28: false | R28: false | S28: External ID which is used for data loading only.
A29: [FieldDefinition] | B29: [EntityDefinition] | C29: OCE__CallItem__c | D29: 01I3X000001zXyY.00N3X00000JUTx2 | E29: Interaction | F29: OCE__Call__c | G29: Lookup(Interaction) | H29: OCE__Call__r | J29: 18 | K29: 0 | L29: id | M29: true | N29: false | O29: false | P29: false | Q29: false | R29: false | S29: The Call associated with the CallItem
A30: [FieldDefinition] | B30: [EntityDefinition] | C30: OCE__CallItem__c | D30: 01I3X000001zXyY.00N3X00000JUTx1 | E30: Interaction Ref Data | F30: OCE__CallRefData__c | G30: Text(255) | J30: 255 | K30: 0 | L30: string | M30: false | N30: true | O30: false | P30: false | Q30: false | R30: false | S30: Denormalized call name.
A31: [FieldDefinition] | B31: [EntityDefinition] | C31: OCE__CallItem__c | D31: 01I3X000001zXyY.00N3X00000JUTx0 | E31: Account | F31: OCE__Account__c | G31: Lookup(Account) | H31: OCE__Account__r | J31: 18 | K31: 0 | L31: id | M31: true | N31: true | O31: false | P31: false | Q31: false | R31: false | S31: The Account for which the Item was disbursed. This is used to link an Account to a Call Item.
A32: [FieldDefinition] | B32: [EntityDefinition] | C32: OCE__CallItem__c | D32: 01I3X000001zXyY.00N3X00000JUTwz | E32: Account Territories | F32: OCE__AccountTerritories__c | G32: Text(255) | J32: 255 | K32: 0 | L32: string | M32: false | N32: true | O32: false | P32: false | Q32: false | R32: false | S32: Territories associated with Account.
A33: [FieldDefinition] | B33: [EntityDefinition] | C33: OCE__CallItem__c | D33: 01I3X000001zXyY.00N3X00000JUTwy | E33: Account Ref Data | F33: OCE__AccountRefData__c | G33: Text(255) | J33: 255 | K33: 0 | L33: string | M33: false | N33: true | O33: false | P33: false | Q33: false | R33: false | S33: Denormalized account name.
A34: [FieldDefinition] | B34: [EntityDefinition] | C34: OCE__CallExpense__c | D34: 01I3X000001zXyX.UserRecordAccess | E34: Object Access Level | F34: UserRecordAccessId | G34: Lookup(User Record Access) | H34: UserRecordAccess | J34: 18 | K34: 0 | L34: id | M34: false | N34: true | O34: false | P34: false | Q34: false | R34: false
A35: [FieldDefinition] | B35: [EntityDefinition] | C35: OCE__CallExpense__c | D35: 01I3X000001zXyX.SystemModstamp | E35: System Modstamp | F35: SystemModstamp | G35: Date/Time | J35: 0 | K35: 0 | L35: datetime | M35: true | N35: false | O35: false | P35: false | Q35: false | R35: false
A36: [FieldDefinition] | B36: [EntityDefinition] | C36: OCE__CallExpense__c | D36: 01I3X000001zXyX.Owner | E36: Owner | F36: OwnerId | G36: Lookup(User,Group) | H36: Owner | J36: 18 | K36: 0 | L36: id | M36: true | N36: false | O36: false | P36: false | Q36: false | R36: false
A37: [FieldDefinition] | B37: [EntityDefinition] | C37: OCE__CallExpense__c | D37: 01I3X000001zXyX.Name | E37: Interaction Expense Name | F37: Name | G37: Auto Number | J37: 80 | K37: 0 | L37: string | M37: true | N37: false | O37: false | P37: false | Q37: false | R37: false
A38: [FieldDefinition] | B38: [EntityDefinition] | C38: OCE__CallExpense__c | D38: 01I3X000001zXyX.LastModifiedDate | E38: Last Modified Date | F38: LastModifiedDate | G38: Date/Time | J38: 0 | K38: 0 | L38: datetime | M38: false | N38: false | O38: false | P38: false | Q38: false | R38: false
A39: [FieldDefinition] | B39: [EntityDefinition] | C39: OCE__CallExpense__c | D39: 01I3X000001zXyX.LastModifiedBy | E39: Last Modified By | F39: LastModifiedById | G39: Lookup(User) | H39: LastModifiedBy | J39: 18 | K39: 0 | L39: id | M39: false | N39: false | O39: false | P39: false | Q39: false | R39: false
A40: [FieldDefinition] | B40: [EntityDefinition] | C40: OCE__CallExpense__c | D40: 01I3X000001zXyX.LastActivityDate | E40: Last Activity Date | F40: LastActivityDate | G40: Date | J40: 0 | K40: 0 | L40: date | M40: false | N40: true | O40: false | P40: false | Q40: false | R40: false
A41: [FieldDefinition] | B41: [EntityDefinition] | C41: OCE__CallExpense__c | D41: 01I3X000001zXyX.IsDeleted | E41: Deleted | F41: IsDeleted | G41: Checkbox | J41: 0 | K41: 0 | L41: boolean | M41: true | N41: false | O41: false | P41: false | Q41: false | R41: false
A42: [FieldDefinition] | B42: [EntityDefinition] | C42: OCE__CallExpense__c | D42: 01I3X000001zXyX.Id | E42: Record ID | F42: Id | G42: Lookup() | J42: 18 | K42: 0 | L42: id | M42: true | N42: false | O42: false | P42: false | Q42: false | R42: false
A43: [FieldDefinition] | B43: [EntityDefinition] | C43: OCE__CallExpense__c | D43: 01I3X000001zXyX.CurrencyIsoCode | E43: Currency | F43: CurrencyIsoCode | G43: Picklist | J43: 3 | K43: 0 | L43: string | M43: false | N43: true | O43: false | P43: false | Q43: false | R43: false
A44: [FieldDefinition] | B44: [EntityDefinition] | C44: OCE__CallExpense__c | D44: 01I3X000001zXyX.CreatedDate | E44: Created Date | F44: CreatedDate | G44: Date/Time | J44: 0 | K44: 0 | L44: datetime | M44: true | N44: false | O44: false | P44: false | Q44: false | R44: false
A45: [FieldDefinition] | B45: [EntityDefinition] | C45: OCE__CallExpense__c | D45: 01I3X000001zXyX.CreatedBy | E45: Created By | F45: CreatedById | G45: Lookup(User) | H45: CreatedBy | J45: 18 | K45: 0 | L45: id | M45: false | N45: false | O45: false | P45: false | Q45: false | R45: false
A46: [FieldDefinition] | B46: [EntityDefinition] | C46: OCE__CallExpense__c | D46: 01I3X000001zXyX.00N3X00000JUTwx | E46: Unique Integration ID | F46: OCE__UniqueIntegrationID__c | G46: Text(100) (External ID) (Unique Case Sensitive) | J46: 100 | K46: 0 | L46: string | M46: true | N46: true | O46: false | P46: false | Q46: false | R46: false | S46: Unique External ID which is used for data loading only.
A47: [FieldDefinition] | B47: [EntityDefinition] | C47: OCE__CallExpense__c | D47: 01I3X000001zXyX.00N3X00000JUTww | E47: Type | F47: OCE__Type__c | G47: Picklist | J47: 255 | K47: 0 | L47: string | M47: false | N47: true | O47: false | P47: false | Q47: false | R47: false | S47: The type of Call Expense, such as Food, Entertainment, Transportation, etc. This is used to understand what the Expense was incurred for.
A48: [FieldDefinition] | B48: [EntityDefinition] | C48: OCE__CallExpense__c | D48: 01I3X000001zXyX.00N3X00000JUTwv | E48: Product | F48: OCE__Product__c | G48: Lookup(Product) | H48: OCE__Product__r | J48: 18 | K48: 0 | L48: id | M48: true | N48: true | O48: false | P48: false | Q48: false | R48: false | S48: Product that is related to the Expense
A49: [FieldDefinition] | B49: [EntityDefinition] | C49: OCE__CallExpense__c | D49: 01I3X000001zXyX.00N3X00000JUTwt | E49: Offline Unique Id | F49: OCE__OfflineUniqueId__c | G49: Text(255) (External ID) | J49: 255 | K49: 0 | L49: string | M49: true | N49: true | O49: false | P49: false | Q49: false | R49: false | S49: Globally unique string that identifies an offline created record.
A50: [FieldDefinition] | B50: [EntityDefinition] | C50: OCE__CallExpense__c | D50: 01I3X000001zXyX.00N3X00000JUTws | E50: Offline Last Modified Date | F50: OCE__OfflineLastModifiedDate__c | G50: Date/Time | J50: 0 | K50: 0 | L50: datetime | M50: false | N50: true | O50: false | P50: false | Q50: false | R50: false | S50: Offline Last Modified Date
A51: [FieldDefinition] | B51: [EntityDefinition] | C51: OCE__CallExpense__c | D51: 01I3X000001zXyX.00N3X00000JUTwr | E51: Offline Last Modified By Id | F51: OCE__OfflineLastModifiedByID__c | G51: Lookup(User) | H51: OCE__OfflineLastModifiedByID__r | J51: 18 | K51: 0 | L51: id | M51: true | N51: true | O51: false | P51: false | Q51: false | R51: false | S51: Offline Last Modified By ID
A52: [FieldDefinition] | B52: [EntityDefinition] | C52: OCE__CallExpense__c | D52: 01I3X000001zXyX.00N3X00000JUTwq | E52: Offline Created Date | F52: OCE__OfflineCreatedDate__c | G52: Date/Time | J52: 0 | K52: 0 | L52: datetime | M52: false | N52: true | O52: false | P52: false | Q52: false | R52: false | S52: Offline Created Date
A53: [FieldDefinition] | B53: [EntityDefinition] | C53: OCE__CallExpense__c | D53: 01I3X000001zXyX.00N3X00000JUTwp | E53: Offline Created By Id | F53: OCE__OfflineCreatedByID__c | G53: Lookup(User) | H53: OCE__OfflineCreatedByID__r | J53: 18 | K53: 0 | L53: id | M53: true | N53: true | O53: false | P53: false | Q53: false | R53: false | S53: Offline Created By ID
A54: [FieldDefinition] | B54: [EntityDefinition] | C54: OCE__CallExpense__c | D54: 01I3X000001zXyX.00N3X00000JUTwo | E54: Notes | F54: OCE__Notes__c | G54: Text(255) | J54: 255 | K54: 0 | L54: string | M54: false | N54: true | O54: false | P54: false | Q54: false | R54: false | S54: Any relevant notes about the Expense.
A55: [FieldDefinition] | B55: [EntityDefinition] | C55: OCE__CallExpense__c | D55: 01I3X000001zXyX.00N3X00000JUTwm | E55: Integration Id | F55: OCE__IntegrationId__c | G55: Text(100) | J55: 100 | K55: 0 | L55: string | M55: false | N55: true | O55: false | P55: false | Q55: false | R55: false | S55: External ID which is used for data loading only.
A56: [FieldDefinition] | B56: [EntityDefinition] | C56: OCE__CallExpense__c | D56: 01I3X000001zXyX.00N3X00000JUTwl | E56: Full Amount | F56: OCE__FullAmount__c | G56: Currency(16, 2) | J56: 0 | K56: 18 | L56: double | M56: false | N56: true | O56: false | P56: false | Q56: false | R56: false | S56: The amount of Expense associated with all persons on single Type of single Product
A57: [FieldDefinition] | B57: [EntityDefinition] | C57: OCE__CallExpense__c | D57: 01I3X000001zXyX.00N3X00000JUTwk | E57: Date | F57: OCE__Date__c | G57: Formula (Date) | J57: 0 | K57: 0 | L57: date | M57: false | N57: true | O57: false | P57: false | Q57: false | R57: true | S57: The field shows date of the related parent Call
A58: [FieldDefinition] | B58: [EntityDefinition] | C58: OCE__CallExpense__c | D58: 01I3X000001zXyX.00N3X00000JUTwj | E58: Interaction | F58: OCE__Call__c | G58: Lookup(Interaction) | H58: OCE__Call__r | J58: 18 | K58: 0 | L58: id | M58: true | N58: false | O58: false | P58: false | Q58: false | R58: false | S58: The Call for which the Expense is reported
A59: [FieldDefinition] | B59: [EntityDefinition] | C59: OCE__CallExpense__c | D59: 01I3X000001zXyX.00N3X00000JUTwh | E59: Account | F59: OCE__CallExpenseAccount__c | G59: Lookup(Account) | H59: OCE__CallExpenseAccount__r | J59: 18 | K59: 0 | L59: id | M59: true | N59: true | O59: false | P59: false | Q59: false | R59: false | S59: The Account the Call was made on. This is used to tie a specific Account to the Call.
A60: [FieldDefinition] | B60: [EntityDefinition] | C60: OCE__CallExpense__c | D60: 01I3X000001zXyX.00N3X00000JUTwf | E60: Account Territories | F60: OCE__AccountTerritories__c | G60: Text(255) | J60: 255 | K60: 0 | L60: string | M60: false | N60: true | O60: false | P60: false | Q60: false | R60: false | S60: Territories associated with Account.
A61: [FieldDefinition] | B61: [EntityDefinition] | C61: OCE__CallEmployeeAttendee__c | D61: 01I3X000001zXyV.UserRecordAccess | E61: Object Access Level | F61: UserRecordAccessId | G61: Lookup(User Record Access) | H61: UserRecordAccess | J61: 18 | K61: 0 | L61: id | M61: false | N61: true | O61: false | P61: false | Q61: false | R61: false
A62: [FieldDefinition] | B62: [EntityDefinition] | C62: OCE__CallEmployeeAttendee__c | D62: 01I3X000001zXyV.SystemModstamp | E62: System Modstamp | F62: SystemModstamp | G62: Date/Time | J62: 0 | K62: 0 | L62: datetime | M62: true | N62: false | O62: false | P62: false | Q62: false | R62: false
A63: [FieldDefinition] | B63: [EntityDefinition] | C63: OCE__CallEmployeeAttendee__c | D63: 01I3X000001zXyV.Owner | E63: Owner | F63: OwnerId | G63: Lookup(User,Group) | H63: Owner | J63: 18 | K63: 0 | L63: id | M63: true | N63: false | O63: false | P63: false | Q63: false | R63: false
A64: [FieldDefinition] | B64: [EntityDefinition] | C64: OCE__CallEmployeeAttendee__c | D64: 01I3X000001zXyV.Name | E64: Interaction Employee Name | F64: Name | G64: Auto Number | J64: 80 | K64: 0 | L64: string | M64: true | N64: false | O64: false | P64: false | Q64: false | R64: false
A65: [FieldDefinition] | B65: [EntityDefinition] | C65: OCE__CallEmployeeAttendee__c | D65: 01I3X000001zXyV.LastModifiedDate | E65: Last Modified Date | F65: LastModifiedDate | G65: Date/Time | J65: 0 | K65: 0 | L65: datetime | M65: false | N65: false | O65: false | P65: false | Q65: false | R65: false
A66: [FieldDefinition] | B66: [EntityDefinition] | C66: OCE__CallEmployeeAttendee__c | D66: 01I3X000001zXyV.LastModifiedBy | E66: Last Modified By | F66: LastModifiedById | G66: Lookup(User) | H66: LastModifiedBy | J66: 18 | K66: 0 | L66: id | M66: false | N66: false | O66: false | P66: false | Q66: false | R66: false
A67: [FieldDefinition] | B67: [EntityDefinition] | C67: OCE__CallEmployeeAttendee__c | D67: 01I3X000001zXyV.IsDeleted | E67: Deleted | F67: IsDeleted | G67: Checkbox | J67: 0 | K67: 0 | L67: boolean | M67: true | N67: false | O67: false | P67: false | Q67: false | R67: false
A68: [FieldDefinition] | B68: [EntityDefinition] | C68: OCE__CallEmployeeAttendee__c | D68: 01I3X000001zXyV.Id | E68: Record ID | F68: Id | G68: Lookup() | J68: 18 | K68: 0 | L68: id | M68: true | N68: false | O68: false | P68: false | Q68: false | R68: false
A69: [FieldDefinition] | B69: [EntityDefinition] | C69: OCE__CallEmployeeAttendee__c | D69: 01I3X000001zXyV.CurrencyIsoCode | E69: Currency | F69: CurrencyIsoCode | G69: Picklist | J69: 3 | K69: 0 | L69: string | M69: false | N69: true | O69: false | P69: false | Q69: false | R69: false
A70: [FieldDefinition] | B70: [EntityDefinition] | C70: OCE__CallEmployeeAttendee__c | D70: 01I3X000001zXyV.CreatedDate | E70: Created Date | F70: CreatedDate | G70: Date/Time | J70: 0 | K70: 0 | L70: datetime | M70: true | N70: false | O70: false | P70: false | Q70: false | R70: false
A71: [FieldDefinition] | B71: [EntityDefinition] | C71: OCE__CallEmployeeAttendee__c | D71: 01I3X000001zXyV.CreatedBy | E71: Created By | F71: CreatedById | G71: Lookup(User) | H71: CreatedBy | J71: 18 | K71: 0 | L71: id | M71: false | N71: false | O71: false | P71: false | Q71: false | R71: false
A72: [FieldDefinition] | B72: [EntityDefinition] | C72: OCE__CallEmployeeAttendee__c | D72: 01I3X000001zXyV.00N3X00000ML0H6 | E72: OCE Attendee Email | F72: RCH_gCal_OCE_Attendee_Email__c | G72: Formula (Text) | J72: 1300 | K72: 0 | L72: string | M72: false | N72: true | O72: false | P72: false | Q72: false | R72: true
A73: [FieldDefinition] | B73: [EntityDefinition] | C73: OCE__CallEmployeeAttendee__c | D73: 01I3X000001zXyV.00N3X00000ML0H5 | E73: gCal Attendee External Id | F73: RCH_gCal_Attendee_External_Id__c | G73: Text(250) | J73: 250 | K73: 0 | L73: string | M73: false | N73: true | O73: false | P73: false | Q73: false | R73: false
A74: [FieldDefinition] | B74: [EntityDefinition] | C74: OCE__CallEmployeeAttendee__c | D74: 01I3X000001zXyV.00N3X00000ML0H4 | E74: gCal Attendee Email | F74: RCH_gCal_Attendee_Email__c | G74: Text(100) | J74: 100 | K74: 0 | L74: string | M74: false | N74: true | O74: false | P74: false | Q74: false | R74: false
A75: [FieldDefinition] | B75: [EntityDefinition] | C75: OCE__CallEmployeeAttendee__c | D75: 01I3X000001zXyV.00N3X00000JUTwU | E75: Attendee Employee | F75: OCE__User__c | G75: Lookup(User) | H75: OCE__User__r | J75: 18 | K75: 0 | L75: id | M75: true | N75: true | O75: false | P75: false | Q75: false | R75: false | S75: The employee that is attending the Call with SalesRep, usually SalesReps manager .
A76: [FieldDefinition] | B76: [EntityDefinition] | C76: OCE__CallEmployeeAttendee__c | D76: 01I3X000001zXyV.00N3X00000JUTwS | E76: Unique Integration Id | F76: OCE__UniqueIntegrationId__c | G76: Text(100) (External ID) (Unique Case Insensitive) | J76: 100 | K76: 0 | L76: string | M76: true | N76: true | O76: false | P76: false | Q76: false | R76: false | S76: External ID which is used for data loading only.
A77: [FieldDefinition] | B77: [EntityDefinition] | C77: OCE__CallEmployeeAttendee__c | D77: 01I3X000001zXyV.00N3X00000JUTwR | E77: Offline Unique Id | F77: OCE__OfflineUniqueId__c | G77: Text(100) (External ID) | J77: 100 | K77: 0 | L77: string | M77: true | N77: true | O77: false | P77: false | Q77: false | R77: false | S77: Globally unique string that identifies an offline created record.
A78: [FieldDefinition] | B78: [EntityDefinition] | C78: OCE__CallEmployeeAttendee__c | D78: 01I3X000001zXyV.00N3X00000JUTwQ | E78: Offline Last Modified Date | F78: OCE__OfflineLastModifiedDate__c | G78: Date/Time | J78: 0 | K78: 0 | L78: datetime | M78: false | N78: true | O78: false | P78: false | Q78: false | R78: false | S78: Date and time when this record was last modified by a User offline.
A79: [FieldDefinition] | B79: [EntityDefinition] | C79: OCE__CallEmployeeAttendee__c | D79: 01I3X000001zXyV.00N3X00000JUTwP | E79: Offline Last Modified By Id | F79: OCE__OfflineLastModifiedByID__c | G79: Lookup(User) | H79: OCE__OfflineLastModifiedByID__r | J79: 18 | K79: 0 | L79: id | M79: true | N79: true | O79: false | P79: false | Q79: false | R79: false | S79: ID of the User who last updated this record offline.
A80: [FieldDefinition] | B80: [EntityDefinition] | C80: OCE__CallEmployeeAttendee__c | D80: 01I3X000001zXyV.00N3X00000JUTwO | E80: Offline Created Date | F80: OCE__OfflineCreatedDate__c | G80: Date/Time | J80: 0 | K80: 0 | L80: datetime | M80: false | N80: true | O80: false | P80: false | Q80: false | R80: false | S80: Date and time when this record was created offline.
A81: [FieldDefinition] | B81: [EntityDefinition] | C81: OCE__CallEmployeeAttendee__c | D81: 01I3X000001zXyV.00N3X00000JUTwN | E81: Offline Created By Id | F81: OCE__OfflineCreatedByID__c | G81: Lookup(User) | H81: OCE__OfflineCreatedByID__r | J81: 18 | K81: 0 | L81: id | M81: true | N81: true | O81: false | P81: false | Q81: false | R81: false | S81: ID of the User who created this record offline.
A82: [FieldDefinition] | B82: [EntityDefinition] | C82: OCE__CallEmployeeAttendee__c | D82: 01I3X000001zXyV.00N3X00000JUTwL | E82: Interaction | F82: OCE__Call__c | G82: Lookup(Interaction) | H82: OCE__Call__r | J82: 18 | K82: 0 | L82: id | M82: true | N82: true | O82: false | P82: false | Q82: false | R82: false | S82: Lookup to Call object.
A83: [FieldDefinition] | B83: [EntityDefinition] | C83: OCE__CallDialogue__c | D83: 01I3X000001zXyS.UserRecordAccess | E83: Object Access Level | F83: UserRecordAccessId | G83: Lookup(User Record Access) | H83: UserRecordAccess | J83: 18 | K83: 0 | L83: id | M83: false | N83: true | O83: false | P83: false | Q83: false | R83: false
A84: [FieldDefinition] | B84: [EntityDefinition] | C84: OCE__CallDialogue__c | D84: 01I3X000001zXyS.SystemModstamp | E84: System Modstamp | F84: SystemModstamp | G84: Date/Time | J84: 0 | K84: 0 | L84: datetime | M84: true | N84: false | O84: false | P84: false | Q84: false | R84: false
A85: [FieldDefinition] | B85: [EntityDefinition] | C85: OCE__CallDialogue__c | D85: 01I3X000001zXyS.Owner | E85: Owner | F85: OwnerId | G85: Lookup(User,Group) | H85: Owner | J85: 18 | K85: 0 | L85: id | M85: true | N85: false | O85: false | P85: false | Q85: false | R85: false
A86: [FieldDefinition] | B86: [EntityDefinition] | C86: OCE__CallDialogue__c | D86: 01I3X000001zXyS.Name | E86: Interaction Dialogue Name | F86: Name | G86: Auto Number | J86: 80 | K86: 0 | L86: string | M86: true | N86: false | O86: false | P86: false | Q86: false | R86: false
A87: [FieldDefinition] | B87: [EntityDefinition] | C87: OCE__CallDialogue__c | D87: 01I3X000001zXyS.LastModifiedDate | E87: Last Modified Date | F87: LastModifiedDate | G87: Date/Time | J87: 0 | K87: 0 | L87: datetime | M87: false | N87: false | O87: false | P87: false | Q87: false | R87: false
A88: [FieldDefinition] | B88: [EntityDefinition] | C88: OCE__CallDialogue__c | D88: 01I3X000001zXyS.LastModifiedBy | E88: Last Modified By | F88: LastModifiedById | G88: Lookup(User) | H88: LastModifiedBy | J88: 18 | K88: 0 | L88: id | M88: false | N88: false | O88: false | P88: false | Q88: false | R88: false
A89: [FieldDefinition] | B89: [EntityDefinition] | C89: OCE__CallDialogue__c | D89: 01I3X000001zXyS.LastActivityDate | E89: Last Activity Date | F89: LastActivityDate | G89: Date | J89: 0 | K89: 0 | L89: date | M89: false | N89: true | O89: false | P89: false | Q89: false | R89: false
A90: [FieldDefinition] | B90: [EntityDefinition] | C90: OCE__CallDialogue__c | D90: 01I3X000001zXyS.IsDeleted | E90: Deleted | F90: IsDeleted | G90: Checkbox | J90: 0 | K90: 0 | L90: boolean | M90: true | N90: false | O90: false | P90: false | Q90: false | R90: false
A91: [FieldDefinition] | B91: [EntityDefinition] | C91: OCE__CallDialogue__c | D91: 01I3X000001zXyS.Id | E91: Record ID | F91: Id | G91: Lookup() | J91: 18 | K91: 0 | L91: id | M91: true | N91: false | O91: false | P91: false | Q91: false | R91: false
A92: [FieldDefinition] | B92: [EntityDefinition] | C92: OCE__CallDialogue__c | D92: 01I3X000001zXyS.CurrencyIsoCode | E92: Currency | F92: CurrencyIsoCode | G92: Picklist | J92: 3 | K92: 0 | L92: string | M92: false | N92: true | O92: false | P92: false | Q92: false | R92: false
A93: [FieldDefinition] | B93: [EntityDefinition] | C93: OCE__CallDialogue__c | D93: 01I3X000001zXyS.CreatedDate | E93: Created Date | F93: CreatedDate | G93: Date/Time | J93: 0 | K93: 0 | L93: datetime | M93: true | N93: false | O93: false | P93: false | Q93: false | R93: false
A94: [FieldDefinition] | B94: [EntityDefinition] | C94: OCE__CallDialogue__c | D94: 01I3X000001zXyS.CreatedBy | E94: Created By | F94: CreatedById | G94: Lookup(User) | H94: CreatedBy | J94: 18 | K94: 0 | L94: id | M94: false | N94: false | O94: false | P94: false | Q94: false | R94: false
A95: [FieldDefinition] | B95: [EntityDefinition] | C95: OCE__CallDialogue__c | D95: 01I3X000001zXyS.00N3X00000JUTvZ | E95: Offline Created Date | F95: OCE__OfflineCreatedDate__c | G95: Date/Time | J95: 0 | K95: 0 | L95: datetime | M95: false | N95: true | O95: false | P95: false | Q95: false | R95: false | S95: Date and time when this record was created offline.
A96: [FieldDefinition] | B96: [EntityDefinition] | C96: OCE__CallDialogue__c | D96: 01I3X000001zXyS.00N3X00000JUTvX | E96: Is Deleted Offline | F96: OCE__IsDeletedOffline__c | G96: Checkbox | J96: 0 | K96: 0 | L96: boolean | M96: false | N96: false | O96: false | P96: false | Q96: false | R96: false | S96: Indicates whether the record has been deleted offline or not.
A97: [FieldDefinition] | B97: [EntityDefinition] | C97: OCE__CallDialogue__c | D97: 01I3X000001zXyS.00N3X00000JUTvW | E97: Interaction | F97: OCE__Call__c | G97: Lookup(Interaction) | H97: OCE__Call__r | J97: 18 | K97: 0 | L97: id | M97: true | N97: true | O97: false | P97: false | Q97: false | R97: false | S97: Lookup to Call object.
A98: [FieldDefinition] | B98: [EntityDefinition] | C98: OCE__CallDialogue__c | D98: 01I3X000001zXyS.00N3X00000JUTvU | E98: Interaction Detail | F98: OCE__CallDetail__c | G98: Lookup(Interaction Detail) | H98: OCE__CallDetail__r | J98: 18 | K98: 0 | L98: id | M98: true | N98: true | O98: false | P98: false | Q98: false | R98: false | S98: Lookup to Call Detail object.
A99: [FieldDefinition] | B99: [EntityDefinition] | C99: OCE__CallDialogue__c | D99: 01I3X000001zXyS.00N3X00000JUTvS | E99: Account | F99: OCE__Account__c | G99: Lookup(Account) | H99: OCE__Account__r | J99: 18 | K99: 0 | L99: id | M99: true | N99: true | O99: false | P99: false | Q99: false | R99: false | S99: The Account the Call was made on. This is used to tie a specific Account to the Call.
A100: [FieldDefinition] | B100: [EntityDefinition] | C100: OCE__CallDialogue__c | D100: 01I3X000001zXyS.00N3X00000JUTvR | E100: Account Territories | F100: OCE__AccountTerritories__c | G100: Text(255) | J100: 255 | K100: 0 | L100: string | M100: false | N100: true | O100: false | P100: false | Q100: false | R100: false | S100: Territories associated with Account.
...

Sheet TGT - Vault CRM Object Fields
A1: Object Name | B1: Object Label | C1: Field Name | D1: Field Label | E1: Field Type | F1: Field Description
A2: call2__v | B2: Call | C2: account__v | D2: Account | E2: Object | F2: Lookup to the account that the call is associated with.
A3: call2__v | B3: Call | C3: account_credentials__v | D3: Credentials | E3: Picklist
A4: call2__v | B4: Call | C4: account_identifier__v | D4: Account Identifier | E4: String
A5: call2__v | B5: Call | C5: account_plan__v | D5: Account Plan | E5: Object | F5: Lookup to account plan associated with this call. This field is optional.
A6: call2__v | B6: Call | C6: add_detail__v | D6: Add Detail | E6: LongText | F6: Field used to assist in the creation of Call2 Detail records to a Call2 record. The 18-digit Product Ids are ordered from left to right and are comma-delimited. The field will be blanked out after each save. A trigger on Call2 Header will parse the delim
A7: call2__v | B7: Call | C7: add_key_message__v | D7: Add Key Message | E7: LongText | F7: Field used to assist in the creation of Call2 Key Message records for a Call2 record. Input format is a list delimited by ";;;" of the following five fields (the last two, though, are optional) that are separated by "@@" - <Key_Message_ID>@@<Product_ID>@@
A8: call2__v | B8: Call | C8: address__v | D8: Address | E8: LongText | F8: A field used to denormalize the address information associated with a call. This aids in data loading and displaying information on related lists.
A9: call2__v | B9: Call | C9: address_line_1__v | D9: Address Line 1 | E9: String | F9: Address Line 1 of the Call Address. This field should not be displayed on the Page Layout.
A10: call2__v | B10: Call | C10: address_line_2__v | D10: Address Line 2 | E10: String | F10: Address Line 2 of the Call Address. This field should not be displayed on the Page Layout.
A11: call2__v | B11: Call | C11: allowed_products__v | D11: Allowed Products | E11: LongText
A12: call2__v | B12: Call | C12: assigner__v | D12: Assigner | E12: Object
A13: call2__v | B13: Call | C13: assignment_datetime__v | D13: Assignment Datetime | E13: DateTime
A14: call2__v | B14: Call | C14: assmca__v | D14: ASSMCA | E14: String | F14: The ASSMCA # is a license number when sampling controlled substances for a Puerto Rican-based Physician.
A15: call2__v | B15: Call | C15: attendee_list__v | D15: Other Non-HCP Attendees | E15: LongText | F15: This text field is a semi colon delimited list of Non-HCP attendees who were on this call. This text field can be displayed in Concur so that the User can then match to other Non-HCPs later.
A16: call2__v | B16: Call | C16: attendee_post_status__v | D16: Attendee Post Status | E16: String | F16: This field was included as an option in v14. It is no longer being utilized in the current version of the integration and is not part of the standard connector.
A17: call2__v | B17: Call | C17: attendee_type__v | D17: Attendee Type | E17: Picklist | F17: The type of entity who the call is created for. This field is used in reporting. For performance reasons, this is not set by an APEX trigger. For data import, this field should be set correctly otherwise reports that depend on this field may not run corr
A18: call2__v | B18: Call | C18: attendees__v | D18: Attendees | E18: Number | F18: The total number of attendees for this call. For a group call with four doctors, this would be "3" for the parent call associated to the parent account and "0" for the child calls. For performance reasons, this is not set via a trigger.
A19: call2__v | B19: Call | C19: call2_status__v | D19: Call Status | E19: Picklist
A20: call2__v | B20: Call | C20: call_channel__v | D20: Channel | E20: Picklist | F20: Specifies the channel of communication for this interaction.
A21: call2__v | B21: Call | C21: call_channel_formula__v | D21: Call Channel Formula | E21: String | F21: If a user has read FLS to this formula field, the result of the formula auto-populates call_channel__v. To use, replace OOTB formula with custom formula.
A22: call2__v | B22: Call | C22: call_comments__v | D22: Comments | E22: LongText | F22: Free text comments for call.
A23: call2__v | B23: Call | C23: call_date__v | D23: Date | E23: Date | F23: The date of the call when it was first saved or submitted. This field is set via a trigger to the current date if neither the date or datetime field is supplied.
A24: call2__v | B24: Call | C24: call_datetime__v | D24: Datetime | E24: DateTime | F24: The time when the rep specified for the call unless the call was signed, in which case this is the signature time. This field is optional for users who which to plan their calls down to a specific hour or minute. If a datetime is specified, a correspond
A25: call2__v | B25: Call | C25: call_reminder__v | D25: Call Reminder | E25: String
A26: call2__v | B26: Call | C26: call_type__v | D26: Call Type | E26: Picklist | F26: Type of call which is system maintained based on the type and contents of the call. This field is used for reporting purposes. Valid values are: Detail Only, Detail with Sample, Group Detail, Group Detail with Sample, Sample Only. These values should not
A27: call2__v | B27: Call | C27: cds__v | D27: CDS # | E27: String
A28: call2__v | B28: Call | C28: cds_expiration_date__v | D28: CDS Expiration Date | E28: Date
A29: call2__v | B29: Call | C29: chat_summary__v | D29: Chat Summary | E29: LongText
A30: call2__v | B30: Call | C30: check_in_latitude__v | D30: Check In Latitude | E30: Number
A31: call2__v | B31: Call | C31: check_in_location_services_status__v | D31: Check In Location Services Status | E31: Picklist
A32: call2__v | B32: Call | C32: check_in_longitude__v | D32: Check In Longitude | E32: Number
A33: call2__v | B33: Call | C33: check_in_status__v | D33: Check In Status | E33: Picklist
A34: call2__v | B34: Call | C34: check_in_timestamp__v | D34: Check In Timestamp | E34: Number
A35: call2__v | B35: Call | C35: child_account__v | D35: Child Account | E35: Object
A36: call2__v | B36: Call | C36: child_account_id__v | D36: Child Account Id | E36: String
A37: call2__v | B37: Call | C37: city__v | D37: City | E37: String | F37: City of the Call Address. This field should not be displayed on the Page Layout.
A38: call2__v | B38: Call | C38: clm__v | D38: CLM | E38: Boolean | F38: If checked indicates CLM has been run for this call and the call contents were populated from CLM.
A39: call2__v | B39: Call | C39: clm_location_latitude__v | D39: CLM Location Latitude | E39: Number
A40: call2__v | B40: Call | C40: clm_location_longitude__v | D40: CLM Location Longitude | E40: Number
A41: call2__v | B41: Call | C41: clm_location_services_status__v | D41: CLM Location Services Status | E41: Picklist
A42: call2__v | B42: Call | C42: cobrowse_mc_activity__v | D42: CoBrowse Activity | E42: Object
A43: call2__v | B43: Call | C43: cobrowse_mc_session__v | D43: CoBrowse Session | E43: String
A44: call2__v | B44: Call | C44: cobrowse_presentation__v | D44: Presentation | E44: Object
A45: call2__v | B45: Call | C45: cobrowse_url_participant__v | D45: Participant URL | E45: String
A46: call2__v | B46: Call | C46: cobrowse_url_presenter__v | D46: Presenter URL | E46: String
A47: call2__v | B47: Call | C47: color__v | D47: Color | E47: Picklist | F47: The user-selectable color for a call, as visible in VMobile.
A48: call2__v | B48: Call | C48: concur_report_name__v | D48: Concur Report Name | E48: String
A49: call2__v | B49: Call | C49: controlling_parent_account__v | D49: Controlling Parent Account | E49: Object
A50: call2__v | B50: Call | C50: controlling_ship_to_address_account__v | D50: Controlling Ship to Address Account | E50: Object
A51: call2__v | B51: Call | C51: country_account__v | D51: Account Country | E51: Object
A52: call2__v | B52: Call | C52: country_user__v | D52: User Country | E52: Object
A53: call2__v | B53: Call | C53: created_by__v | D53: Created By | E53: Object
A54: call2__v | B54: Call | C54: created_date__v | D54: Created Date | E54: DateTime
A55: call2__v | B55: Call | C55: createdby_platform__v | D55: Created By Platform | E55: Picklist
A56: call2__v | B56: Call | C56: credentials__v | D56: Credentials | E56: String | F56: The credentials of the Account signing for a sample
A57: call2__v | B57: Call | C57: dea__v | D57: DEA # | E57: String | F57: The DEA # is the DEA License # of the Physician that received the Samples.
A58: call2__v | B58: Call | C58: dea_address__v | D58: DEA Address | E58: Object | F58: The DEA Address is a reference field to the Address record where the Controlled Substance has been sampled or shipped. This reference value will be removed if the Address record is deleted.
A59: call2__v | B59: Call | C59: dea_address_line_1__v | D59: DEA Address Line 1 | E59: String | F59: Address Line 1 of the DEA Address.
A60: call2__v | B60: Call | C60: dea_address_line_2__v | D60: DEA Address Line 2 | E60: String | F60: Address Line 2 of the DEA Address.
A61: call2__v | B61: Call | C61: dea_city__v | D61: DEA City | E61: String | F61: City of the DEA Address.
A62: call2__v | B62: Call | C62: dea_expiration_date__v | D62: DEA Expiration Date | E62: Date | F62: DEA Expiration Date of the Physician's DEA License that received the controlled substance.
A63: call2__v | B63: Call | C63: dea_state__v | D63: DEA State | E63: String | F63: State of the DEA Address.
A64: call2__v | B64: Call | C64: dea_zip_4__v | D64: DEA Zip 4 | E64: String | F64: Zip Code 4 of the DEA Address.
A65: call2__v | B65: Call | C65: dea_zip__v | D65: DEA Zip | E65: String | F65: Zip Code of the DEA Address.
A66: call2__v | B66: Call | C66: detail_section_attribute__v | D66: Detail Section Attribute | E66: String
A67: call2__v | B67: Call | C67: detailed_products__v | D67: Detailed Products | E67: String | F67: A helper field to display the list of detailed products for a call. Product names should be delimited by double-spaces and order in priority from left to right. This field does not control processing and is included to make related lists and reports more
A68: call2__v | B68: Call | C68: disbursed_to__v | D68: Disbursed To | E68: String | F68: Used to record sample disbursement information (if any). This contains all PDMA required fields (name, address, etc.) in text format. This value is copied in to the sample transaction object via a trigger. It is maintained on call header for synchronizati
A69: call2__v | B69: Call | C69: disbursement_order_created__v | D69: Disbursement Created | E69: Boolean
A70: call2__v | B70: Call | C70: disclaimer__v | D70: Disclaimer | E70: LongText | F70: Used to record sample disclaimer used if a disbursement was made. This value is copied in to the sample transaction object via a trigger. It is maintained on call header for synchronization purposes.
A71: call2__v | B71: Call | C71: documented_interest__v | D71: Documented Interest | E71: Object | F71: Stores the ID of the selected Documented Interest record.
A72: call2__v | B72: Call | C72: duration__v | D72: Duration | E72: Number | F72: Duration of the call in minutes.
A73: call2__v | B73: Call | C73: em_event__v | D73: EM Event | E73: Object
A74: call2__v | B74: Call | C74: entity_display_name__v | D74: Entity Display Name | E74: String | F74: Entity's displayed name
A75: call2__v | B75: Call | C75: entity_reference_id__v | D75: Entity Reference Id | E75: String | F75: For Internal Use Only
A76: call2__v | B76: Call | C76: error_reference_call__v | D76: Error Reference Call | E76: Object | F76: Indicates the call this call is a duplicate of.
A77: call2__v | B77: Call | C77: expense_amount__v | D77: Expense Amount | E77: Number | F77: Holds the number of amount of the expense on this call
A78: call2__v | B78: Call | C78: expense_amount_corpv__sys | D78: Expense Amount Corp | E78: Number
A79: call2__v | B79: Call | C79: expense_attendee_type__v | D79: Expense Attendee Type | E79: Picklist
A80: call2__v | B80: Call | C80: expense_post_status__v | D80: Expense Post Status | E80: String | F80: Holds a Success or Fail status based on the attempt to post this status into Concur. If the expense was not yet posted, status = null
A81: call2__v | B81: Call | C81: expense_receipt_status__v | D81: Expense Receipt Status | E81: String
A82: call2__v | B82: Call | C82: expense_system_external_id__v | D82: Expense System ID | E82: String | F82: The ID that maps to the expense management system
A83: call2__v | B83: Call | C83: global_id__sys | D83: Global ID | E83: String
A84: call2__v | B84: Call | C84: id | D84: ID | E84: ID
A85: call2__v | B85: Call | C85: incurred_expense__v | D85: Incurred Expense | E85: Boolean | F85: Attendees with the Incurred Expense button checked will be posted as Attendees to Concur.
A86: call2__v | B86: Call | C86: is_parent_call__v | D86: Is Parent Call? | E86: Number | F86: Formula Field to determine if the Call record is the Parent Call or an Attendee Call record. 1 indicates that the record is the Parent Call. 0 indicates that it is an Attendee Call.
A87: call2__v | B87: Call | C87: is_sampled_call__v | D87: Is Sampled Call | E87: Boolean | F87: Checked if this call header designates the account that received samples for the call.
A88: call2__v | B88: Call | C88: last_device__v | D88: Last Device | E88: Picklist | F88: This field is used to track the last device used to save a call. You can build reports using this field to determine what devices are being used to record calls.
A89: call2__v | B89: Call | C89: lastmodifiedby_platform__v | D89: Last Modified By Platform | E89: Picklist
A90: call2__v | B90: Call | C90: legacy_crm_id__v | D90: Legacy CRM Id | E90: String
A91: call2__v | B91: Call | C91: license__v | D91: License # | E91: String | F91: State License Number for the corresponding State of the Address.
A92: call2__v | B92: Call | C92: license_expiration_date__v | D92: License Expiration Date | E92: Date
A93: call2__v | B93: Call | C93: license_status__v | D93: License Status | E93: String
A94: call2__v | B94: Call | C94: lifecycle__v | D94: Lifecycle | E94: Component
A95: call2__v | B95: Call | C95: link__sys | D95: Link | E95: String
A96: call2__v | B96: Call | C96: link_external_id__v | D96: Link External ID | E96: String
A97: call2__v | B97: Call | C97: link_from_email__v | D97: From Email | E97: String
A98: call2__v | B98: Call | C98: link_from_id__v | D98: From ID | E98: String
A99: call2__v | B99: Call | C99: local_currency__sys | D99: Local Currency | E99: Object
A100: call2__v | B100: Call | C100: location__v | D100: Location | E100: String | F100: Text field to note the location of the call. There is no special processing on this field.
...

Sheet Mapping Objects
A1: Source Objects | D1: Target Object | G1: OOB Mapping Status | H1: Custom Mapping Status | I1: Comments | J1: Additional notes | L1: Target Object
A2: Object | B2: Object Label | C2: Object Description | D2: Object | E2: Object Label | F2: Object Description | L2: Object | M2: Object Label | N2: Object Description | O2: Match Found?
A3: OCE__Call__c | B3: Interactions | C3: The Call object stores all data pertaining to Calls Reps have logged using the Log a Call module. | D3: call2__v | E3: =IFNA(IF(VLOOKUP(D3,L:N,2,FALSE)="","",VLOOKUP(D3,L:N,2,FALSE)),"") -> Call | F3: =IFNA(IF(VLOOKUP(D3,L:N,3,FALSE)="","",VLOOKUP(D3,L:N,3,FALSE)),"") -> This object stores the main call header information. There is one call row for every account or contact on the call. A group call with 3 doctors will produce 4 call rows. | G3: Reviewed with Roche | I3: Pending to review from Veeva and confirmation from field location_name__v | J3: In OCE-P the calls have in one single record the information from the HCP and the location-address, which is connected with the workplace (HCO). In Veeva we will need to create multiple records: - The visits without parent call and without any child call will be face to face. The Vault parent call will be the HCPs data and a new records will need to be created in Vault for the HCO as child call. - The visits with parent call will be group calls. The Vault parent call will be the HCOs data from the OCE-P location. The child call records will be the HCPs. | L3: call2__v | M3: Call | N3: This object stores the main call header information. There is one call row for every account or contact on the call. A group call with 3 doctors will produce 4 call rows. | O3: =IFNA(IF(VLOOKUP(L3,D:D,1,FALSE)=L3,"Yes","No"),"No") -> Yes
A4: OCE__CallEmployeeAttendee__c | B4: Call Employee Attendees | C4: Junction object which contains users which are added as attendees to call. | D4: call2__v | E4: =IFNA(IF(VLOOKUP(D4,L:N,2,FALSE)="","",VLOOKUP(D4,L:N,2,FALSE)),"") -> Call | F4: =IFNA(IF(VLOOKUP(D4,L:N,3,FALSE)="","",VLOOKUP(D4,L:N,3,FALSE)),"") -> This object stores the main call header information. There is one call row for every account or contact on the call. A group call with 3 doctors will produce 4 call rows. | G4: Reviewed with Roche | J4: This records will be child calls where attendees are users | L4: call2_detail__v | M4: Call Detail | N4: This object stores all product details data recorded on any call. | O4: =IFNA(IF(VLOOKUP(L4,D:D,1,FALSE)=L4,"Yes","No"),"No") -> Yes
A5: OCE__CallDetail__c | B5: Interaction Details | C5: The object stores data related to Details during the Call | D5: call2_detail__v | E5: =IFNA(IF(VLOOKUP(D5,L:N,2,FALSE)="","",VLOOKUP(D5,L:N,2,FALSE)),"") -> Call Detail | F5: =IFNA(IF(VLOOKUP(D5,L:N,3,FALSE)="","",VLOOKUP(D5,L:N,3,FALSE)),"") -> This object stores all product details data recorded on any call. | G5: Pending few fields to review with Roche | L5: action_item__v | M5: Call Discussion | N5: This object stores all product discussions data recorded on any call, as well as allows for creating different product discussions layouts | O5: =IFNA(IF(VLOOKUP(L5,D:D,1,FALSE)=L5,"Yes","No"),"No") -> Yes
A6: OCE__CallDiscussion__c | B6: Call Discussions | C6: The object stores data related to Discussions about products, during the Call | D6: call2_discussion__v | E6: =IFNA(IF(VLOOKUP(D6,L:N,2,FALSE)="","",VLOOKUP(D6,L:N,2,FALSE)),"") | F6: =IFNA(IF(VLOOKUP(D6,L:N,3,FALSE)="","",VLOOKUP(D6,L:N,3,FALSE)),"") | G6: Pending few fields to review with Roche | L6: call2_expense__v | M6: Call Expense | N6: This object stores all expense data recorded on a call | O6: =IFNA(IF(VLOOKUP(L6,D:D,1,FALSE)=L6,"Yes","No"),"No") -> No
A7: OCE__CallMessage__c | B7: Call Messages | C7: The object stores data related to messages/reactions during the Call | D7: call2_key_message__v | E7: =IFNA(IF(VLOOKUP(D7,L:N,2,FALSE)="","",VLOOKUP(D7,L:N,2,FALSE)),"") -> Call Key Message | F7: =IFNA(IF(VLOOKUP(D7,L:N,3,FALSE)="","",VLOOKUP(D7,L:N,3,FALSE)),"") -> This object stores all Key Messages recorded on a call | G7: Pending few fields to review with Roche | L7: call2_key_message__v | M7: Call Key Message | N7: This object stores all Key Messages recorded on a call | O7: =IFNA(IF(VLOOKUP(L7,D:D,1,FALSE)=L7,"Yes","No"),"No") -> Yes
A8: OCE__CallItem__c | B8: Call Items | C8: The object stores data related to Items during the Call | D8: call2_sample__v | E8: =IFNA(IF(VLOOKUP(D8,L:N,2,FALSE)="","",VLOOKUP(D8,L:N,2,FALSE)),"") -> Call Sample | F8: =IFNA(IF(VLOOKUP(D8,L:N,3,FALSE)="","",VLOOKUP(D8,L:N,3,FALSE)),"") -> Samples and Promotional Items itemized on Call Reports | G8: Reviewed with Roche | J8: Items are educational item materials (papers) delivered during call reporting. In Veeva maybe are Promotional Items from Call Sample | L8: call2_sample__v | M8: Call Sample | N8: Samples and Promotional Items itemized on Call Reports | O8: =IFNA(IF(VLOOKUP(L8,D:D,1,FALSE)=L8,"Yes","No"),"No") -> Yes
A9: OCE__CallPresentation__c | B9: Call Presentations | C9: The object stores data related to Presentations shown from Call, Meeting, etc. | D9: OOS | E9: =IFNA(IF(VLOOKUP(D9,L:N,2,FALSE)="","",VLOOKUP(D9,L:N,2,FALSE)),"") | F9: =IFNA(IF(VLOOKUP(D9,L:N,3,FALSE)="","",VLOOKUP(D9,L:N,3,FALSE)),"") | G9: Out of Scope | J9: In calls, the field presentations__v should contain the list of presentations (CLMs) related with OCE_CallPresentation__c per call. | L9: call2_sample_cancel__v | M9: Call Sample Cancel | N9: The Call Sample Cancel object provides the ability to Cancel the delivery of a Sample Send request for a physician. | O9: =IFNA(IF(VLOOKUP(L9,D:D,1,FALSE)=L9,"Yes","No"),"No") -> No
A10: OCE__ClickStreamMetric__c | B10: Click Stream Metric | C10: Used for gathering CLM clickstream data. | D10: OOS | E10: =IFNA(IF(VLOOKUP(D10,L:N,2,FALSE)="","",VLOOKUP(D10,L:N,2,FALSE)),"") | F10: =IFNA(IF(VLOOKUP(D10,L:N,3,FALSE)="","",VLOOKUP(D10,L:N,3,FALSE)),"") | G10: Out of Scope | J10: In calls, the field presentations__v should contain the list of presentations (CLMs) related with OCE_CallPresentation__c per call. | L10: call_clickstream__v | M10: Call Clickstream | N10: Object containing clickstream data received from CLM system. | O10: =IFNA(IF(VLOOKUP(L10,D:D,1,FALSE)=L10,"Yes","No"),"No") -> No
A11: OCE__ClickStreamMetric__c | B11: Click Stream Metric | C11: Used for gathering CLM clickstream data. | D11: call2_key_message__v | E11: =IFNA(IF(VLOOKUP(D11,L:N,2,FALSE)="","",VLOOKUP(D11,L:N,2,FALSE)),"") -> Call Key Message | F11: =IFNA(IF(VLOOKUP(D11,L:N,3,FALSE)="","",VLOOKUP(D11,L:N,3,FALSE)),"") -> This object stores all Key Messages recorded on a call | G11: Pending few fields to review with Roche | J11: In calls, the field presentations__v should contain the list of presentations (CLMs) related with OCE_CallPresentation__c per call. | L11: call_cycle_entry__v | M11: Call Cycle Entry | N11: Call Cycle Entries store information about a rep's weekly route. They only store account name, the default address for each account is used when the call cycle is applied to a day. Call cycles (and their titles) are only editable on VMobile. However, r | O11: =IFNA(IF(VLOOKUP(L11,D:D,1,FALSE)=L11,"Yes","No"),"No") -> No
A12: OCE__CallDialogue__c | B12: Interaction Dialogues | C12: Contains surveys passed on LogACall. | D12: OOS | E12: =IFNA(IF(VLOOKUP(D12,L:N,2,FALSE)="","",VLOOKUP(D12,L:N,2,FALSE)),"") | F12: =IFNA(IF(VLOOKUP(D12,L:N,3,FALSE)="","",VLOOKUP(D12,L:N,3,FALSE)),"") | G12: Out of Scope | J12: No historical data in scope | L12: call_error__v | M12: Call Error | N12: This is a temporary holding object for failed synchronization messages from the mobile client. The messages will be accepted or rejected by an administrator. | O12: =IFNA(IF(VLOOKUP(L12,D:D,1,FALSE)=L12,"Yes","No"),"No") -> No
A13: OCE__CallSampleOrder__c | B13: Call Sample Orders | C13: The object stores data related to Sample Orders during the Call | D13: call2_sample__v | E13: =IFNA(IF(VLOOKUP(D13,L:N,2,FALSE)="","",VLOOKUP(D13,L:N,2,FALSE)),"") -> Call Sample | F13: =IFNA(IF(VLOOKUP(D13,L:N,3,FALSE)="","",VLOOKUP(D13,L:N,3,FALSE)),"") -> Samples and Promotional Items itemized on Call Reports | G13: Pending few fields to review with Roche | J13: Are call samples send via logistic operator. Potentially can be the Veeva BRCs. | L13: call_followup_task__v | M13: Call Followup Task | N13: This is the user task object that stores records for call follow up activities. | O13: =IFNA(IF(VLOOKUP(L13,D:D,1,FALSE)=L13,"Yes","No"),"No") -> No
A14: OCE__CallStudy__c | B14: Interaction clinical trials | C14: Studies which were done during call. | D14: medical_insight__v | E14: =IFNA(IF(VLOOKUP(D14,L:N,2,FALSE)="","",VLOOKUP(D14,L:N,2,FALSE)),"") -> Medical Insight | F14: =IFNA(IF(VLOOKUP(D14,L:N,3,FALSE)="","",VLOOKUP(D14,L:N,3,FALSE)),"") -> Stores Key Medical Insights and relevant Insight sources | G14: Pending business decisions | I14: [20260423] Pending to decide the approach for this object migration. | J14: [20260423] Pending to decide the approach for this object migration. | L14: call_followup_template__v | M14: Call Followup Template | N14: A Call Follow-up Template controls how follow-up activities are created on Call Reports. One Template per Follow-up type (todo, medical information,...). | O14: =IFNA(IF(VLOOKUP(L14,D:D,1,FALSE)=L14,"Yes","No"),"No") -> No
A15: OCE__CallToDo__c | B15: Interaction To-Dos | C15: Junction object between Call and To-Do objects | D15: action_item__v | E15: =IFNA(IF(VLOOKUP(D15,L:N,2,FALSE)="","",VLOOKUP(D15,L:N,2,FALSE)),"") -> Call Discussion | F15: =IFNA(IF(VLOOKUP(D15,L:N,3,FALSE)="","",VLOOKUP(D15,L:N,3,FALSE)),"") -> This object stores all product discussions data recorded on any call, as well as allows for creating different product discussions layouts | G15: Pending business decisions | I15: [20260423] It's not yet discussed the approach for Account Plan, and this may have and impact on the management for this object, since it can be hadled via action_item__v, but also with call_followup_task__v or call2_objective__v. Next week it's planned a call from Veeva with business to decide on that. | J15: [20260423] It's not yet discussed the approach for Account Plan, and this may have and impact on the management for this object, since it can be hadled via action_item__v, but also with call_followup_task__v or call2_objective__v. Next week it's planned a call from Veeva with business to decide on that. | L15: call_objective__v | M15: Call Objective | N15: Call Objective can be accessed through Call Report | O15: =IFNA(IF(VLOOKUP(L15,D:D,1,FALSE)=L15,"Yes","No"),"No") -> No
A16: OCE__CallAccountTactic__c | B16: Interaction Tactics | C16: Junction object to connect Call to Tactics. | D16: call2_discussion__v | E16: =IFNA(IF(VLOOKUP(D16,L:N,2,FALSE)="","",VLOOKUP(D16,L:N,2,FALSE)),"") | F16: =IFNA(IF(VLOOKUP(D16,L:N,3,FALSE)="","",VLOOKUP(D16,L:N,3,FALSE)),"") | G16: Pending business decisions | I16: [20260423] To link an executed tactic during a call in Vault CRM should be done with action_item__v or with call2_objective__, which may or may not be connected with an Account Plan. Wait for next week meeting to review this topic. | J16: [20260423] To link an executed tactic during a call in Vault CRM should be done with action_item__v or with call2_objective__, which may or may not be connected with an Account Plan. Wait for next week meeting to review this topic. | L16: medical_insight__v | M16: Medical Insight | N16: Stores Key Medical Insights and relevant Insight sources | O16: =IFNA(IF(VLOOKUP(L16,D:D,1,FALSE)=L16,"Yes","No"),"No") -> Yes
A17: OCE__CallSample__c | B17: Call Samples | C17: The object stores data related to Samples during the Call | D17: OOS | E17: Call Sample | F17: Samples and Promotional Items itemized on Call Reports | G17: Out of Scope | J17: OCE_CallSample__c is empty but it's for F2F sample delivery. | L17: action_item__v | M17: Action Item | N17: Object used to represent a task that is associated to an account plan through the Account Plan hierarchy. | O17: =IFNA(IF(VLOOKUP(L17,D:D,1,FALSE)=L17,"Yes","No"),"No") -> Yes
A18: OCE__CallPlan__c | B18: Call Plans | C18: A strategic plan that is focused on reach and frequency. | D18: OOS | E18: =IFNA(IF(VLOOKUP(D18,L:N,2,FALSE)="","",VLOOKUP(D18,L:N,2,FALSE)),"") | F18: =IFNA(IF(VLOOKUP(D18,L:N,3,FALSE)="","",VLOOKUP(D18,L:N,3,FALSE)),"") | G18: Out of Scope
A19: OCE__CallExpense__c | B19: Call Expenses | C19: The object stores data related to Expenses during the Call | D19: OOS | E19: Call Expense | F19: This object stores all expense data recorded on a call | G19: Out of Scope | J19: OCE__CallExpense__c is empty

Sheet Sample_Data
A1: Person Call Parent
A2: SELECT FIELDS(ALL) from OCE__Call__c where OCE__ParentCall__c = null and OCE__Account__r.IsPersonAccount = true limit 200
A3: _ | B3: Id | C3: OwnerId | D3: IsDeleted | E3: Name | F3: CurrencyIsoCode | G3: RecordTypeId | H3: CreatedDate | I3: CreatedById | J3: LastModifiedDate | K3: LastModifiedById | L3: SystemModstamp | M3: LastViewedDate | N3: LastReferencedDate | O3: OCE__Accompaniedby__c | P3: OCE__AccountName__c | Q3: OCE__AccountRefData__c | R3: OCE__AccountRestrictedProductsByTerritories__c | S3: OCE__AccountRestrictedProducts__c | T3: OCE__AccountTerritories__c | U3: OCE__Account__c | V3: OCE__AddressLine1__c | W3: OCE__AddressLine2__c | X3: OCE__AddressLine3__c | Y3: OCE__AddressLine4__c | Z3: OCE__AttendeeStatus__c | AA3: OCE__AudioConferenceID__c | AB3: OCE__CSPExpirationDate__c | AC3: OCE__CSPnumber__c | AD3: OCE__CallAddress__c | AE3: OCE__CallDateTime__c | AF3: OCE__CallPlanRefData__c | AG3: OCE__CallPlan__c | AH3: OCE__CallShipToAddress__c | AI3: OCE__CallType__c | AJ3: OCE__Channel__c | AK3: OCE__ChildCallParams__c | AL3: OCE__City__c | AM3: OCE__DEAExpirationDate__c | AN3: OCE__DEALicenseAddress__c | AO3: OCE__DEASchedule__c | AP3: OCE__DEAStatus__c | AQ3: OCE__DEAnumber__c | AR3: OCE__Date__c | AS3: OCE__DisclaimerMessage__c | AT3: OCE__DurationPicklist__c | AU3: OCE__Duration__c | AV3: OCE__EndCallDateTime__c | AW3: OCE__ExpenseAmount__c | AX3: OCE__ExternalID__c | AY3: OCE__GeolocationCheckDateTimeOnSignature__c | AZ3: OCE__GeolocationCheckDateTimeOnSubmit__c | BA3: OCE__GeolocationMissingReasonOnSignature__c | BB3: OCE__GeolocationMissingReasonOnSubmit__c | BC3: OCE__GeolocationOnSignature__Latitude__s | BD3: OCE__GeolocationOnSignature__Longitude__s | BE3: OCE__GeolocationOnSignature__c | BF3: OCE__GeolocationOnSubmit__Latitude__s | BG3: OCE__GeolocationOnSubmit__Longitude__s | BH3: OCE__GeolocationOnSubmit__c | BI3: OCE__IntegrationID__c | BJ3: OCE__InvitationBouncedMessage__c | BK3: OCE__InvitationEmail__c | BL3: OCE__InvitationStatus__c | BM3: OCE__IsConfirmed__c | BN3: OCE__IsDeletedOffline__c | BO3: OCE__IsGroupCall__c | BP3: OCE__IsSignatureCopyRequested__c | BQ3: OCE__IssuesDiscussed__c | BR3: OCE__LicenseExpirationDate__c | BS3: OCE__LicenseStatus__c | BT3: OCE__Licensenumber__c | BU3: OCE__Location__c | BV3: OCE__ManagerComment__c | BW3: OCE__ManagerConfirmationDatetime__c | BX3: OCE__ManagerConfirmationRequest__c | BY3: OCE__ManagerPresenceConfirmed__c | BZ3: OCE__ManagerPresenceStatus__c | CA3: OCE__NextCallObjectivePicklist__c | CB3: OCE__NextCallObjective__c | CC3: OCE__NumberOfCallDetails__c | CD3: OCE__NumberOfCallSampleOrders__c | CE3: OCE__NumberOfCallSamples__c | CF3: OCE__Objections__c | CG3: OCE__OfflineCreatedByID__c | CH3: OCE__OfflineCreatedDate__c | CI3: OCE__OfflineLastModifiedByID__c | CJ3: OCE__OfflineLastModifiedDate__c | CK3: OCE__OfflineUniqueId__c | CL3: OCE__PDMATextInfo__c | CM3: OCE__ParentCallRefData__c | CN3: OCE__ParentCall__c | CO3: OCE__PhysicalFormReason__c | CP3: OCE__PhysicalForm__c | CQ3: OCE__PhysicianDEALicenseNo__c | CR3: OCE__PhysicianDEALicense__c | CS3: OCE__PhysicianStateLicenseNo__c | CT3: OCE__PhysicianStateLicense__c | CU3: OCE__PlannedDate__c | CV3: OCE__PreCallNotes__c | CW3: OCE__ProfessionalDesignation__c | CX3: OCE__RemoteExternalID__c | CY3: OCE__RequestManagerPresence__c | CZ3: OCE__RestrictedProductsOverride__c | DA3: OCE__RouteRefData__c | DB3: OCE__Route__c | DC3: OCE__SalesRepRefData__c | DD3: OCE__SalesRep__c | DE3: OCE__Salutation__c | DF3: OCE__SessionKey__c | DG3: OCE__ShipToAddressLine1__c | DH3: OCE__ShipToAddressLine2__c | DI3: OCE__ShipToCity__c | DJ3: OCE__ShipToRefData__c | DK3: OCE__ShipToState__c | DL3: OCE__ShipToZip__c | DM3: OCE__ShipTo__c | DN3: OCE__ShippingAddress__c | DO3: OCE__SignatureDate__c | DP3: OCE__SignatureTimestamp__c | DQ3: OCE__Signature__c | DR3: OCE__State__c | DS3: OCE__Status__c | DT3: OCE__Subject__c | DU3: OCE__SubmissionDate__c | DV3: OCE__SubmissionDelayReasonPicklist__c | DW3: OCE__SubmissionDelayReason__c | DX3: OCE__Territory__c | DY3: OCE__TotalCallAttendeeCount__c | DZ3: OCE__UniqueIntegrationID__c | EA3: OCE__UserAudioToken__c | EB3: OCE__WithdrawnDate__c | EC3: OCE__Zip__c | ED3: OCE__BookingStatus__c | EE3: OCE__RejectReason__c | EF3: OCE__ComplianceStatements__c | EG3: OCE__HasAttachments__c | EH3: OCE__NextCallProductObjectives__c | EI3: OCE__PreCallProductNotes__c | EJ3: RCH_Is_Unlocked__c | EK3: OCE__Meeting__c | EL3: OCE__Country__c | EM3: OCE__IsAdHocCall__c | EN3: OCE__ToDo__c | EO3: External_Link__c | EP3: RCH_AE_Disclaimer__c | EQ3: RCH_Account_Country__c | ER3: RCH_Account_Mdm_Id__c | ES3: RCH_Account_Name__c | ET3: RCH_Activity_Type__c | EU3: RCH_Activity_owner_Role__c | EV3: RCH_Adverse_Event_Number__c | EW3: RCH_Call_Date_Time_3_days__c | EX3: RCH_Call_Submitted_Entry_Delay_in_Days__c | EY3: RCH_Indication__c | EZ3: RCH_Interaction_Url__c | FA3: RCH_Is_Person_Account__c | FB3: RCH_Is_Signature_Sent__c | FC3: RCH_Is_Visible__c | FD3: RCH_NextInteractionProductObjective__c | FE3: RCH_No_Of_Days__c | FF3: RCH_Non_Visit__c | FG3: RCH_Number_of_Attendees__c | FH3: RCH_Owner_Email__c | FI3: RCH_Owner_FederationIdentifier__c | FJ3: RCH_Owner_Profile_Name__c | FK3: RCH_PC_Disclaimer__c | FL3: RCH_PEER_Activity__c | FM3: RCH_Product_Complaint_Number__c | FN3: RCH_Products__c | FO3: RCH_Profile__c | FP3: RCH_Response_Type__c | FQ3: RCH_Sub_Channel__c | FR3: RCH_TherapeuticArea__c | FS3: OCE1__AccountOneKeyID__c | FT3: RCH_gCal_Account_Name__c | FU3: RCH_gCal_Channel_Value__c | FV3: RCH_gCal_Count_of_Employee_Attendess__c | FW3: RCH_gCal_External_Id__c | FX3: RCH_gCal_HCP_Attendee_Count__c | FY3: RCH_AETrackerReocrdType__c | FZ3: RCH_Activity_Type_Sub_Type__c | GA3: RCH_Interaction_Nature__c | GB3: RCH_Response_Type_Promo__c | GC3: OCE__CallDetailProducts__c | GD3: OCE__ComplianceAgreementStatus__c | GE3: OCE__CallInformation__c | GF3: RCH_Is_Admin__c | GG3: HyperLink__c | GH3: RCH_Attendees__c | GI3: RCH_ChildStateModified__c | GJ3: RCH_Colleagues__c | GK3: RCH_gCal_Update_Interaction__c | GL3: RCH_Owner_Country__c | GM3: OCE1__CountryCode__c | GN3: OCE1__IsIntegrationUserContext__c | GO3: OCE1__WorkplaceOneKeyID__c | GP3: RCH_Owner_Timezone__c | GQ3: RCH_Description__c | GR3: RCH_OwnerName__c | GS3: RCH_Short_Description__c | GT3: RCH_VisitReason__c | GU3: RCH_EpiCX_Network_Attendees__c | GV3: RCH_RecordTypeName__c | GW3: RCH_Global_Sub_type__c | GX3: OCE1__LastModifiedBulkFormAndDate__c | GY3: EditDetailsFromCallCreate__c | GZ3: RCH_Call__c | HA3: RCH_Product_Messages__c | HB3: RCH_Sample_Products__c | HC3: RCH_Sub_type__c | HD3: OCE1__NextCallObjectives__c | HE3: OCE1__PrevCallObjectives__c | HF3: RCH_Linked_Call_Flag__c | HG3: RCH_Customer_to_be_surveyed__c | HH3: RCH_EmailTransaction__c
A4: [OCE__Call__c] | B4: a2Q6900000992d0EAA | C4: 0057U000001eKP1QAM | D4: false | E4: C-00312851 | F4: EUR | G4: 0123X000000wzbXQAQ | H4: 2023-11-03T14:49:37.000+0000 | I4: 0057U000001eKP1QAM | J4: 2024-06-19T12:56:19.000+0000 | K4: 0057U000001Yt7KQAS | L4: 2024-06-19T12:56:19.000+0000 | P4: Milica Neric | Q4: Milica Neric | R4: [] | S4: [] | U4: 0013X00003gWlCxQAK | V4: Brezovik Bb | AD4: Brezovik Bb, Nikšić, ME, 81400 | AE4: 2023-10-26T12:30:00.000+0000 | AI4: Detail Only | AJ4: Face To Face | AL4: Nikšić | AN4: false | AT4: 90 | AV4: 2023-10-26T14:00:00.000+0000 | AW4: 0 | BM4: false | BN4: false | BO4: false | BP4: false | BU4: a1J3X00000DYpE5UAL | BX4: false | BY4: false | CC4: 1 | CD4: 0 | CE4: 0 | CY4: false | CZ4: [{"isAllowAccount":false,"accId":"0013X00003gWlCxQAK"}] | DS4: Submitted | DU4: 2023-11-03T14:49:36.000+0000 | DX4: ME_CORE_TERR_007 | EC4: 81400 | EF4: [{"statementId":"a663X00000094MjQAI","statementType":"Note","statementLabel":"Documenting an Adverse event (AE), Special Situation (SS), Product complaints (PC) in CRM does not constitute a AE/SS/PC reporting to Drug Safety.","statementLabelText":"Documenting an Adverse event (AE), Special Situation (SS), Product complaints (PC) in CRM does not constitute a AE/SS/PC reporting to Drug Safety.","sortOrder":1},{"statementId":"a663X00000094MeQAI","statementType":"Note","statementLabel":"The information (in free text fields) must have been obtained legitimately and must be unambiguous, precise and clear. Only write facts, do not speculate","statementLabelText":"The information (in free text fields) must have been obtained legitimately and must be unambiguous, precise and clear. Only write facts, do not speculate","sortOrder":2}] | EG4: false | EJ4: false | EL4: ME | EM4: false | EP4: false | EQ4: ME | ET4: Call | EU4: Marketing | EW4: true | EX4: 8 | EZ4: https://roche-eu-oce--uat.sandbox.lightning.force.com/a2Q6900000992d0 | FA4: 1 | FB4: false | FC4: false | FE4: 5 | FF4: false | FG4: 1 | FH4: dijana.stojanovski@roche.com.invalid | FI4: rudovid1 | FJ4: Core Non Promotional Customer Facing | FK4: false | FL4: false | FN4: Tecentriq | FO4: Core Non Promotional Customer Facing | FP4: Proactive | FT4: Milica Neric | FU4: Face To Face | FY4: PV/HCO | GC4: Tecentriq | GE4: Tecentriq | GF4: true | GK4: false | GL4: ME | GM4: ME | GN4: false | GP4: Europe/Berlin | GR4: Dijana Stojanovski | GV4: Non-Promotional Face To Face | GY4: true | HF4: false
A5: [OCE__Call__c] | B5: a2Q69000009AIAKEA4 | C5: 0057U000001eKP1QAM | D5: false | E5: C-00422115 | F5: EUR | G5: 0123X000000wzbXQAQ | H5: 2024-01-26T15:34:07.000+0000 | I5: 0057U000001eKP1QAM | J5: 2024-01-26T15:35:50.000+0000 | K5: 0053X00000BBu6fQAD | L5: 2024-01-26T15:35:50.000+0000 | P5: Milica Neric | U5: 0013X00003gWlCxQAK | V5: Brezovik Bb | AD5: Brezovik Bb, Nikšić, ME, 81400 | AE5: 2024-01-23T11:45:00.000+0000 | AJ5: Face To Face | AL5: Nikšić | AN5: false | AT5: 60 | AV5: 2024-01-23T12:45:00.000+0000 | BM5: false | BN5: false | BO5: false | BP5: false | BU5: a1J3X00000DYpE5UAL | BX5: false | BY5: false | CC5: 1 | CD5: 0 | CE5: 0 | CY5: false | DS5: Submitted | DU5: 2024-01-26T15:35:43.000+0000 | DX5: ME_CORE_TERR_007 | EC5: 81400 | EF5: [{"statementValidationType":"None","statementValidationResponse":"Skipped","statementType":"Note","statementLabelText":"Documenting Adverse Events (AE), Special Situations (SS), or Product Complaints (PC), in CRM does not constitute AE/SS/PC reporting to Drug Safety.","statementLabel":"Documenting Adverse Events (AE), Special Situations (SS), or Product Complaints (PC), in CRM does not constitute AE/SS/PC reporting to Drug Safety.","statementId":"a6669000007KfNLAA0","sortOrder":1},{"statementValidationType":"None","statementValidationResponse":"Skipped","statementType":"Note","statementLabelText":"The information (in free text fields) must have been obtained legitimately and must be unambiguous, precise and clear. Only write facts, do not speculate","statementLabel":"The information (in free text fields) must have been obtained legitimately and must be unambiguous, precise and clear. Only write facts, do not speculate","statementId":"a6669000007KfNMAA0","sortOrder":2}] | EG5: false | EH5: [ ] | EJ5: false | EL5: ME | EM5: false | EP5: false | EQ5: ME | ET5: Call | EU5: Marketing | EW5: true | EX5: 3 | EZ5: https://roche-eu-oce--uat.sandbox.lightning.force.com/a2Q69000009AIAK | FA5: 1 | FB5: false | FC5: false | FE5: 5 | FF5: false | FG5: 3 | FH5: dijana.stojanovski@roche.com.invalid | FI5: rudovid1 | FJ5: Core Non Promotional Customer Facing | FK5: false | FL5: false | FN5: Tecentriq | FO5: Core Non Promotional Customer Facing | FP5: Proactive | FQ5: Group Interaction | FT5: Milica Neric | FU5: Face To Face | FX5: 1 | FY5: PV/HCO | GC5: Tecentriq | GD5: Not Required | GE5: Tecentriq | GF5: true | GK5: false | GL5: ME | GM5: ME | GN5: false | GP5: Europe/Berlin | GR5: Dijana Stojanovski | GV5: Non-Promotional Face To Face | GY5: true | HF5: false
A6: [OCE__Call__c] | B6: a2Q69000009DINWEA4 | C6: 0057U000001eKP1QAM | D6: false | E6: C-00069579 | F6: EUR | G6: 0123X000000wzbXQAQ | H6: 2023-04-14T22:21:05.000+0000 | I6: 0057U000001eKP1QAM | J6: 2024-06-19T11:18:14.000+0000 | K6: 0057U000001Yt7KQAS | L6: 2024-06-19T11:18:14.000+0000 | P6: Milica Pejovic | Q6: Milica Pejovic | R6: [] | S6: [] | U6: 0013X00003gWlCxQAK | V6: BREZOVIK BB | AD6: BREZOVIK BB, Nikšić, ME, 81400 | AE6: 2023-04-05T23:30:00.000+0000 | AI6: Detail Only | AJ6: Face To Face | AL6: Nikšić | AN6: false | AT6: 30 | AV6: 2023-04-06T00:00:00.000+0000 | AW6: 0 | BM6: false | BN6: false | BO6: false | BP6: false | BU6: a1J3X00000DYpE5UAL | BX6: false | BY6: false | CC6: 1 | CD6: 0 | CE6: 0 | CY6: false | CZ6: [{"isAllowAccount":false,"accId":"0013X00003gWlCxQAK"}] | DS6: Submitted | DU6: 2023-04-14T22:21:05.000+0000 | DX6: ME_CORE_TERR_007 | EC6: 81400 | EF6: [{"statementId":"a663X00000094MjQAI","statementType":"Note","statementLabel":"Documenting an Adverse event (AE), Special Situation (SS), Product complaints (PC) in CRM does not constitute a AE/SS/PC reporting to Drug Safety.","statementLabelText":"Documenting an Adverse event (AE), Special Situation (SS), Product complaints (PC) in CRM does not constitute a AE/SS/PC reporting to Drug Safety.","sortOrder":1},{"statementId":"a663X00000094MeQAI","statementType":"Note","statementLabel":"The information (in free text fields) must have been obtained legitimately and must be unambiguous, precise and clear. Only write facts, do not speculate","statementLabelText":"The information (in free text fields) must have been obtained legitimately and must be unambiguous, precise and clear. Only write facts, do not speculate","sortOrder":2}] | EG6: false | EJ6: false | EL6: ME | EM6: false | EP6: false | EQ6: ME | ET6: Call | EU6: Marketing | EW6: true | EX6: 9 | EY6: Lung Cancer | EZ6: https://roche-eu-oce--uat.sandbox.lightning.force.com/a2Q69000009DINW | FA6: 1 | FB6: false | FC6: false | FE6: 5 | FF6: false | FG6: 1 | FH6: dijana.stojanovski@roche.com.invalid | FI6: rudovid1 | FJ6: Core Non Promotional Customer Facing | FK6: false | FL6: false | FN6: Alecensa | FO6: Core Non Promotional Customer Facing | FP6: Proactive | FT6: Milica Neric | FU6: Face To Face | FY6: PV/HCO | GC6: Alecensa-Lung Cancer | GE6: Alecensa-Lung Cancer | GF6: true | GK6: false | GL6: ME | GM6: ME | GN6: false | GP6: Europe/Berlin | GR6: Dijana Stojanovski | GV6: Non-Promotional Face To Face | GY6: true | HF6: false
A7: [OCE__Call__c] | B7: a2Q69000009DIO5EAO | C7: 0057U000001eKP1QAM | D7: false | E7: C-00069589 | F7: EUR | G7: 0123X000000wzbXQAQ | H7: 2023-04-14T22:50:58.000+0000 | I7: 0057U000001eKP1QAM | J7: 2024-06-19T11:18:14.000+0000 | K7: 0057U000001Yt7KQAS | L7: 2024-06-19T11:18:14.000+0000 | P7: Milica Pejovic | Q7: Milica Pejovic | R7: [] | S7: [] | U7: 0013X00003gWlCxQAK | V7: BREZOVIK BB | AD7: BREZOVIK BB, Nikšić, ME, 81400 | AE7: 2023-03-08T23:00:00.000+0000 | AI7: Detail Only | AJ7: Face To Face | AL7: Nikšić | AN7: false | AT7: 75 | AV7: 2023-03-09T00:15:00.000+0000 | AW7: 0 | BM7: false | BN7: false | BO7: false | BP7: false | BU7: a1J3X00000DYpE5UAL | BX7: false | BY7: false | CC7: 1 | CD7: 0 | CE7: 0 | CY7: false | CZ7: [{"isAllowAccount":false,"accId":"0013X00003gWlCxQAK"}] | DS7: Submitted | DU7: 2023-04-14T22:50:57.000+0000 | DX7: ME_CORE_TERR_007 | EC7: 81400 | EF7: [{"statementId":"a663X00000094MjQAI","statementType":"Note","statementLabel":"Documenting an Adverse event (AE), Special Situation (SS), Product complaints (PC) in CRM does not constitute a AE/SS/PC reporting to Drug Safety.","statementLabelText":"Documenting an Adverse event (AE), Special Situation (SS), Product complaints (PC) in CRM does not constitute a AE/SS/PC reporting to Drug Safety.","sortOrder":1},{"statementId":"a663X00000094MeQAI","statementType":"Note","statementLabel":"The information (in free text fields) must have been obtained legitimately and must be unambiguous, precise and clear. Only write facts, do not speculate","statementLabelText":"The information (in free text fields) must have been obtained legitimately and must be unambiguous, precise and clear. Only write facts, do not speculate","sortOrder":2}] | EG7: false | EJ7: false | EL7: ME | EM7: false | EP7: false | EQ7: ME | ET7: Call | EU7: Marketing | EW7: true | EX7: 37 | EZ7: https://roche-eu-oce--uat.sandbox.lightning.force.com/a2Q69000009DIO5 | FA7: 1 | FB7: false | FC7: false | FE7: 5 | FF7: false | FG7: 1 | FH7: dijana.stojanovski@roche.com.invalid | FI7: rudovid1 | FJ7: Core Non Promotional Customer Facing | FK7: false | FL7: false | FN7: Tecentriq | FO7: Core Non Promotional Customer Facing | FP7: Proactive | FT7: Milica Neric | FU7: Face To Face | FY7: PV/HCO | GC7: Tecentriq | GE7: Tecentriq | GF7: true | GK7: false | GL7: ME | GM7: ME | GN7: false | GP7: Europe/Berlin | GR7: Dijana Stojanovski | GV7: Non-Promotional Face To Face | GY7: true | HF7: false
A8: [OCE__Call__c] | B8: a2Q69000009QbZCEA0 | C8: 0057U000001eKP1QAM | D8: false | E8: C-00170935 | F8: EUR | G8: 0123X000000wzbXQAQ | H8: 2023-07-27T05:44:22.000+0000 | I8: 0057U000001eKP1QAM | J8: 2024-06-19T09:59:43.000+0000 | K8: 0057U000001Yt7KQAS | L8: 2024-06-19T09:59:43.000+0000 | P8: Milica Pejovic | Q8: Milica Pejovic | R8: [] | S8: [] | U8: 0013X00003gWlCxQAK | V8: BREZOVIK BB | AD8: BREZOVIK BB, Nikšić, ME, 81400 | AE8: 2023-07-25T10:15:00.000+0000 | AI8: Detail Only | AJ8: Face To Face | AL8: Nikšić | AN8: false | AT8: 75 | AV8: 2023-07-25T11:30:00.000+0000 | AW8: 0 | BM8: false | BN8: false | BO8: false | BP8: false | BU8: a1J3X00000DYpE5UAL | BX8: false | BY8: false | CC8: 1 | CD8: 0 | CE8: 0 | CY8: false | CZ8: [{"isAllowAccount":false,"accId":"0013X00003gWlCxQAK"}] | DS8: Submitted | DU8: 2023-07-27T16:59:01.000+0000 | DX8: ME_CORE_TERR_007 | EC8: 81400 | EF8: [{"statementId":"a663X00000094MjQAI","statementType":"Note","statementLabel":"Documenting an Adverse event (AE), Special Situation (SS), Product complaints (PC) in CRM does not constitute a AE/SS/PC reporting to Drug Safety.","statementLabelText":"Documenting an Adverse event (AE), Special Situation (SS), Product complaints (PC) in CRM does not constitute a AE/SS/PC reporting to Drug Safety.","sortOrder":1},{"statementId":"a663X00000094MeQAI","statementType":"Note","statementLabel":"The information (in free text fields) must have been obtained legitimately and must be unambiguous, precise and clear. Only write facts, do not speculate","statementLabelText":"The information (in free text fields) must have been obtained legitimately and must be unambiguous, precise and clear. Only write facts, do not speculate","sortOrder":2}] | EG8: false | EJ8: false | EL8: ME | EM8: false | EP8: false | EQ8: ME | ET8: Call | EU8: Marketing | EW8: false | EX8: 2 | EY8: Lung Cancer | EZ8: https://roche-eu-oce--uat.sandbox.lightning.force.com/a2Q69000009QbZC | FA8: 1 | FB8: false | FC8: false | FE8: 5 | FF8: false | FG8: 1 | FH8: dijana.stojanovski@roche.com.invalid | FI8: rudovid1 | FJ8: Core Non Promotional Customer Facing | FK8: false | FL8: false | FO8: Core Non Promotional Customer Facing | FP8: Proactive | FT8: Milica Neric | FU8: Face To Face | FY8: PV/HCO | GC8: Lung Cancer | GE8: Lung Cancer | GF8: true | GK8: false | GL8: ME | GM8: ME | GN8: false | GP8: Europe/Berlin | GR8: Dijana Stojanovski | GV8: Non-Promotional Face To Face | GY8: true | HF8: false
A9: [OCE__Call__c] | B9: a2Q69000009Yi1vEAC | C9: 0057U000001eKP1QAM | D9: false | E9: C-00192122 | F9: EUR | G9: 0123X000000wzbXQAQ | H9: 2023-08-18T12:18:18.000+0000 | I9: 0057U000001eKP1QAM | J9: 2024-06-19T12:51:13.000+0000 | K9: 0057U000001Yt7KQAS | L9: 2024-06-19T12:51:13.000+0000 | P9: Milica Pejovic | Q9: Milica Pejovic | R9: [] | S9: [] | U9: 0013X00003gWlCxQAK | V9: Brezovik Bb | AD9: Brezovik Bb, Nikšić, ME, 81400 | AE9: 2023-08-18T09:15:00.000+0000 | AI9: Detail Only | AJ9: Face To Face | AL9: Nikšić | AN9: false | AT9: 30 | AV9: 2023-08-18T09:45:00.000+0000 | AW9: 0 | BM9: false | BN9: false | BO9: false | BP9: false | BU9: a1J3X00000DYpE5UAL | BX9: false | BY9: false | CC9: 1 | CD9: 0 | CE9: 0 | CY9: false | CZ9: [{"isAllowAccount":false,"accId":"0013X00003gWlCxQAK"}] | DS9: Submitted | DU9: 2023-09-01T12:52:31.000+0000 | DX9: ME_CORE_TERR_007 | EC9: 81400 | EF9: [{"statementId":"a663X00000094MjQAI","statementType":"Note","statementLabel":"Documenting an Adverse event (AE), Special Situation (SS), Product complaints (PC) in CRM does not constitute a AE/SS/PC reporting to Drug Safety.","statementLabelText":"Documenting an Adverse event (AE), Special Situation (SS), Product complaints (PC) in CRM does not constitute a AE/SS/PC reporting to Drug Safety.","sortOrder":1},{"statementId":"a663X00000094MeQAI","statementType":"Note","statementLabel":"The information (in free text fields) must have been obtained legitimately and must be unambiguous, precise and clear. Only write facts, do not speculate","statementLabelText":"The information (in free text fields) must have been obtained legitimately and must be unambiguous, precise and clear. Only write facts, do not speculate","sortOrder":2}] | EG9: false | EJ9: false | EL9: ME | EM9: false | EP9: false | EQ9: ME | ET9: Call | EU9: Marketing | EW9: true | EX9: 14 | EY9: Lung Cancer | EZ9: https://roche-eu-oce--uat.sandbox.lightning.force.com/a2Q69000009Yi1v | FA9: 1 | FB9: false | FC9: false | FE9: 5 | FF9: false | FG9: 1 | FH9: dijana.stojanovski@roche.com.invalid | FI9: rudovid1 | FJ9: Core Non Promotional Customer Facing | FK9: false | FL9: false | FN9: Alecensa | FO9: Core Non Promotional Customer Facing | FP9: Proactive | FT9: Milica Neric | FU9: Face To Face | FY9: PV/HCO | GC9: Alecensa-Lung Cancer | GE9: Alecensa-Lung Cancer | GF9: true | GK9: false | GL9: ME | GM9: ME | GN9: false | GP9: Europe/Berlin | GR9: Dijana Stojanovski | GV9: Non-Promotional Face To Face | GY9: true | HF9: false
A10: [OCE__Call__c] | B10: a2Q69000009YsADEA0 | C10: 0057U000001eKP1QAM | D10: false | E10: C-00206109 | F10: EUR | G10: 0123X000000wzbXQAQ | H10: 2023-09-01T13:03:23.000+0000 | I10: 0057U000001eKP1QAM | J10: 2024-06-19T14:36:56.000+0000 | K10: 0057U000001Yt7KQAS | L10: 2024-06-19T14:36:56.000+0000 | P10: Milica Pejovic | Q10: Milica Pejovic | R10: [] | S10: [] | U10: 0013X00003gWlCxQAK | V10: Brezovik Bb | AD10: Brezovik Bb, Nikšić, ME, 81400 | AE10: 2023-08-31T10:30:00.000+0000 | AI10: Detail Only | AJ10: Face To Face | AL10: Nikšić | AN10: false | AT10: 30 | AV10: 2023-08-31T11:00:00.000+0000 | AW10: 0 | BM10: false | BN10: false | BO10: false | BP10: false | BU10: a1J3X00000DYpE5UAL | BX10: false | BY10: false | CC10: 1 | CD10: 0 | CE10: 0 | CY10: false | CZ10: [{"isAllowAccount":false,"accId":"0013X00003gWlCxQAK"}] | DS10: Submitted | DU10: 2023-09-01T13:03:22.000+0000 | DX10: ME_CORE_TERR_007 | EC10: 81400 | EF10: [{"statementId":"a663X00000094MjQAI","statementType":"Note","statementLabel":"Documenting an Adverse event (AE), Special Situation (SS), Product complaints (PC) in CRM does not constitute a AE/SS/PC reporting to Drug Safety.","statementLabelText":"Documenting an Adverse event (AE), Special Situation (SS), Product complaints (PC) in CRM does not constitute a AE/SS/PC reporting to Drug Safety.","sortOrder":1},{"statementId":"a663X00000094MeQAI","statementType":"Note","statementLabel":"The information (in free text fields) must have been obtained legitimately and must be unambiguous, precise and clear. Only write facts, do not speculate","statementLabelText":"The information (in free text fields) must have been obtained legitimately and must be unambiguous, precise and clear. Only write facts, do not speculate","sortOrder":2}] | EG10: false | EJ10: false | EL10: ME | EM10: false | EP10: false | EQ10: ME | ET10: Call | EU10: Marketing | EW10: false | EX10: 1 | EZ10: https://roche-eu-oce--uat.sandbox.lightning.force.com/a2Q69000009YsAD | FA10: 1 | FB10: false | FC10: false | FE10: 5 | FF10: false | FG10: 1 | FH10: dijana.stojanovski@roche.com.invalid | FI10: rudovid1 | FJ10: Core Non Promotional Customer Facing | FK10: false | FL10: false | FN10: Tecentriq | FO10: Core Non Promotional Customer Facing | FP10: Proactive | FT10: Milica Neric | FU10: Face To Face | FY10: PV/HCO | GC10: Tecentriq | GE10: Tecentriq | GF10: true | GK10: false | GL10: ME | GM10: ME | GN10: false | GP10: Europe/Berlin | GR10: Dijana Stojanovski | GV10: Non-Promotional Face To Face | GY10: true | HF10: false
A11: [OCE__Call__c] | B11: a2Q7U000000oa8OUAQ | C11: 0057U000001eKP1QAM | D11: false | E11: C-00054162 | F11: EUR | G11: 0123X000000wzbXQAQ | H11: 2023-03-01T08:12:18.000+0000 | I11: 0057U000001eKP1QAM | J11: 2024-06-19T17:43:49.000+0000 | K11: 0057U000001Yt7KQAS | L11: 2024-06-19T17:43:49.000+0000 | P11: Milica Pejovic | Q11: Milica Pejovic | R11: [] | S11: [] | U11: 0013X00003gWlCxQAK | V11: BREZOVIK BB | AD11: BREZOVIK BB, Nikšić, ME, 81400 | AE11: 2023-02-07T11:30:00.000+0000 | AI11: Detail Only | AJ11: Face To Face | AL11: Nikšić | AN11: false | AT11: 30 | AV11: 2023-02-07T12:00:00.000+0000 | AW11: 0 | BM11: false | BN11: false | BO11: false | BP11: false | BU11: a1J3X00000DYpE5UAL | BX11: false | BY11: false | CC11: 1 | CD11: 0 | CE11: 0 | CY11: false | CZ11: [{"isAllowAccount":false,"accId":"0013X00003gWlCxQAK"}] | DS11: Submitted | DU11: 2023-03-01T08:48:47.000+0000 | DX11: ME_CORE_TERR_007 | EC11: 81400 | EF11: [{"statementId":"a663X00000094MjQAI","statementType":"Note","statementLabel":"Documenting an Adverse event (AE), Special Situation (SS), Product complaints (PC) in CRM does not constitute a AE/SS/PC reporting to Drug Safety.","statementLabelText":"Documenting an Adverse event (AE), Special Situation (SS), Product complaints (PC) in CRM does not constitute a AE/SS/PC reporting to Drug Safety.","sortOrder":1},{"statementId":"a663X00000094MeQAI","statementType":"Note","statementLabel":"The information (in free text fields) must have been obtained legitimately and must be unambiguous, precise and clear. Only write facts, do not speculate","statementLabelText":"The information (in free text fields) must have been obtained legitimately and must be unambiguous, precise and clear. Only write facts, do not speculate","sortOrder":2}] | EG11: false | EJ11: false | EL11: ME | EM11: false | EP11: false | EQ11: ME | ET11: Call | EU11: Marketing | EW11: true | EX11: 22 | EZ11: https://roche-eu-oce--uat.sandbox.lightning.force.com/a2Q7U000000oa8O | FA11: 1 | FB11: false | FC11: false | FE11: 5 | FF11: false | FG11: 1 | FH11: dijana.stojanovski@roche.com.invalid | FI11: rudovid1 | FJ11: Core Non Promotional Customer Facing | FK11: false | FL11: false | FN11: Tecentriq | FO11: Core Non Promotional Customer Facing | FP11: Proactive | FT11: Milica Neric | FU11: Face To Face | FY11: PV/HCO | GC11: Tecentriq | GE11: Tecentriq | GF11: true | GK11: false | GL11: ME | GM11: ME | GN11: false | GP11: Europe/Berlin | GR11: Dijana Stojanovski | GV11: Non-Promotional Face To Face | GY11: true | HF11: false
A12: [OCE__Call__c] | B12: a2QSe000001dCqLMAU | C12: 0057U000001eKP1QAM | D12: false | E12: C-00715769 | F12: EUR | G12: 0123X000000wzbXQAQ | H12: 2024-07-22T12:41:36.000+0000 | I12: 0057U000001eKP1QAM | J12: 2024-07-22T12:42:13.000+0000 | K12: 0053X00000BBu6fQAD | L12: 2024-07-22T12:42:13.000+0000 | P12: Predrag Pejovic | Q12: Predrag Pejovic | U12: 0013X00003gWlCyQAK | V12: Brezovik Bb | AD12: Brezovik Bb, Nikšić, ME, 81400 | AE12: 2024-06-24T09:45:00.000+0000 | AJ12: Face To Face | AL12: Nikšić | AN12: false | AT12: 15 | AV12: 2024-06-24T10:00:00.000+0000 | BM12: false | BN12: false | BO12: false | BP12: false | BU12: a1J3X00000DYpE6UAL | BX12: false | BY12: false | CC12: 1 | CD12: 0 | CE12: 0 | CY12: false | DS12: Submitted | DU12: 2024-07-22T12:42:06.000+0000 | DX12: ME_CORE_TERR_007 | EC12: 81400 | EF12: [{"statementValidationType":"None","statementValidationResponse":"Skipped","statementType":"Note","statementLabelText":"Documenting Adverse Events (AE), Special Situations (SS), or Product Complaints (PC), in CRM does not constitute AE/SS/PC reporting to Drug Safety.","statementLabel":"Documenting Adverse Events (AE), Special Situations (SS), or Product Complaints (PC), in CRM does not constitute AE/SS/PC reporting to Drug Safety.","statementId":"a6669000007KfNLAA0","sortOrder":1},{"statementValidationType":"None","statementValidationResponse":"Skipped","statementType":"Note","statementLabelText":"The information (in free text fields) must have been obtained legitimately and must be unambiguous, precise and clear. Only write facts, do not speculate","statementLabel":"The information (in free text fields) must have been obtained legitimately and must be unambiguous, precise and clear. Only write facts, do not speculate","statementId":"a6669000007KfNMAA0","sortOrder":2}] | EG12: false | EH12: [ ] | EJ12: false | EL12: ME | EM12: false | EP12: false | EQ12: ME | ET12: Call | EU12: Marketing | EW12: true | EX12: 28 | EY12: Non-Small Cell Lung Cancer | EZ12: https://roche-eu-oce--uat.sandbox.lightning.force.com/a2QSe000001dCqL | FA12: 1 | FB12: false | FC12: false | FE12: 5 | FF12: false | FH12: dijana.stojanovski@roche.com.invalid | FI12: rudovid1 | FJ12: Core Non Promotional Customer Facing | FK12: false | FL12: false | FN12: Tecentriq | FO12: Core Non Promotional Customer Facing | FP12: Proactive | FQ12: 1:1 Interaction | FT12: Predrag Pejovic | FU12: Face To Face | FY12: PV/HCO | GC12: Tecentriq-Non-Small Cell Lung Cancer | GD12: Not Required | GE12: Tecentriq-Non-Small Cell Lung Cancer | GF12: true | GK12: false | GL12: ME | GM12: ME | GN12: false | GP12: Europe/Berlin | GR12: Dijana Stojanovski | GV12: Non-Promotional Face To Face | GY12: true | HF12: false
A13: [OCE__Call__c] | B13: a2QSe000006LVQMMA4 | C13: 0053X00000E3yMaQAJ | D13: false | E13: C-01380767 | F13: RSD | G13: 0123X000000wzbXQAQ | H13: 2025-08-22T14:10:25.000+0000 | I13: 0053X00000E3yMaQAJ | J13: 2025-08-22T14:12:27.000+0000 | K13: 0053X00000BBu6fQAD | L13: 2025-08-22T14:12:27.000+0000 | P13: Predrag Pejovic | Q13: Predrag Pejovic | U13: 0013X00003gWlCyQAK | V13: Brezovik Bb | AD13: Brezovik Bb, Nikšić, ME, 81400 | AE13: 2025-08-22T10:00:00.000+0000 | AJ13: Face To Face | AL13: Nikšić | AN13: false | AT13: 30 | AV13: 2025-08-22T10:30:00.000+0000 | BM13: false | BN13: false | BO13: false | BP13: false | BU13: a1J3X00000DYpE6UAL | BX13: false | BY13: false | CC13: 1 | CD13: 0 | CE13: 0 | CY13: false | DS13: Submitted | DU13: 2025-08-22T14:12:22.000+0000 | DX13: ME_CORE_TERR_002 | EC13: 81400 | EF13: [{"statementValidationType":"None","statementValidationResponse":"Skipped","statementType":"Note","statementLabelText":"Documenting Adverse Events (AE), Special Situations (SS), or Product Complaints (PC), in CRM does not constitute AE/SS/PC reporting to Drug Safety.","statementLabel":"Documenting Adverse Events (AE), Special Situations (SS), or Product Complaints (PC), in CRM does not constitute AE/SS/PC reporting to Drug Safety.","statementId":"a6669000007KfNLAA0","sortOrder":1},{"statementValidationType":"None","statementValidationResponse":"Skipped","statementType":"Note","statementLabelText":"The information (in free text fields) must have been obtained legitimately and must be unambiguous, precise and clear. Only write facts, do not speculate","statementLabel":"The information (in free text fields) must have been obtained legitimately and must be unambiguous, precise and clear. Only write facts, do not speculate","statementId":"a6669000007KfNMAA0","sortOrder":2}] | EG13: false | EH13: [ ] | EJ13: false | EL13: ME | EM13: false | EP13: false | EQ13: ME | ET13: Call | EU13: Marketing | EW13: false | EX13: 0 | EY13: Non-Small Cell Lung Cancer | EZ13: https://roche-eu-oce--uat.sandbox.lightning.force.com/a2QSe000006LVQM | FA13: 1 | FB13: false | FC13: false | FE13: 5 | FF13: false | FH13: milos.radjenovic@roche.com.invalid | FI13: radjenom | FJ13: Core Non Promotional Customer Facing | FK13: false | FL13: false | FN13: Tecentriq | FO13: Core Non Promotional Customer Facing | FP13: Proactive | FT13: Predrag Pejovic | FU13: Face To Face | FY13: PV/HCO | GC13: Tecentriq-Non-Small Cell Lung Cancer | GD13: Not Required | GE13: Tecentriq-Non-Small Cell Lung Cancer | GF13: true | GK13: false | GL13: RS | GM13: ME | GN13: false | GP13: Europe/Berlin | GR13: Milos Radjenovic | GV13: Non-Promotional Face To Face | GY13: true | HC13: MD | HF13: false
A14: [OCE__Call__c] | B14: a2Q6900000992fIEAQ | C14: 0057U000001eKP1QAM | D14: false | E14: C-00312412 | F14: EUR | G14: 0123X000000wzbXQAQ | H14: 2023-11-03T13:49:00.000+0000 | I14: 0057U000001eKP1QAM | J14: 2024-06-19T12:56:23.000+0000 | K14: 0057U000001Yt7KQAS | L14: 2024-06-19T12:56:23.000+0000 | P14: Dejan Perovic | Q14: Dejan Perovic | R14: [] | S14: [] | U14: 0013X00003gWlCzQAK | V14: Brezovik Bb | AD14: Brezovik Bb, Nikšić, ME, 81400 | AE14: 2023-10-17T10:00:00.000+0000 | AI14: Group Detail | AJ14: Face To Face | AL14: Nikšić | AN14: false | AT14: 45 | AV14: 2023-10-17T10:45:00.000+0000 | AW14: 0 | BM14: false | BN14: false | BO14: true | BP14: false | BU14: a1J3X00000DYpE7UAL | BX14: false | BY14: false | CC14: 1 | CD14: 0 | CE14: 0 | CY14: false | CZ14: [{"isAllowAccount":false,"accId":"0013X00003gWlCzQAK"},{"isAllowAccount":false,"accId":"0017U00000GufzIQAR"}] | DS14: Submitted | DU14: 2023-11-03T13:48:59.000+0000 | DX14: ME_CORE_TERR_007 | EC14: 81400 | EF14: [{"statementId":"a663X00000094MjQAI","statementType":"Note","statementLabel":"Documenting an Adverse event (AE), Special Situation (SS), Product complaints (PC) in CRM does not constitute a AE/SS/PC reporting to Drug Safety.","statementLabelText":"Documenting an Adverse event (AE), Special Situation (SS), Product complaints (PC) in CRM does not constitute a AE/SS/PC reporting to Drug Safety.","sortOrder":1},{"statementId":"a663X00000094MeQAI","statementType":"Note","statementLabel":"The information (in free text fields) must have been obtained legitimately and must be unambiguous, precise and clear. Only write facts, do not speculate","statementLabelText":"The information (in free text fields) must have been obtained legitimately and must be unambiguous, precise and clear. Only write facts, do not speculate","sortOrder":2}] | EG14: false | EJ14: false | EL14: ME | EM14: false | EP14: false | EQ14: ME | ET14: Call | EU14: Marketing | EW14: true | EX14: 17 | EY14: Non-Small Cell Lung Cancer | EZ14: https://roche-eu-oce--uat.sandbox.lightning.force.com/a2Q6900000992fI | FA14: 1 | FB14: false | FC14: false | FE14: 5 | FF14: false | FG14: 2 | FH14: dijana.stojanovski@roche.com.invalid | FI14: rudovid1 | FJ14: Core Non Promotional Customer Facing | FK14: false | FL14: false | FN14: Tecentriq | FO14: Core Non Promotional Customer Facing | FP14: Proactive | FT14: Dejan Perovic | FU14: Face To Face | FX14: 1 | FY14: PV/HCO | GC14: Tecentriq-Non-Small Cell Lung Cancer | GE14: Tecentriq-Non-Small Cell Lung Cancer | GF14: true | GH14: Dejan Perovic (Primary);Rade Kovac | GI14: 2023-11-03T13:49:03.000+0000 | GK14: false | GL14: ME | GM14: ME | GN14: false | GP14: Europe/Berlin | GR14: Dijana Stojanovski | GV14: Non-Promotional Face To Face | GY14: true | HF14: false
A15: [OCE__Call__c] | B15: a2Q69000009AIBmEAO | C15: 0057U000001eKP1QAM | D15: false | E15: C-00422149 | F15: EUR | G15: 0123X000000wzbXQAQ | H15: 2024-01-26T15:50:58.000+0000 | I15: 0057U000001eKP1QAM | J15: 2024-06-19T10:36:13.000+0000 | K15: 0057U000001Yt7KQAS | L15: 2024-06-19T10:36:13.000+0000 | P15: Dejan Perovic | U15: 0013X00003gWlCzQAK | V15: Brezovik Bb | AD15: Brezovik Bb, Nikšić, ME, 81400 | AE15: 2024-01-26T10:00:00.000+0000 | AJ15: Face To Face | AL15: Nikšić | AN15: false | AT15: 60 | AV15: 2024-01-26T11:00:00.000+0000 | BM15: false | BN15: false | BO15: false | BP15: false | BU15: a1J3X00000DYpE7UAL | BX15: false | BY15: false | CC15: 1 | CD15: 0 | CE15: 0 | CY15: false | DS15: Submitted | DU15: 2024-01-26T15:51:59.000+0000 | DX15: ME_CORE_TERR_007 | EC15: 81400 | EF15: [{"statementValidationType":"None","statementValidationResponse":"Skipped","statementType":"Note","statementLabelText":"Documenting Adverse Events (AE), Special Situations (SS), or Product Complaints (PC), in CRM does not constitute AE/SS/PC reporting to Drug Safety.","statementLabel":"Documenting Adverse Events (AE), Special Situations (SS), or Product Complaints (PC), in CRM does not constitute AE/SS/PC reporting to Drug Safety.","statementId":"a6669000007KfNLAA0","sortOrder":1},{"statementValidationType":"None","statementValidationResponse":"Skipped","statementType":"Note","statementLabelText":"The information (in free text fields) must have been obtained legitimately and must be unambiguous, precise and clear. Only write facts, do not speculate","statementLabel":"The information (in free text fields) must have been obtained legitimately and must be unambiguous, precise and clear. Only write facts, do not speculate","statementId":"a6669000007KfNMAA0","sortOrder":2}] | EG15: false | EH15: [ ] | EJ15: false | EL15: ME | EM15: false | EP15: false | EQ15: ME | ET15: Call | EU15: Marketing | EW15: false | EX15: 0 | EY15: Lung Cancer | EZ15: https://roche-eu-oce--uat.sandbox.lightning.force.com/a2Q69000009AIBm | FA15: 1 | FB15: false | FC15: false | FE15: 5 | FF15: false | FG15: 1 | FH15: dijana.stojanovski@roche.com.invalid | FI15: rudovid1 | FJ15: Core Non Promotional Customer Facing | FK15: false | FL15: false | FO15: Core Non Promotional Customer Facing | FP15: Responsive | FQ15: 1:1 Interaction | FT15: Dejan Perovic | FU15: Face To Face | FY15: PV/HCO | GC15: Lung Cancer | GD15: Not Required | GE15: Lung Cancer | GF15: true | GK15: false | GL15: ME | GM15: ME | GN15: false | GP15: Europe/Berlin | GR15: Dijana Stojanovski | GV15: Non-Promotional Face To Face | GY15: true | HF15: false
A16: [OCE__Call__c] | B16: a2Q69000009AvCnEAK | C16: 0057U000001eKP1QAM | D16: false | E16: C-00482001 | F16: EUR | G16: 0123X000000wzbXQAQ | H16: 2024-03-01T07:29:27.000+0000 | I16: 0057U000001eKP1QAM | J16: 2024-03-01T07:31:25.000+0000 | K16: 0053X00000BBu6fQAD | L16: 2024-03-01T07:31:25.000+0000 | P16: Dejan Perovic | U16: 0013X00003gWlCzQAK | V16: Brezovik Bb | AD16: Brezovik Bb, Nikšić, ME, 81400 | AE16: 2024-02-08T10:45:00.000+0000 | AJ16: Face To Face | AL16: Nikšić | AN16: false | AT16: 30 | AV16: 2024-02-08T11:15:00.000+0000 | BM16: false | BN16: false | BO16: false | BP16: false | BU16: a1J3X00000DYpE7UAL | BX16: false | BY16: false | CC16: 1 | CD16: 0 | CE16: 0 | CY16: false | DS16: Submitted | DU16: 2024-03-01T07:31:20.000+0000 | DX16: ME_CORE_TERR_007 | EC16: 81400 | EF16: [{"statementValidationType":"None","statementValidationResponse":"Skipped","statementType":"Note","statementLabelText":"Documenting Adverse Events (AE), Special Situations (SS), or Product Complaints (PC), in CRM does not constitute AE/SS/PC reporting to Drug Safety.","statementLabel":"Documenting Adverse Events (AE), Special Situations (SS), or Product Complaints (PC), in CRM does not constitute AE/SS/PC reporting to Drug Safety.","statementId":"a6669000007KfNLAA0","sortOrder":1},{"statementValidationType":"None","statementValidationResponse":"Skipped","statementType":"Note","statementLabelText":"The information (in free text fields) must have been obtained legitimately and must be unambiguous, precise and clear. Only write facts, do not speculate","statementLabel":"The information (in free text fields) must have been obtained legitimately and must be unambiguous, precise and clear. Only write facts, do not speculate","statementId":"a6669000007KfNMAA0","sortOrder":2}] | EG16: false | EH16: [ ] | EJ16: false | EL16: ME | EM16: false | EP16: false | EQ16: ME | ET16: Call | EU16: Marketing | EW16: true | EX16: 22 | EY16: Lung Cancer | EZ16: https://roche-eu-oce--uat.sandbox.lightning.force.com/a2Q69000009AvCn | FA16: 1 | FB16: false | FC16: false | FE16: 5 | FF16: false | FG16: 3 | FH16: dijana.stojanovski@roche.com.invalid | FI16: rudovid1 | FJ16: Core Non Promotional Customer Facing | FK16: false | FL16: false | FO16: Core Non Promotional Customer Facing | FP16: Proactive | FQ16: Group Interaction | FT16: Dejan Perovic | FU16: Face To Face | FX16: 1 | FY16: PV/HCO | GC16: Lung Cancer | GD16: Not Required | GE16: Lung Cancer | GF16: true | GK16: false | GL16: ME | GM16: ME | GN16: false | GP16: Europe/Berlin | GR16: Dijana Stojanovski | GV16: Non-Promotional Face To Face | GY16: true | HF16: false
A17: [OCE__Call__c] | B17: a2Q69000009C1U9EAK | C17: 0057U000001eKP1QAM | D17: false | E17: C-00589625 | F17: EUR | G17: 0123X000000wzbXQAQ | H17: 2024-05-03T20:03:18.000+0000 | I17: 0057U000001eKP1QAM | J17: 2024-05-03T20:04:48.000+0000 | K17: 0053X00000BBu6fQAD | L17: 2024-05-03T20:04:48.000+0000 | P17: Dejan Perovic | U17: 0013X00003gWlCzQAK | V17: Brezovik Bb | AD17: Brezovik Bb, Nikšić, ME, 81400 | AE17: 2024-03-07T11:00:00.000+0000 | AJ17: Face To Face | AL17: Nikšić | AN17: false | AT17: 30 | AV17: 2024-03-07T11:30:00.000+0000 | BM17: false | BN17: false | BO17: false | BP17: false | BU17: a1J3X00000DYpE7UAL | BX17: false | BY17: false | CC17: 1 | CD17: 0 | CE17: 0 | CY17: false | DS17: Submitted | DU17: 2024-05-03T20:04:43.000+0000 | DX17: ME_CORE_TERR_007 | EC17: 81400 | EF17: [{"statementValidationType":"None","statementValidationResponse":"Skipped","statementType":"Note","statementLabelText":"Documenting Adverse Events (AE), Special Situations (SS), or Product Complaints (PC), in CRM does not constitute AE/SS/PC reporting to Drug Safety.","statementLabel":"Documenting Adverse Events (AE), Special Situations (SS), or Product Complaints (PC), in CRM does not constitute AE/SS/PC reporting to Drug Safety.","statementId":"a6669000007KfNLAA0","sortOrder":1},{"statementValidationType":"None","statementValidationResponse":"Skipped","statementType":"Note","statementLabelText":"The information (in free text fields) must have been obtained legitimately and must be unambiguous, precise and clear. Only write facts, do not speculate","statementLabel":"The information (in free text fields) must have been obtained legitimately and must be unambiguous, precise and clear. Only write facts, do not speculate","statementId":"a6669000007KfNMAA0","sortOrder":2}] | EG17: false | EH17: [ ] | EJ17: false | EL17: ME | EM17: false | EP17: false | EQ17: ME | ET17: Call | EU17: Marketing | EW17: true | EX17: 57 | EY17: Lung Cancer | EZ17: https://roche-eu-oce--uat.sandbox.lightning.force.com/a2Q69000009C1U9 | FA17: 1 | FB17: false | FC17: false | FE17: 5 | FF17: false | FG17: 3 | FH17: dijana.stojanovski@roche.com.invalid | FI17: rudovid1 | FJ17: Core Non Promotional Customer Facing | FK17: false | FL17: false | FO17: Core Non Promotional Customer Facing | FP17: Proactive | FQ17: Group Interaction | FT17: Dejan Perovic | FU17: Face To Face | FX17: 1 | FY17: PV/HCO | GC17: Lung Cancer | GD17: Not Required | GE17: Lung Cancer | GF17: true | GK17: false | GL17: ME | GM17: ME | GN17: false | GP17: Europe/Berlin | GR17: Dijana Stojanovski | GV17: Non-Promotional Face To Face | GY17: true | HF17: false
A18: [OCE__Call__c] | B18: a2Q69000009C1UxEAK | C18: 0057U000001eKP1QAM | D18: false | E18: C-00589658 | F18: EUR | G18: 0123X000000wzbXQAQ | H18: 2024-05-03T20:19:55.000+0000 | I18: 0057U000001eKP1QAM | J18: 2024-05-03T20:20:50.000+0000 | K18: 0053X00000BBu6fQAD | L18: 2024-05-03T20:20:50.000+0000 | P18: Dejan Perovic | U18: 0013X00003gWlCzQAK | V18: Brezovik Bb | AD18: Brezovik Bb, Nikšić, ME, 81400 | AE18: 2024-03-21T10:45:00.000+0000 | AJ18: Face To Face | AL18: Nikšić | AN18: false | AT18: 15 | AV18: 2024-03-21T11:00:00.000+0000 | BM18: false | BN18: false | BO18: false | BP18: false | BU18: a1J3X00000DYpE7UAL | BX18: false | BY18: false | CC18: 1 | CD18: 0 | CE18: 0 | CY18: false | DS18: Submitted | DU18: 2024-05-03T20:20:44.000+0000 | DX18: ME_CORE_TERR_007 | EC18: 81400 | EF18: [{"statementValidationType":"None","statementValidationResponse":"Skipped","statementType":"Note","statementLabelText":"Documenting Adverse Events (AE), Special Situations (SS), or Product Complaints (PC), in CRM does not constitute AE/SS/PC reporting to Drug Safety.","statementLabel":"Documenting Adverse Events (AE), Special Situations (SS), or Product Complaints (PC), in CRM does not constitute AE/SS/PC reporting to Drug Safety.","statementId":"a6669000007KfNLAA0","sortOrder":1},{"statementValidationType":"None","statementValidationResponse":"Skipped","statementType":"Note","statementLabelText":"The information (in free text fields) must have been obtained legitimately and must be unambiguous, precise and clear. Only write facts, do not speculate","statementLabel":"The information (in free text fields) must have been obtained legitimately and must be unambiguous, precise and clear. Only write facts, do not speculate","statementId":"a6669000007KfNMAA0","sortOrder":2}] | EG18: false | EH18: [ ] | EJ18: false | EL18: ME | EM18: false | EP18: false | EQ18: ME | ET18: Call | EU18: Marketing | EW18: true | EX18: 43 | EY18: Lung Cancer | EZ18: https://roche-eu-oce--uat.sandbox.lightning.force.com/a2Q69000009C1Ux | FA18: 1 | FB18: false | FC18: false | FE18: 5 | FF18: false | FH18: dijana.stojanovski@roche.com.invalid | FI18: rudovid1 | FJ18: Core Non Promotional Customer Facing | FK18: false | FL18: false | FO18: Core Non Promotional Customer Facing | FP18: Responsive | FQ18: 1:1 Interaction | FT18: Dejan Perovic | FU18: Face To Face | FY18: PV/HCO | GC18: Lung Cancer | GD18: Not Required | GE18: Lung Cancer | GF18: true | GK18: false | GL18: ME | GM18: ME | GN18: false | GP18: Europe/Berlin | GR18: Dijana Stojanovski | GV18: Non-Promotional Face To Face | GY18: true | HF18: false
A19: [OCE__Call__c] | B19: a2Q69000009DINHEA4 | C19: 0057U000001eKP1QAM | D19: false | E19: C-00069573 | F19: EUR | G19: 0123X000000wzbXQAQ | H19: 2023-04-14T22:08:32.000+0000 | I19: 0057U000001eKP1QAM | J19: 2024-06-19T11:18:14.000+0000 | K19: 0057U000001Yt7KQAS | L19: 2024-06-19T11:18:14.000+0000 | P19: Dejan Perovic | Q19: Dejan Perovic | R19: [] | S19: [] | U19: 0013X00003gWlCzQAK | V19: BREZOVIK BB | AD19: BREZOVIK BB, Nikšić, ME, 81400 | AE19: 2023-04-05T22:00:00.000+0000 | AI19: Detail Only | AJ19: Face To Face | AL19: Nikšić | AN19: false | AT19: 60 | AV19: 2023-04-05T23:00:00.000+0000 | AW19: 0 | BM19: false | BN19: false | BO19: false | BP19: false | BU19: a1J3X00000DYpE7UAL | BX19: false | BY19: false | CC19: 1 | CD19: 0 | CE19: 0 | CY19: false | CZ19: [{"isAllowAccount":false,"accId":"0013X00003gWlCzQAK"}] | DS19: Submitted | DU19: 2023-04-14T22:08:32.000+0000 | DX19: ME_CORE_TERR_007 | EC19: 81400 | EF19: [{"statementId":"a663X00000094MjQAI","statementType":"Note","statementLabel":"Documenting an Adverse event (AE), Special Situation (SS), Product complaints (PC) in CRM does not constitute a AE/SS/PC reporting to Drug Safety.","statementLabelText":"Documenting an Adverse event (AE), Special Situation (SS), Product complaints (PC) in CRM does not constitute a AE/SS/PC reporting to Drug Safety.","sortOrder":1},{"statementId":"a663X00000094MeQAI","statementType":"Note","statementLabel":"The information (in free text fields) must have been obtained legitimately and must be unambiguous, precise and clear. Only write facts, do not speculate","statementLabelText":"The information (in free text fields) must have been obtained legitimately and must be unambiguous, precise and clear. Only write facts, do not speculate","sortOrder":2}] | EG19: false | EJ19: false | EL19: ME | EM19: false | EP19: false | EQ19: ME | ET19: Call | EU19: Marketing | EW19: true | EX19: 9 | EY19: Lung Cancer | EZ19: https://roche-eu-oce--uat.sandbox.lightning.force.com/a2Q69000009DINH | FA19: 1 | FB19: false | FC19: false | FE19: 5 | FF19: false | FG19: 1 | FH19: dijana.stojanovski@roche.com.invalid | FI19: rudovid1 | FJ19: Core Non Promotional Customer Facing | FK19: false | FL19: false | FO19: Core Non Promotional Customer Facing | FP19: Proactive | FT19: Dejan Perovic | FU19: Face To Face | FY19: PV/HCO | GC19: Lung Cancer | GE19: Lung Cancer | GF19: true | GK19: false | GL19: ME | GM19: ME | GN19: false | GP19: Europe/Berlin | GR19: Dijana Stojanovski | GV19: Non-Promotional Face To Face | GY19: true | HF19: false
A20: [OCE__Call__c] | B20: a2Q69000009PiwfEAC | C20: 0057U000001eKP1QAM | D20: false | E20: C-00099502 | F20: EUR | G20: 0123X000000wzbXQAQ | H20: 2023-06-08T12:32:40.000+0000 | I20: 0057U000001eKP1QAM | J20: 2024-06-19T11:55:54.000+0000 | K20: 0057U000001Yt7KQAS | L20: 2024-06-19T11:55:54.000+0000 | P20: Dejan Perovic | Q20: Dejan Perovic | R20: [] | S20: [] | U20: 0013X00003gWlCzQAK | V20: BREZOVIK BB | AD20: BREZOVIK BB, Nikšić, ME, 81400 | AE20: 2023-04-27T17:15:00.000+0000 | AI20: Detail Only | AJ20: Face To Face | AL20: Nikšić | AN20: false | AT20: 75 | AV20: 2023-04-27T18:30:00.000+0000 | AW20: 0 | BM20: false | BN20: false | BO20: false | BP20: false | BU20: a1J3X00000DYpE7UAL | BX20: false | BY20: false | CC20: 1 | CD20: 0 | CE20: 0 | CY20: false | CZ20: [{"isAllowAccount":false,"accId":"0013X00003gWlCzQAK"}] | DS20: Submitted | DU20: 2023-06-08T12:37:04.000+0000 | DX20: ME_CORE_TERR_007 | EC20: 81400 | EF20: [{"statementId":"a663X00000094MjQAI","statementType":"Note","statementLabel":"Documenting an Adverse event (AE), Special Situation (SS), Product complaints (PC) in CRM does not constitute a AE/SS/PC reporting to Drug Safety.","statementLabelText":"Documenting an Adverse event (AE), Special Situation (SS), Product complaints (PC) in CRM does not constitute a AE/SS/PC reporting to Drug Safety.","sortOrder":1},{"statementId":"a663X00000094MeQAI","statementType":"Note","statementLabel":"The information (in free text fields) must have been obtained legitimately and must be unambiguous, precise and clear. Only write facts, do not speculate","statementLabelText":"The information (in free text fields) must have been obtained legitimately and must be unambiguous, precise and clear. Only write facts, do not speculate","sortOrder":2}] | EG20: false | EJ20: false | EL20: ME | EM20: false | EP20: false | EQ20: ME | ET20: Call | EU20: Marketing | EW20: true | EX20: 42 | EY20: Lung Cancer | EZ20: https://roche-eu-oce--uat.sandbox.lightning.force.com/a2Q69000009Piwf | FA20: 1 | FB20: false | FC20: false | FE20: 5 | FF20: false | FG20: 1 | FH20: dijana.stojanovski@roche.com.invalid | FI20: rudovid1 | FJ20: Core Non Promotional Customer Facing | FK20: false | FL20: false | FO20: Core Non Promotional Customer Facing | FP20: Proactive | FT20: Dejan Perovic | FU20: Face To Face | FY20: PV/HCO | GC20: Lung Cancer | GE20: Lung Cancer | GF20: true | GK20: false | GL20: ME | GM20: ME | GN20: false | GP20: Europe/Berlin | GR20: Dijana Stojanovski | GV20: Non-Promotional Face To Face | GY20: true | HF20: false
A21: [OCE__Call__c] | B21: a2Q69000009PjWkEAK | C21: 0057U000001eKP1QAM | D21: false | E21: C-00100297 | F21: EUR | G21: 0123X000000wzbXQAQ | H21: 2023-06-09T11:29:11.000+0000 | I21: 0057U000001eKP1QAM | J21: 2024-06-19T11:56:57.000+0000 | K21: 0057U000001Yt7KQAS | L21: 2024-06-19T11:56:57.000+0000 | P21: Dejan Perovic | Q21: Dejan Perovic | R21: [] | S21: [] | U21: 0013X00003gWlCzQAK | V21: BREZOVIK BB | AD21: BREZOVIK BB, Nikšić, ME, 81400 | AE21: 2023-05-04T08:00:00.000+0000 | AI21: Detail Only | AJ21: Face To Face | AL21: Nikšić | AN21: false | AT21: 60 | AV21: 2023-05-04T09:00:00.000+0000 | AW21: 0 | BM21: false | BN21: false | BO21: false | BP21: false | BU21: a1J3X00000DYpE7UAL | BX21: false | BY21: false | CC21: 1 | CD21: 0 | CE21: 0 | CY21: false | CZ21: [{"isAllowAccount":false,"accId":"0013X00003gWlCzQAK"}] | DS21: Submitted | DU21: 2023-06-09T11:29:10.000+0000 | DX21: ME_CORE_TERR_007 | EC21: 81400 | EF21: [{"statementId":"a663X00000094MjQAI","statementType":"Note","statementLabel":"Documenting an Adverse event (AE), Special Situation (SS), Product complaints (PC) in CRM does not constitute a AE/SS/PC reporting to Drug Safety.","statementLabelText":"Documenting an Adverse event (AE), Special Situation (SS), Product complaints (PC) in CRM does not constitute a AE/SS/PC reporting to Drug Safety.","sortOrder":1},{"statementId":"a663X00000094MeQAI","statementType":"Note","statementLabel":"The information (in free text fields) must have been obtained legitimately and must be unambiguous, precise and clear. Only write facts, do not speculate","statementLabelText":"The information (in free text fields) must have been obtained legitimately and must be unambiguous, precise and clear. Only write facts, do not speculate","sortOrder":2}] | EG21: false | EJ21: false | EL21: ME | EM21: false | EP21: false | EQ21: ME | ET21: Call | EU21: Marketing | EW21: true | EX21: 36 | EY21: Lung Cancer | EZ21: https://roche-eu-oce--uat.sandbox.lightning.force.com/a2Q69000009PjWk | FA21: 1 | FB21: false | FC21: false | FE21: 5 | FF21: false | FG21: 1 | FH21: dijana.stojanovski@roche.com.invalid | FI21: rudovid1 | FJ21: Core Non Promotional Customer Facing | FK21: false | FL21: false | FO21: Core Non Promotional Customer Facing | FP21: Responsive | FT21: Dejan Perovic | FU21: Face To Face | FY21: PV/HCO | GC21: Lung Cancer | GE21: Lung Cancer | GF21: true | GK21: false | GL21: ME | GM21: ME | GN21: false | GP21: Europe/Berlin | GR21: Dijana Stojanovski | GV21: Non-Promotional Face To Face | GY21: true | HF21: false
A22: [OCE__Call__c] | B22: a2Q69000009Px28EAC | C22: 0057U000001eKP1QAM | D22: false | E22: C-00114214 | F22: EUR | G22: 0123X000000wzbXQAQ | H22: 2023-06-25T17:11:32.000+0000 | I22: 0057U000001eKP1QAM | J22: 2024-06-19T10:15:00.000+0000 | K22: 0057U000001Yt7KQAS | L22: 2024-06-19T10:15:00.000+0000 | P22: Dejan Perovic | Q22: Dejan Perovic | R22: [] | S22: [] | U22: 0013X00003gWlCzQAK | V22: BREZOVIK BB | AD22: BREZOVIK BB, Nikšić, ME, 81400 | AE22: 2023-06-23T11:15:00.000+0000 | AI22: Detail Only | AJ22: Face To Face | AL22: Nikšić | AN22: false | AT22: 45 | AV22: 2023-06-23T12:00:00.000+0000 | AW22: 0 | BM22: false | BN22: false | BO22: false | BP22: false | BU22: a1J3X00000DYpE7UAL | BX22: false | BY22: false | CC22: 1 | CD22: 0 | CE22: 0 | CY22: false | CZ22: [{"isAllowAccount":false,"accId":"0013X00003gWlCzQAK"}] | DS22: Submitted | DU22: 2023-07-10T07:10:58.000+0000 | DX22: ME_CORE_TERR_007 | EC22: 81400 | EF22: [{"statementId":"a663X00000094MjQAI","statementType":"Note","statementLabel":"Documenting an Adverse event (AE), Special Situation (SS), Product complaints (PC) in CRM does not constitute a AE/SS/PC reporting to Drug Safety.","statementLabelText":"Documenting an Adverse event (AE), Special Situation (SS), Product complaints (PC) in CRM does not constitute a AE/SS/PC reporting to Drug Safety.","sortOrder":1},{"statementId":"a663X00000094MeQAI","statementType":"Note","statementLabel":"The information (in free text fields) must have been obtained legitimately and must be unambiguous, precise and clear. Only write facts, do not speculate","statementLabelText":"The information (in free text fields) must have been obtained legitimately and must be unambiguous, precise and clear. Only write facts, do not speculate","sortOrder":2}] | EG22: false | EJ22: false | EL22: ME | EM22: false | EP22: false | EQ22: ME | ET22: Call | EU22: Marketing | EW22: true | EX22: 17 | EY22: Lung Cancer | EZ22: https://roche-eu-oce--uat.sandbox.lightning.force.com/a2Q69000009Px28 | FA22: 1 | FB22: false | FC22: false | FE22: 5 | FF22: false | FG22: 1 | FH22: dijana.stojanovski@roche.com.invalid | FI22: rudovid1 | FJ22: Core Non Promotional Customer Facing | FK22: false | FL22: false | FO22: Core Non Promotional Customer Facing | FP22: Proactive | FT22: Dejan Perovic | FU22: Face To Face | FY22: PV/HCO | GC22: Lung Cancer | GE22: Lung Cancer | GF22: true | GK22: false | GL22: ME | GM22: ME | GN22: false | GP22: Europe/Berlin | GR22: Dijana Stojanovski | GV22: Non-Promotional Face To Face | GY22: true | HF22: false
A23: [OCE__Call__c] | B23: a2Q69000009QaxCEAS | C23: 0057U000001eKP1QAM | D23: false | E23: C-00170145 | F23: EUR | G23: 0123X000000wzbXQAQ | H23: 2023-07-26T13:04:37.000+0000 | I23: 0057U000001eKP1QAM | J23: 2024-06-19T09:58:35.000+0000 | K23: 0057U000001Yt7KQAS | L23: 2024-06-19T09:58:35.000+0000 | P23: Dejan Perovic | Q23: Dejan Perovic | R23: [] | S23: [] | U23: 0013X00003gWlCzQAK | V23: BREZOVIK BB | AD23: BREZOVIK BB, Nikšić, ME, 81400 | AE23: 2023-07-11T10:15:00.000+0000 | AI23: Detail Only | AJ23: Face To Face | AL23: Nikšić | AN23: false | AT23: 45 | AV23: 2023-07-11T11:00:00.000+0000 | AW23: 0 | BM23: false | BN23: false | BO23: false | BP23: false | BU23: a1J3X00000DYpE7UAL | BX23: false | BY23: false | CC23: 1 | CD23: 0 | CE23: 0 | CY23: false | CZ23: [{"isAllowAccount":false,"accId":"0013X00003gWlCzQAK"}] | DS23: Submitted | DU23: 2023-07-27T16:53:12.000+0000 | DX23: ME_CORE_TERR_007 | EC23: 81400 | EF23: [{"statementId":"a663X00000094MjQAI","statementType":"Note","statementLabel":"Documenting an Adverse event (AE), Special Situation (SS), Product complaints (PC) in CRM does not constitute a AE/SS/PC reporting to Drug Safety.","statementLabelText":"Documenting an Adverse event (AE), Special Situation (SS), Product complaints (PC) in CRM does not constitute a AE/SS/PC reporting to Drug Safety.","sortOrder":1},{"statementId":"a663X00000094MeQAI","statementType":"Note","statementLabel":"The information (in free text fields) must have been obtained legitimately and must be unambiguous, precise and clear. Only write facts, do not speculate","statementLabelText":"The information (in free text fields) must have been obtained legitimately and must be unambiguous, precise and clear. Only write facts, do not speculate","sortOrder":2}] | EG23: false | EJ23: false | EL23: ME | EM23: false | EP23: false | EQ23: ME | ET23: Call | EU23: Marketing | EW23: true | EX23: 16 | EY23: Lung Cancer | EZ23: https://roche-eu-oce--uat.sandbox.lightning.force.com/a2Q69000009QaxC | FA23: 1 | FB23: false | FC23: false | FE23: 5 | FF23: false | FG23: 1 | FH23: dijana.stojanovski@roche.com.invalid | FI23: rudovid1 | FJ23: Core Non Promotional Customer Facing | FK23: false | FL23: false | FO23: Core Non Promotional Customer Facing | FP23: Proactive | FT23: Dejan Perovic | FU23: Face To Face | FY23: PV/HCO | GC23: Lung Cancer | GE23: Lung Cancer | GF23: true | GK23: false | GL23: ME | GM23: ME | GN23: false | GP23: Europe/Berlin | GR23: Dijana Stojanovski | GV23: Non-Promotional Face To Face | GY23: true | HF23: false
A24: [OCE__Call__c] | B24: a2Q69000009YrYTEA0 | C24: 0057U000001eKP1QAM | D24: false | E24: C-00205242 | F24: EUR | G24: 0123X000000wzbXQAQ | H24: 2023-09-01T07:26:18.000+0000 | I24: 0057U000001eKP1QAM | J24: 2024-06-19T14:23:28.000+0000 | K24: 0057U000001Yt7KQAS | L24: 2024-06-19T14:23:28.000+0000 | P24: Dejan Perovic | Q24: Dejan Perovic | R24: [] | S24: [] | U24: 0013X00003gWlCzQAK | V24: Brezovik Bb | AD24: Brezovik Bb, Nikšić, ME, 81400 | AE24: 2023-08-31T10:00:00.000+0000 | AI24: Detail Only | AJ24: Face To Face | AL24: Nikšić | AN24: false | AT24: 30 | AV24: 2023-08-31T10:30:00.000+0000 | AW24: 0 | BM24: false | BN24: false | BO24: false | BP24: false | BU24: a1J3X00000DYpE7UAL | BX24: false | BY24: false | CC24: 1 | CD24: 0 | CE24: 0 | CY24: false | CZ24: [{"isAllowAccount":false,"accId":"0013X00003gWlCzQAK"}] | DS24: Submitted | DU24: 2023-09-01T07:28:05.000+0000 | DX24: ME_CORE_TERR_007 | EC24: 81400 | EF24: [{"statementId":"a663X00000094MjQAI","statementType":"Note","statementLabel":"Documenting an Adverse event (AE), Special Situation (SS), Product complaints (PC) in CRM does not constitute a AE/SS/PC reporting to Drug Safety.","statementLabelText":"Documenting an Adverse event (AE), Special Situation (SS), Product complaints (PC) in CRM does not constitute a AE/SS/PC reporting to Drug Safety.","sortOrder":1},{"statementId":"a663X00000094MeQAI","statementType":"Note","statementLabel":"The information (in free text fields) must have been obtained legitimately and must be unambiguous, precise and clear. Only write facts, do not speculate","statementLabelText":"The information (in free text fields) must have been obtained legitimately and must be unambiguous, precise and clear. Only write facts, do not speculate","sortOrder":2}] | EG24: false | EJ24: false | EL24: ME | EM24: false | EP24: false | EQ24: ME | ET24: Call | EU24: Marketing | EW24: false | EX24: 1 | EY24: Lung Cancer | EZ24: https://roche-eu-oce--uat.sandbox.lightning.force.com/a2Q69000009YrYT | FA24: 1 | FB24: false | FC24: false | FE24: 5 | FF24: false | FG24: 1 | FH24: dijana.stojanovski@roche.com.invalid | FI24: rudovid1 | FJ24: Core Non Promotional Customer Facing | FK24: false | FL24: false | FO24: Core Non Promotional Customer Facing | FP24: Responsive | FT24: Dejan Perovic | FU24: Face To Face | FY24: PV/HCO | GC24: Lung Cancer | GE24: Lung Cancer | GF24: true | GK24: false | GL24: ME | GM24: ME | GN24: false | GP24: Europe/Berlin | GR24: Dijana Stojanovski | GV24: Non-Promotional Face To Face | GY24: true | HF24: false
A25: [OCE__Call__c] | B25: a2Q69000009ZWvIEAW | C25: 0057U000001eKP1QAM | D25: false | E25: C-00265122 | F25: EUR | G25: 0123X000000wzbXQAQ | H25: 2023-10-10T13:09:18.000+0000 | I25: 0057U000001eKP1QAM | J25: 2024-06-19T15:44:46.000+0000 | K25: 0057U000001Yt7KQAS | L25: 2024-06-19T15:44:46.000+0000 | P25: Dejan Perovic | Q25: Dejan Perovic | R25: [] | S25: [] | U25: 0013X00003gWlCzQAK | V25: Brezovik Bb | AD25: Brezovik Bb, Nikšić, ME, 81400 | AE25: 2023-09-19T09:30:00.000+0000 | AI25: Detail Only | AJ25: Face To Face | AL25: Nikšić | AN25: false | AT25: 30 | AV25: 2023-09-19T10:00:00.000+0000 | AW25: 0 | BM25: false | BN25: false | BO25: false | BP25: false | BU25: a1J3X00000DYpE7UAL | BX25: false | BY25: false | CC25: 1 | CD25: 0 | CE25: 0 | CY25: false | CZ25: [{"isAllowAccount":false,"accId":"0013X00003gWlCzQAK"}] | DS25: Submitted | DU25: 2023-10-10T13:39:26.000+0000 | DX25: ME_CORE_TERR_007 | EC25: 81400 | EF25: [{"statementId":"a663X00000094MjQAI","statementType":"Note","statementLabel":"Documenting an Adverse event (AE), Special Situation (SS), Product complaints (PC) in CRM does not constitute a AE/SS/PC reporting to Drug Safety.","statementLabelText":"Documenting an Adverse event (AE), Special Situation (SS), Product complaints (PC) in CRM does not constitute a AE/SS/PC reporting to Drug Safety.","sortOrder":1},{"statementId":"a663X00000094MeQAI","statementType":"Note","statementLabel":"The information (in free text fields) must have been obtained legitimately and must be unambiguous, precise and clear. Only write facts, do not speculate","statementLabelText":"The information (in free text fields) must have been obtained legitimately and must be unambiguous, precise and clear. Only write facts, do not speculate","sortOrder":2}] | EG25: false | EJ25: false | EL25: ME | EM25: false | EP25: false | EQ25: ME | ET25: Call | EU25: Marketing | EW25: true | EX25: 21 | EY25: Lung Cancer | EZ25: https://roche-eu-oce--uat.sandbox.lightning.force.com/a2Q69000009ZWvI | FA25: 1 | FB25: false | FC25: false | FE25: 5 | FF25: false | FG25: 1 | FH25: dijana.stojanovski@roche.com.invalid | FI25: rudovid1 | FJ25: Core Non Promotional Customer Facing | FK25: false | FL25: false | FO25: Core Non Promotional Customer Facing | FP25: Proactive | FT25: Dejan Perovic | FU25: Face To Face | FY25: PV/HCO | GC25: Lung Cancer | GE25: Lung Cancer | GF25: true | GK25: false | GL25: ME | GM25: ME | GN25: false | GP25: Europe/Berlin | GR25: Dijana Stojanovski | GV25: Non-Promotional Face To Face | GY25: true | HF25: false
A26: [OCE__Call__c] | B26: a2QSe000001dFzVMAU | C26: 0057U000001eKP1QAM | D26: false | E26: C-00715938 | F26: EUR | G26: 0123X000000wzbXQAQ | H26: 2024-07-22T13:36:13.000+0000 | I26: 0057U000001eKP1QAM | J26: 2024-07-22T13:37:35.000+0000 | K26: 0053X00000BBu6fQAD | L26: 2024-07-22T13:37:35.000+0000 | P26: Dejan Perovic | Q26: Dejan Perovic | U26: 0013X00003gWlCzQAK | V26: Brezovik Bb | AD26: Brezovik Bb, Nikšić, ME, 81400 | AE26: 2024-06-27T10:00:00.000+0000 | AJ26: Face To Face | AL26: Nikšić | AN26: false | AT26: 75 | AV26: 2024-06-27T11:15:00.000+0000 | BM26: false | BN26: false | BO26: false | BP26: false | BU26: a1J3X00000DYpE7UAL | BX26: false | BY26: false | CC26: 1 | CD26: 0 | CE26: 0 | CY26: false | DS26: Submitted | DU26: 2024-07-22T13:37:29.000+0000 | DX26: ME_CORE_TERR_007 | EC26: 81400 | EF26: [{"statementValidationType":"None","statementValidationResponse":"Skipped","statementType":"Note","statementLabelText":"Documenting Adverse Events (AE), Special Situations (SS), or Product Complaints (PC), in CRM does not constitute AE/SS/PC reporting to Drug Safety.","statementLabel":"Documenting Adverse Events (AE), Special Situations (SS), or Product Complaints (PC), in CRM does not constitute AE/SS/PC reporting to Drug Safety.","statementId":"a6669000007KfNLAA0","sortOrder":1},{"statementValidationType":"None","statementValidationResponse":"Skipped","statementType":"Note","statementLabelText":"The information (in free text fields) must have been obtained legitimately and must be unambiguous, precise and clear. Only write facts, do not speculate","statementLabel":"The information (in free text fields) must have been obtained legitimately and must be unambiguous, precise and clear. Only write facts, do not speculate","statementId":"a6669000007KfNMAA0","sortOrder":2}] | EG26: false | EH26: [ ] | EJ26: false | EL26: ME | EM26: false | EP26: false | EQ26: ME | ET26: Call | EU26: Marketing | EW26: true | EX26: 25 | EY26: Non-Small Cell Lung Cancer | EZ26: https://roche-eu-oce--uat.sandbox.lightning.force.com/a2QSe000001dFzV | FA26: 1 | FB26: false | FC26: false | FE26: 5 | FF26: false | FG26: 3 | FH26: dijana.stojanovski@roche.com.invalid | FI26: rudovid1 | FJ26: Core Non Promotional Customer Facing | FK26: false | FL26: false | FN26: Tecentriq | FO26: Core Non Promotional Customer Facing | FP26: Proactive | FQ26: Group Interaction | FT26: Dejan Perovic | FU26: Face To Face | FX26: 1 | FY26: PV/HCO | GC26: Tecentriq-Non-Small Cell Lung Cancer | GD26: Not Required | GE26: Tecentriq-Non-Small Cell Lung Cancer | GF26: true | GH26: Dejan Perovic (Primary);Rade Kovac | GI26: 2024-07-22T13:37:09.000+0000 | GK26: false | GL26: ME | GM26: ME | GN26: false | GP26: Europe/Berlin | GR26: Dijana Stojanovski | GV26: Non-Promotional Face To Face | GY26: true | HF26: false
A27: [OCE__Call__c] | B27: a2QSe000004MZxhMAG | C27: 0057U000001eKP1QAM | D27: false | E27: C-01159047 | F27: EUR | G27: 0123X000000wzbXQAQ | H27: 2025-04-27T09:07:15.000+0000 | I27: 0057U000001eKP1QAM | J27: 2025-04-27T09:16:59.000+0000 | K27: 0053X00000BBu6fQAD | L27: 2025-04-27T09:16:59.000+0000 | P27: Dejan Perovic | Q27: Dejan Perovic | U27: 0013X00003gWlCzQAK | V27: Brezovik Bb | AD27: Brezovik Bb, Nikšić, ME, 81400 | AE27: 2025-04-25T09:30:00.000+0000 | AJ27: Face To Face | AL27: Nikšić | AN27: false | AT27: 30 | AV27: 2025-04-25T10:00:00.000+0000 | BM27: false | BN27: false | BO27: true | BP27: false | BU27: a1J3X00000DYpE7UAL | BX27: false | BY27: false | CC27: 1 | CD27: 0 | CE27: 0 | CY27: false | DS27: Submitted | DU27: 2025-04-27T09:16:50.000+0000 | DX27: ME_CORE_TERR_007 | EC27: 81400 | EF27: [{"statementValidationType":"None","statementValidationResponse":"Skipped","statementType":"Note","statementLabelText":"Documenting Adverse Events (AE), Special Situations (SS), or Product Complaints (PC), in CRM does not constitute AE/SS/PC reporting to Drug Safety.","statementLabel":"Documenting Adverse Events (AE), Special Situations (SS), or Product Complaints (PC), in CRM does not constitute AE/SS/PC reporting to Drug Safety.","statementId":"a6669000007KfNLAA0","sortOrder":1},{"statementValidationType":"None","statementValidationResponse":"Skipped","statementType":"Note","statementLabelText":"The information (in free text fields) must have been obtained legitimately and must be unambiguous, precise and clear. Only write facts, do not speculate","statementLabel":"The information (in free text fields) must have been obtained legitimately and must be unambiguous, precise and clear. Only write facts, do not speculate","statementId":"a6669000007KfNMAA0","sortOrder":2}] | EG27: false | EH27: [ ] | EJ27: false | EL27: ME | EM27: false | EP27: false | EQ27: ME | ET27: Call | EU27: Marketing | EW27: false | EX27: 2 | EY27: Lung Cancer | EZ27: https://roche-eu-oce--uat.sandbox.lightning.force.com/a2QSe000004MZxh | FA27: 1 | FB27: false | FC27: false | FE27: 5 | FF27: false | FG27: 3 | FH27: dijana.stojanovski@roche.com.invalid | FI27: rudovid1 | FJ27: Core Non Promotional Customer Facing | FK27: false | FL27: false | FO27: Core Non Promotional Customer Facing | FP27: Responsive | FQ27: Group Interaction | FT27: Dejan Perovic | FU27: Face To Face | FX27: 1 | FY27: PV/HCO | GC27: Lung Cancer | GD27: Not Required | GE27: Lung Cancer | GF27: true | GH27: Dejan Perovic (Primary);Rade Kovac | GI27: 2025-04-27T09:08:25.000+0000 | GK27: false | GL27: ME | GM27: ME | GN27: false | GP27: Europe/Berlin | GR27: Dijana Stojanovski | GV27: Non-Promotional Face To Face | GY27: true | HC27: MD | HF27: false
A28: [OCE__Call__c] | B28: a2QSe000006R4iPMAS | C28: 0053X00000E3yMaQAJ | D28: false | E28: C-01386118 | F28: RSD | G28: 0123X000000wzbXQAQ | H28: 2025-08-28T10:15:07.000+0000 | I28: 0053X00000E3yMaQAJ | J28: 2025-08-28T10:19:36.000+0000 | K28: 0053X00000BBu6fQAD | L28: 2025-08-28T10:19:36.000+0000 | P28: Dejan Perovic | Q28: Dejan Perovic | U28: 0013X00003gWlCzQAK | AE28: 2025-08-26T11:00:00.000+0000 | AJ28: Face To Face | AN28: false | AT28: 30 | AV28: 2025-08-26T11:30:00.000+0000 | BM28: false | BN28: false | BO28: false | BP28: false | BX28: false | BY28: false | CC28: 1 | CD28: 0 | CE28: 0 | CY28: false | DS28: Submitted | DU28: 2025-08-28T10:19:31.000+0000 | DX28: ME_CORE_TERR_002 | EF28: [{"statementValidationType":"None","statementValidationResponse":"Skipped","statementType":"Note","statementLabelText":"Documenting Adverse Events (AE), Special Situations (SS), or Product Complaints (PC), in CRM does not constitute AE/SS/PC reporting to Drug Safety.","statementLabel":"Documenting Adverse Events (AE), Special Situations (SS), or Product Complaints (PC), in CRM does not constitute AE/SS/PC reporting to Drug Safety.","statementId":"a6669000007KfNLAA0","sortOrder":1},{"statementValidationType":"None","statementValidationResponse":"Skipped","statementType":"Note","statementLabelText":"The information (in free text fields) must have been obtained legitimately and must be unambiguous, precise and clear. Only write facts, do not speculate","statementLabel":"The information (in free text fields) must have been obtained legitimately and must be unambiguous, precise and clear. Only write facts, do not speculate","statementId":"a6669000007KfNMAA0","sortOrder":2}] | EG28: false | EH28: [ ] | EJ28: false | EM28: false | EP28: false | EQ28: ME | ET28: Call | EU28: Marketing | EW28: false | EX28: 2 | EY28: Non-Small Cell Lung Cancer | EZ28: https://roche-eu-oce--uat.sandbox.lightning.force.com/a2QSe000006R4iP | FA28: 1 | FB28: false | FC28: false | FE28: 5 | FF28: false | FH28: milos.radjenovic@roche.com.invalid | FI28: radjenom | FJ28: Core Non Promotional Customer Facing | FK28: false | FL28: false | FN28: Tecentriq | FO28: Core Non Promotional Customer Facing | FP28: Proactive | FT28: Dejan Perovic | FU28: Face To Face | FY28: PV/HCO | GC28: Tecentriq-Non-Small Cell Lung Cancer | GD28: Not Required | GE28: Tecentriq-Non-Small Cell Lung Cancer | GF28: true | GK28: false | GL28: RS | GM28: ME | GN28: false | GP28: Europe/Berlin | GR28: Milos Radjenovic | GV28: Non-Promotional Face To Face | GY28: true | HC28: MD | HF28: false
A29: [OCE__Call__c] | B29: a2QSe000006c922MAA | C29: 0053X00000E3yMaQAJ | D29: false | E29: C-01422365 | F29: RSD | G29: 0123X000000wzbXQAQ | H29: 2025-09-17T12:25:12.000+0000 | I29: 0053X00000E3yMaQAJ | J29: 2025-09-17T12:26:16.000+0000 | K29: 0053X00000BBu6fQAD | L29: 2025-09-17T12:26:16.000+0000 | P29: Dejan Perovic | Q29: Dejan Perovic | U29: 0013X00003gWlCzQAK | V29: Brezovik Bb | AD29: Brezovik Bb, Nikšić, ME, 81400 | AE29: 2025-09-16T07:30:00.000+0000 | AJ29: Face To Face | AL29: Nikšić | AN29: false | AT29: 15 | AV29: 2025-09-16T07:45:00.000+0000 | BM29: false | BN29: false | BO29: false | BP29: false | BU29: a1J3X00000DYpE7UAL | BX29: false | BY29: false | CC29: 1 | CD29: 0 | CE29: 0 | CY29: false | DS29: Submitted | DU29: 2025-09-17T12:26:09.000+0000 | DX29: ME_CORE_TERR_002 | EC29: 81400 | EF29: [{"statementValidationType":"None","statementValidationResponse":"Skipped","statementType":"Note","statementLabelText":"Documenting Adverse Events (AE), Special Situations (SS), or Product Complaints (PC), in CRM does not constitute AE/SS/PC reporting to Drug Safety.","statementLabel":"Documenting Adverse Events (AE), Special Situations (SS), or Product Complaints (PC), in CRM does not constitute AE/SS/PC reporting to Drug Safety.","statementId":"a6669000007KfNLAA0","sortOrder":1},{"statementValidationType":"None","statementValidationResponse":"Skipped","statementType":"Note","statementLabelText":"The information (in free text fields) must have been obtained legitimately and must be unambiguous, precise and clear. Only write facts, do not speculate","statementLabel":"The information (in free text fields) must have been obtained legitimately and must be unambiguous, precise and clear. Only write facts, do not speculate","statementId":"a6669000007KfNMAA0","sortOrder":2}] | EG29: false | EH29: [ ] | EI29: [ ] | EJ29: false | EL29: ME | EM29: false | EP29: false | EQ29: ME | ET29: Call | EU29: Marketing | EW29: false | EX29: 1 | EY29: Non-Small Cell Lung Cancer | EZ29: https://roche-eu-oce--uat.sandbox.lightning.force.com/a2QSe000006c922 | FA29: 1 | FB29: false | FC29: false | FE29: 5 | FF29: false | FH29: milos.radjenovic@roche.com.invalid | FI29: radjenom | FJ29: Core Non Promotional Customer Facing | FK29: false | FL29: false | FN29: Tecentriq | FO29: Core Non Promotional Customer Facing | FP29: Proactive | FT29: Dejan Perovic | FU29: Face To Face | FY29: PV/HCO | GC29: Tecentriq-Non-Small Cell Lung Cancer | GD29: Not Required | GE29: Tecentriq-Non-Small Cell Lung Cancer | GF29: true | GK29: false | GL29: RS | GM29: ME | GN29: false | GP29: Europe/Berlin | GR29: Milos Radjenovic | GV29: Non-Promotional Face To Face | GY29: true | HC29: MD | HF29: false
A30: [OCE__Call__c] | B30: a2QSe000006ny9FMAQ | C30: 0053X00000E3yMaQAJ | D30: false | E30: C-01463203 | F30: RSD | G30: 0123X000000wzbXQAQ | H30: 2025-10-05T08:41:12.000+0000 | I30: 0053X00000E3yMaQAJ | J30: 2025-10-05T08:46:52.000+0000 | K30: 0053X00000BBu6fQAD | L30: 2025-10-05T08:46:52.000+0000 | P30: Dejan Perovic | Q30: Dejan Perovic | U30: 0013X00003gWlCzQAK | V30: Brezovik Bb | AD30: Brezovik Bb, Nikšić, ME, 81400 | AE30: 2025-10-03T19:00:00.000+0000 | AJ30: Face To Face | AL30: Nikšić | AN30: false | AT30: 120 | AV30: 2025-10-03T21:00:00.000+0000 | BM30: false | BN30: false | BO30: false | BP30: false | BU30: a1J3X00000DYpE7UAL | BX30: false | BY30: false | CC30: 1 | CD30: 0 | CE30: 0 | CY30: false | DS30: Submitted | DU30: 2025-10-05T08:46:48.000+0000 | DX30: ME_CORE_TERR_002 | EC30: 81400 | EF30: [{"statementValidationType":"None","statementValidationResponse":"Skipped","statementType":"Note","statementLabelText":"Documenting Adverse Events (AE), Special Situations (SS), or Product Complaints (PC), in CRM does not constitute AE/SS/PC reporting to Drug Safety.","statementLabel":"Documenting Adverse Events (AE), Special Situations (SS), or Product Complaints (PC), in CRM does not constitute AE/SS/PC reporting to Drug Safety.","statementId":"a6669000007KfNLAA0","sortOrder":1},{"statementValidationType":"None","statementValidationResponse":"Skipped","statementType":"Note","statementLabelText":"The information (in free text fields) must have been obtained legitimately and must be unambiguous, precise and clear. Only write facts, do not speculate","statementLabel":"The information (in free text fields) must have been obtained legitimately and must be unambiguous, precise and clear. Only write facts, do not speculate","statementId":"a6669000007KfNMAA0","sortOrder":2}] | EG30: false | EH30: [ ] | EI30: [ ] | EJ30: false | EK30: a3cSe000000iCOrIAM | EL30: ME | EM30: false | EP30: false | EQ30: ME | ET30: Call | EU30: Marketing | EW30: false | EX30: 2 | EY30: Non-Small Cell Lung Cancer | EZ30: https://roche-eu-oce--uat.sandbox.lightning.force.com/a2QSe000006ny9F | FA30: 1 | FB30: false | FC30: false | FE30: 5 | FF30: false | FH30: milos.radjenovic@roche.com.invalid | FI30: radjenom | FJ30: Core Non Promotional Customer Facing | FK30: false | FL30: false | FN30: Tecentriq | FO30: Core Non Promotional Customer Facing | FP30: Proactive | FT30: Dejan Perovic | FU30: Face To Face | FY30: PV/HCO | GC30: Tecentriq-Non-Small Cell Lung Cancer | GD30: Not Required | GE30: Tecentriq-Non-Small Cell Lung Cancer | GF30: true | GK30: false | GL30: RS | GM30: ME | GN30: false | GP30: Europe/Berlin | GR30: Milos Radjenovic | GV30: Non-Promotional Face To Face | GY30: true | HC30: MD | HF30: false
A31: [OCE__Call__c] | B31: a2Q69000009DGPmEAO | C31: 0053X00000E3yQCQAZ | D31: false | E31: C-00067947 | F31: EUR | G31: 0123X000000wzbXQAQ | H31: 2023-04-12T07:24:23.000+0000 | I31: 0053X00000E3yQCQAZ | J31: 2024-06-19T11:16:28.000+0000 | K31: 0057U000001Yt7KQAS | L31: 2024-06-19T11:16:28.000+0000 | P31: Anka Popovic | Q31: Anka Popovic | R31: [] | S31: [] | U31: 0013X00003gWlD2QAK | V31: LJUBLJANSKA BB | AD31: LJUBLJANSKA BB, Podgorica, ME, 81000 | AE31: 2023-03-28T10:10:00.000+0000 | AI31: Detail Only | AJ31: Face To Face | AL31: Podgorica | AN31: false | AT31: 15 | AV31: 2023-03-28T10:25:00.000+0000 | AW31: 0 | BM31: false | BN31: false | BO31: false | BP31: false | BU31: a1J3X00000DYpEeUAL | BX31: false | BY31: false | CB31: Gathering insights about number of newly diagnosed DLBCL in MNE | CC31: 1 | CD31: 0 | CE31: 0 | CY31: false | CZ31: [{"isAllowAccount":false,"accId":"0013X00003gWlD2QAK"}] | DS31: Submitted | DU31: 2023-04-12T07:26:05.000+0000 | DX31: ME_CORE_TERR_004 | EC31: 81000 | EF31: [{"statementId":"a663X00000094MjQAI","statementType":"Note","statementLabel":"Documenting an Adverse event (AE), Special Situation (SS), Product complaints (PC) in CRM does not constitute a AE/SS/PC reporting to Drug Safety.","statementLabelText":"Documenting an Adverse event (AE), Special Situation (SS), Product complaints (PC) in CRM does not constitute a AE/SS/PC reporting to Drug Safety.","sortOrder":1},{"statementId":"a663X00000094MeQAI","statementType":"Note","statementLabel":"The information (in free text fields) must have been obtained legitimately and must be unambiguous, precise and clear. Only write facts, do not speculate","statementLabelText":"The information (in free text fields) must have been obtained legitimately and must be unambiguous, precise and clear. Only write facts, do not speculate","sortOrder":2}] | EG31: false | EJ31: false | EL31: ME | EM31: false | EP31: false | EQ31: ME | ET31: Call | EU31: Marketing | EW31: true | EX31: 15 | EY31: Diffuse Large B Cell Lymphoma | EZ31: https://roche-eu-oce--uat.sandbox.lightning.force.com/a2Q69000009DGPm | FA31: 1 | FB31: false | FC31: false | FE31: 5 | FF31: false | FG31: 1 | FH31: amila.zajmovic@roche.com.invalid | FI31: cikica | FJ31: Core Non Promotional Customer Facing | FK31: false | FL31: false | FN31: Polivy | FO31: Core Non Promotional Customer Facing | FP31: Responsive | FQ31: 1:1 Interaction | FT31: Anka Popovic | FU31: Face To Face | FY31: PV/HCO | GC31: Polivy-Diffuse Large B Cell Lymphoma | GE31: Polivy-Diffuse Large B Cell Lymphoma | GF31: true | GK31: false | GL31: ME | GM31: ME | GN31: false | GP31: Europe/Berlin | GR31: Amila Zajmovic | GV31: Non-Promotional Face To Face | GY31: true | HF31: false
A32: [OCE__Call__c] | B32: a2Q69000009PeVzEAK | C32: 0053X00000E3yQCQAZ | D32: false | E32: C-00094356 | F32: EUR | G32: 0123X000000wzbXQAQ | H32: 2023-05-29T12:55:37.000+0000 | I32: 0053X00000E3yQCQAZ | J32: 2024-06-19T08:52:19.000+0000 | K32: 0057U000001Yt7KQAS | L32: 2024-06-19T08:52:19.000+0000 | P32: Anka Popovic | Q32: Anka Popovic | R32: [] | S32: [] | U32: 0013X00003gWlD2QAK | V32: LJUBLJANSKA BB | AD32: LJUBLJANSKA BB, Podgorica, ME, 81000 | AE32: 2023-04-04T12:00:00.000+0000 | AI32: Detail Only | AJ32: Face To Face | AL32: Podgorica | AN32: false | AT32: 30 | AV32: 2023-04-04T12:30:00.000+0000 | AW32: 0 | BM32: false | BN32: false | BO32: false | BP32: false | BU32: a1J3X00000DYpEeUAL | BX32: false | BY32: false | CC32: 1 | CD32: 0 | CE32: 0 | CV32: Gathering insights about number of newly diagnosed DLBCL in MNE | CY32: false | CZ32: [{"isAllowAccount":false,"accId":"0013X00003gWlD2QAK"}] | DS32: Submitted | DU32: 2023-05-29T12:56:38.000+0000 | DX32: ME_CORE_TERR_004 | EC32: 81000 | EF32: [{"statementId":"a663X00000094MjQAI","statementType":"Note","statementLabel":"Documenting an Adverse event (AE), Special Situation (SS), Product complaints (PC) in CRM does not constitute a AE/SS/PC reporting to Drug Safety.","statementLabelText":"Documenting an Adverse event (AE), Special Situation (SS), Product complaints (PC) in CRM does not constitute a AE/SS/PC reporting to Drug Safety.","sortOrder":1},{"statementId":"a663X00000094MeQAI","statementType":"Note","statementLabel":"The information (in free text fields) must have been obtained legitimately and must be unambiguous, precise and clear. Only write facts, do not speculate","statementLabelText":"The information (in free text fields) must have been obtained legitimately and must be unambiguous, precise and clear. Only write facts, do not speculate","sortOrder":2}] | EG32: false | EJ32: false | EL32: ME | EM32: false | EP32: false | EQ32: ME | ET32: Call | EU32: Marketing | EW32: true | EX32: 55 | EY32: Diffuse Large B Cell Lymphoma | EZ32: https://roche-eu-oce--uat.sandbox.lightning.force.com/a2Q69000009PeVz | FA32: 1 | FB32: false | FC32: false | FE32: 5 | FF32: false | FG32: 1 | FH32: amila.zajmovic@roche.com.invalid | FI32: cikica | FJ32: Core Non Promotional Customer Facing | FK32: false | FL32: false | FN32: Polivy | FO32: Core Non Promotional Customer Facing | FP32: Responsive | FT32: Anka Popovic | FU32: Face To Face | FY32: PV/HCO | GC32: Polivy-Diffuse Large B Cell Lymphoma | GE32: Polivy-Diffuse Large B Cell Lymphoma | GF32: true | GK32: false | GL32: ME | GM32: ME | GN32: false | GP32: Europe/Berlin | GR32: Amila Zajmovic | GV32: Non-Promotional Face To Face | GY32: true | HF32: false
A33: [OCE__Call__c] | B33: a2Q69000009PeWEEA0 | C33: 0053X00000E3yQCQAZ | D33: false | E33: C-00094359 | F33: EUR | G33: 0123X000000wzbdQAA | H33: 2023-05-29T13:01:50.000+0000 | I33: 0053X00000E3yQCQAZ | J33: 2024-06-19T08:52:19.000+0000 | K33: 0057U000001Yt7KQAS | L33: 2024-06-19T08:52:19.000+0000 | P33: Anka Popovic | Q33: Anka Popovic | R33: [] | S33: [] | U33: 0013X00003gWlD2QAK | V33: LJUBLJANSKA BB | AD33: LJUBLJANSKA BB, Podgorica, ME, 81000 | AE33: 2023-04-18T12:00:00.000+0000 | AI33: Detail Only | AJ33: Face To Face | AL33: Podgorica | AN33: false | AT33: 30 | AV33: 2023-04-18T12:30:00.000+0000 | AW33: 0 | BM33: false | BN33: false | BO33: false | BP33: false | BU33: a1J3X00000DYpEeUAL | BX33: false | BY33: false | CC33: 1 | CD33: 0 | CE33: 0 | CY33: false | CZ33: [{"isAllowAccount":false,"accId":"0013X00003gWlD2QAK"}] | DS33: Submitted | DU33: 2023-05-29T13:02:45.000+0000 | DX33: ME_CORE_TERR_004 | EC33: 81000 | EF33: [{"statementId":"a663X00000094MjQAI","statementType":"Note","statementLabel":"Documenting an Adverse event (AE), Special Situation (SS), Product complaints (PC) in CRM does not constitute a AE/SS/PC reporting to Drug Safety.","statementLabelText":"Documenting an Adverse event (AE), Special Situation (SS), Product complaints (PC) in CRM does not constitute a AE/SS/PC reporting to Drug Safety.","sortOrder":1},{"statementId":"a663X00000094MeQAI","statementType":"Note","statementLabel":"The information (in free text fields) must have been obtained legitimately and must be unambiguous, precise and clear. Only write facts, do not speculate","statementLabelText":"The information (in free text fields) must have been obtained legitimately and must be unambiguous, precise and clear. Only write facts, do not speculate","sortOrder":2}] | EG33: false | EJ33: false | EL33: ME | EM33: false | EP33: false | EQ33: ME | ET33: Call | EU33: Marketing | EW33: true | EX33: 41 | EZ33: https://roche-eu-oce--uat.sandbox.lightning.force.com/a2Q69000009PeWE | FA33: 1 | FB33: false | FC33: false | FE33: 5 | FF33: false | FG33: 1 | FH33: amila.zajmovic@roche.com.invalid | FI33: cikica | FJ33: Core Non Promotional Customer Facing | FK33: false | FL33: false | FN33: Gazyvaro | FO33: Core Non Promotional Customer Facing | FT33: Anka Popovic | FU33: Face To Face | FY33: PV/HCO | GC33: Gazyvaro | GE33: Gazyvaro | GF33: true | GK33: false | GL33: ME | GM33: ME | GN33: false | GP33: Europe/Berlin | GR33: Amila Zajmovic | GV33: Promotional Face To Face | GY33: true | HF33: false
A34: [OCE__Call__c] | B34: a2Q69000009PeWJEA0 | C34: 0053X00000E3yQCQAZ | D34: false | E34: C-00094360 | F34: EUR | G34: 0123X000000wzbXQAQ | H34: 2023-05-29T13:08:05.000+0000 | I34: 0053X00000E3yQCQAZ | J34: 2023-11-09T21:30:37.000+0000 | K34: 0053X00000BBu6fQAD | L34: 2023-11-09T21:30:37.000+0000 | P34: Anka Popovic | Q34: Anka Popovic | R34: [] | S34: [] | U34: 0013X00003gWlD2QAK | V34: LJUBLJANSKA BB | AD34: LJUBLJANSKA BB, Podgorica, ME, 81000 | AE34: 2023-04-25T13:00:00.000+0000 | AI34: Group Detail | AJ34: Face To Face | AL34: Podgorica | AN34: false | AT34: 15 | AV34: 2023-04-25T13:15:00.000+0000 | AW34: 0 | BM34: false | BN34: false | BO34: true | BP34: false | BU34: a1J3X00000DYpEeUAL | BX34: false | BY34: false | CC34: 1 | CD34: 0 | CE34: 0 | CY34: false | CZ34: [{"isAllowAccount":false,"accId":"0013X00003gWlD2QAK"},{"isAllowAccount":false,"accId":"0013X00003gWlDGQA0"},{"isAllowAccount":false,"accId":"0013X00003gWlDzQAK"},{"isAllowAccount":false,"accId":"0013X00003gWlEvQAK"}] | DS34: Submitted | DU34: 2023-06-13T10:19:24.000+0000 | DX34: ME_CORE_TERR_004 | EC34: 81000 | EF34: [{"statementId":"a663X00000094MjQAI","statementType":"Note","statementLabel":"Documenting an Adverse event (AE), Special Situation (SS), Product complaints (PC) in CRM does not constitute a AE/SS/PC reporting to Drug Safety.","statementLabelText":"Documenting an Adverse event (AE), Special Situation (SS), Product complaints (PC) in CRM does not constitute a AE/SS/PC reporting to Drug Safety.","sortOrder":1},{"statementId":"a663X00000094MeQAI","statementType":"Note","statementLabel":"The information (in free text fields) must have been obtained legitimately and must be unambiguous, precise and clear. Only write facts, do not speculate","statementLabelText":"The information (in free text fields) must have been obtained legitimately and must be unambiguous, precise and clear. Only write facts, do not speculate","sortOrder":2}] | EG34: false | EJ34: false | EL34: ME | EM34: false | EP34: false | EQ34: ME | ET34: Call | EU34: Marketing | EW34: true | EX34: 49 | EY34: Diffuse Large B Cell Lymphoma | EZ34: https://roche-eu-oce--uat.sandbox.lightning.force.com/a2Q69000009PeWJ | FA34: 1 | FB34: false | FC34: false | FE34: 5 | FF34: false | FG34: 4 | FH34: amila.zajmovic@roche.com.invalid | FI34: cikica | FJ34: Core Non Promotional Customer Facing | FK34: false | FL34: false | FO34: Core Non Promotional Customer Facing | FP34: Responsive | FT34: Anka Popovic | FU34: Face To Face | FX34: 3 | FY34: PV/HCO | GC34: Diffuse Large B Cell Lymphoma | GE34: Diffuse Large B Cell Lymphoma | GF34: true | GH34: Anka Popovic (Primary);Enisa Zaric;Milena Dapcevic;Vesko Vujicic | GI34: 2023-05-29T13:08:07.000+0000 | GK34: false | GL34: ME | GM34: ME | GN34: false | GP34: Europe/Berlin | GR34: Amila Zajmovic | GV34: Non-Promotional Face To Face | GY34: true | HF34: false
A35: [OCE__Call__c] | B35: a2Q69000009PeWYEA0 | C35: 0053X00000E3yQCQAZ | D35: false | E35: C-00094370 | F35: EUR | G35: 0123X000000wzbXQAQ | H35: 2023-05-29T13:12:31.000+0000 | I35: 0053X00000E3yQCQAZ | J35: 2023-11-12T20:14:20.000+0000 | K35: 0053X00000BBu6fQAD | L35: 2023-11-12T20:14:20.000+0000 | P35: Anka Popovic | Q35: Anka Popovic | R35: [] | S35: [] | U35: 0013X00003gWlD2QAK | V35: LJUBLJANSKA BB | AD35: LJUBLJANSKA BB, Podgorica, ME, 81000 | AE35: 2023-05-29T11:00:00.000+0000 | AI35: Detail Only | AJ35: Face To Face | AL35: Podgorica | AN35: false | AT35: 30 | AV35: 2023-05-29T11:30:00.000+0000 | AW35: 0 | BM35: false | BN35: false | BO35: false | BP35: false | BU35: a1J3X00000DYpEeUAL | BX35: false | BY35: false | CC35: 1 | CD35: 0 | CE35: 0 | CY35: false | CZ35: [{"isAllowAccount":false,"accId":"0013X00003gWlD2QAK"}] | DS35: Submitted | DU35: 2023-06-13T10:18:12.000+0000 | DX35: ME_CORE_TERR_004 | EC35: 81000 | EF35: [{"statementId":"a663X00000094MjQAI","statementType":"Note","statementLabel":"Documenting an Adverse event (AE), Special Situation (SS), Product complaints (PC) in CRM does not constitute a AE/SS/PC reporting to Drug Safety.","statementLabelText":"Documenting an Adverse event (AE), Special Situation (SS), Product complaints (PC) in CRM does not constitute a AE/SS/PC reporting to Drug Safety.","sortOrder":1},{"statementId":"a663X00000094MeQAI","statementType":"Note","statementLabel":"The information (in free text fields) must have been obtained legitimately and must be unambiguous, precise and clear. Only write facts, do not speculate","statementLabelText":"The information (in free text fields) must have been obtained legitimately and must be unambiguous, precise and clear. Only write facts, do not speculate","sortOrder":2}] | EG35: false | EJ35: false | EL35: ME | EM35: false | EP35: false | EQ35: ME | ET35: Call | EU35: Marketing | EW35: true | EX35: 15 | EY35: Diffuse Large B Cell Lymphoma | EZ35: https://roche-eu-oce--uat.sandbox.lightning.force.com/a2Q69000009PeWY | FA35: 1 | FB35: false | FC35: false | FE35: 5 | FF35: false | FG35: 1 | FH35: amila.zajmovic@roche.com.invalid | FI35: cikica | FJ35: Core Non Promotional Customer Facing | FK35: false | FL35: false | FO35: Core Non Promotional Customer Facing | FP35: Responsive | FQ35: 1:1 Interaction | FT35: Anka Popovic | FU35: Face To Face | FY35: PV/HCO | GC35: Diffuse Large B Cell Lymphoma | GE35: Diffuse Large B Cell Lymphoma | GF35: true | GK35: false | GL35: ME | GM35: ME | GN35: false | GP35: Europe/Berlin | GR35: Amila Zajmovic | GV35: Non-Promotional Face To Face | GY35: true | HF35: false
A36: [OCE__Call__c] | B36: a2Q7U000000JfoVUAS | C36: 0053X00000E3yQCQAZ | D36: false | E36: C-00046178 | F36: EUR | G36: 0123X000000wzbXQAQ | H36: 2023-02-06T12:13:31.000+0000 | I36: 0053X00000E3yQCQAZ | J36: 2024-06-19T13:34:29.000+0000 | K36: 0057U000001Yt7KQAS | L36: 2024-06-19T13:34:29.000+0000 | P36: Anka Popovic | Q36: Anka Popovic | R36: [] | S36: [] | U36: 0013X00003gWlD2QAK | V36: LJUBLJANSKA BB | AD36: LJUBLJANSKA BB, Podgorica, ME, 81000 | AE36: 2023-01-09T12:00:00.000+0000 | AI36: Detail Only | AJ36: Face To Face | AL36: Podgorica | AN36: false | AT36: 30 | AV36: 2023-01-09T12:30:00.000+0000 | AW36: 0 | BM36: false | BN36: false | BO36: false | BP36: false | BU36: a1J3X00000DYpEeUAL | BX36: false | BY36: false | CC36: 1 | CD36: 0 | CE36: 0 | CY36: false | CZ36: [{"isAllowAccount":false,"accId":"0013X00003gWlD2QAK"}] | DS36: Submitted | DU36: 2023-02-27T14:29:10.000+0000 | DX36: ME_CORE_TERR_004 | EC36: 81000 | EF36: [{"statementId":"a663X00000094MjQAI","statementType":"Note","statementLabel":"Documenting an Adverse event (AE), Special Situation (SS), Product complaints (PC) in CRM does not constitute a AE/SS/PC reporting to Drug Safety.","statementLabelText":"Documenting an Adverse event (AE), Special Situation (SS), Product complaints (PC) in CRM does not constitute a AE/SS/PC reporting to Drug Safety.","sortOrder":1},{"statementId":"a663X00000094MeQAI","statementType":"Note","statementLabel":"The information (in free text fields) must have been obtained legitimately and must be unambiguous, precise and clear. Only write facts, do not speculate","statementLabelText":"The information (in free text fields) must have been obtained legitimately and must be unambiguous, precise and clear. Only write facts, do not speculate","sortOrder":2}] | EG36: false | EJ36: false | EL36: ME | EM36: false | EP36: false | EQ36: ME | ET36: Call | EU36: Marketing | EW36: true | EX36: 49 | EY36: Diffuse Large B Cell Lymphoma | EZ36: https://roche-eu-oce--uat.sandbox.lightning.force.com/a2Q7U000000JfoV | FA36: 1 | FB36: false | FC36: false | FE36: 5 | FF36: false | FG36: 1 | FH36: amila.zajmovic@roche.com.invalid | FI36: cikica | FJ36: Core Non Promotional Customer Facing | FK36: false | FL36: false | FN36: Polivy | FO36: Core Non Promotional Customer Facing | FP36: Responsive | FT36: Anka Popovic | FU36: Face To Face | FY36: PV/HCO | GC36: Polivy-Diffuse Large B Cell Lymphoma | GE36: Polivy-Diffuse Large B Cell Lymphoma | GF36: true | GK36: false | GL36: ME | GM36: ME | GN36: false | GP36: Europe/Berlin | GR36: Amila Zajmovic | GV36: Non-Promotional Face To Face | GY36: true | HF36: false
A37: [OCE__Call__c] | B37: a2Q7U000000XZsJUAW | C37: 0053X00000E3yQCQAZ | D37: false | E37: C-00002263 | F37: EUR | G37: 0123X000000wzbhQAA | H37: 2022-02-09T12:05:09.000+0000 | I37: 0053X00000E3yQCQAZ | J37: 2024-06-19T13:38:02.000+0000 | K37: 0057U000001Yt7KQAS | L37: 2024-06-19T13:38:02.000+0000 | P37: Anka Popovic | Q37: Anka Popovic | R37: [] | S37: [] | U37: 0013X00003gWlD2QAK | V37: LJUBLJANSKA BB | AD37: LJUBLJANSKA BB, Podgorica, ME, 81000 | AE37: 2022-02-07T22:00:00.000+0000 | AI37: Detail Only | AL37: Podgorica | AN37: false | AT37: 15 | AV37: 2022-02-07T22:15:00.000+0000 | AW37: 0 | BM37: false | BN37: false | BO37: false | BP37: false | BU37: a1J3X00000DYpEeUAL | BX37: false | BY37: false | CC37: 1 | CD37: 0 | CE37: 0 | CY37: false | CZ37: [{"isAllowAccount":false,"accId":"0013X00003gWlD2QAK"}] | DS37: Submitted | DU37: 2022-02-09T12:05:08.000+0000 | DX37: ME_CORE_TERR_004 | EC37: 81000 | EF37: [{"statementId":"a663X00000094MjQAI","statementType":"Note","statementLabel":"Documenting an Adverse event (AE), Special Situation (SS), Product complaints (PC) in CRM does not constitute a AE/SS/PC reporting to Drug Safety.","statementLabelText":"Documenting an Adverse event (AE), Special Situation (SS), Product complaints (PC) in CRM does not constitute a AE/SS/PC reporting to Drug Safety.","sortOrder":1},{"statementId":"a663X00000094MeQAI","statementType":"Note","statementLabel":"The information (in free text fields) must have been obtained legitimately and must be unambiguous, precise and clear. Only write facts, do not speculate","statementLabelText":"The information (in free text fields) must have been obtained legitimately and must be unambiguous, precise and clear. Only write facts, do not speculate","sortOrder":2}] | EG37: false | EJ37: false | EL37: ME | EM37: false | EP37: false | EQ37: ME | ET37: Call | EU37: Marketing | EW37: false | EX37: 2 | EZ37: https://roche-eu-oce--uat.sandbox.lightning.force.com/a2Q7U000000XZsJ | FA37: 1 | FB37: false | FC37: false | FE37: 5 | FF37: false | FG37: 1 | FH37: amila.zajmovic@roche.com.invalid | FI37: cikica | FJ37: Core Non Promotional Customer Facing | FK37: false | FL37: false | FO37: Core Non Promotional Customer Facing | FT37: Anka Popovic | FU37: Remote | FY37: PV/HCO | GC37: Gazyvaro-Follicular Lymphoma | GE37: Gazyvaro-Follicular Lymphoma | GF37: true | GK37: false | GL37: ME | GM37: ME | GN37: false | GP37: Europe/Berlin | GR37: Amila Zajmovic | GV37: Promotional Remote | GY37: true | HF37: false
A38: [OCE__Call__c] | B38: a2Q69000009Pq5jEAC | C38: 0053X00000E3yPJQAZ | D38: false | E38: C-00105453 | F38: EUR | G38: 0123X000000wzbXQAQ | H38: 2023-06-16T12:15:29.000+0000 | I38: 0053X00000E3yPJQAZ | J38: 2024-06-19T12:17:51.000+0000 | K38: 0057U000001Yt7KQAS | L38: 2024-06-19T12:17:51.000+0000 | P38: Vladimir Todorovic | Q38: Vladimir Todorovic | R38: [] | S38: [] | U38: 0013X00003gWlD5QAK | V38: LJUBLJANSKA BB | AD38: LJUBLJANSKA BB, Podgorica, ME, 81000 | AE38: 2023-04-03T11:00:00.000+0000 | AI38: Detail Only | AJ38: Face To Face | AL38: Podgorica | AN38: false | AT38: 30 | AV38: 2023-04-03T11:30:00.000+0000 | AW38: 0 | BM38: false | BN38: false | BO38: false | BP38: false | BU38: a1J3X00000DYpEhUAL | BX38: false | BY38: false | CC38: 1 | CD38: 0 | CE38: 0 | CY38: false | CZ38: [{"isAllowAccount":false,"accId":"0013X00003gWlD5QAK"}] | DS38: Submitted | DU38: 2023-06-16T12:15:28.000+0000 | DX38: ME_CORE_TERR_003 | EC38: 81000 | EF38: [{"statementId":"a663X00000094MjQAI","statementType":"Note","statementLabel":"Documenting an Adverse event (AE), Special Situation (SS), Product complaints (PC) in CRM does not constitute a AE/SS/PC reporting to Drug Safety.","statementLabelText":"Documenting an Adverse event (AE), Special Situation (SS), Product complaints (PC) in CRM does not constitute a AE/SS/PC reporting to Drug Safety.","sortOrder":1},{"statementId":"a663X00000094MeQAI","statementType":"Note","statementLabel":"The information (in free text fields) must have been obtained legitimately and must be unambiguous, precise and clear. Only write facts, do not speculate","statementLabelText":"The information (in free text fields) must have been obtained legitimately and must be unambiguous, precise and clear. Only write facts, do not speculate","sortOrder":2}] | EG38: false | EJ38: false | EL38: ME | EM38: false | EP38: false | EQ38: ME | ET38: Call | EU38: Marketing | EW38: true | EX38: 74 | EY38: Breast Cancer | EZ38: https://roche-eu-oce--uat.sandbox.lightning.force.com/a2Q69000009Pq5j | FA38: 1 | FB38: false | FC38: false | FE38: 5 | FF38: false | FG38: 1 | FH38: nemanja.raicevic@roche.com.invalid | FI38: raicevin | FJ38: Core Non Promotional Customer Facing | FK38: false | FL38: false | FN38: Phesgo | FO38: Core Non Promotional Customer Facing | FP38: Proactive | FT38: Vladimir Todorovic | FU38: Face To Face | FY38: PV/HCO | GC38: Phesgo-Breast Cancer | GE38: Phesgo-Breast Cancer | GF38: true | GK38: false | GL38: ME | GM38: ME | GN38: false | GP38: Europe/Berlin | GR38: Nemanja Raicevic | GV38: Non-Promotional Face To Face | GY38: true | HF38: false
A39: [OCE__Call__c] | B39: a2Q69000009Pq8YEAS | C39: 0053X00000E3yPJQAZ | D39: false | E39: C-00105497 | F39: EUR | G39: 0123X000000wzbXQAQ | H39: 2023-06-16T12:54:31.000+0000 | I39: 0053X00000E3yPJQAZ | J39: 2024-06-19T12:17:56.000+0000 | K39: 0057U000001Yt7KQAS | L39: 2024-06-19T12:17:56.000+0000 | P39: Vladimir Todorovic | Q39: Vladimir Todorovic | R39: [] | S39: [] | U39: 0013X00003gWlD5QAK | V39: LJUBLJANSKA BB | AD39: LJUBLJANSKA BB, Podgorica, ME, 81000 | AE39: 2023-06-16T10:00:00.000+0000 | AI39: Detail Only | AJ39: Face To Face | AL39: Podgorica | AN39: false | AT39: 45 | AV39: 2023-06-16T10:45:00.000+0000 | AW39: 0 | BM39: false | BN39: false | BO39: false | BP39: false | BU39: a1J3X00000DYpEhUAL | BX39: false | BY39: false | CC39: 1 | CD39: 0 | CE39: 0 | CY39: false | CZ39: [{"isAllowAccount":false,"accId":"0013X00003gWlD5QAK"}] | DS39: Submitted | DU39: 2023-06-16T12:54:30.000+0000 | DX39: ME_CORE_TERR_003 | EC39: 81000 | EF39: [{"statementId":"a663X00000094MjQAI","statementType":"Note","statementLabel":"Documenting an Adverse event (AE), Special Situation (SS), Product complaints (PC) in CRM does not constitute a AE/SS/PC reporting to Drug Safety.","statementLabelText":"Documenting an Adverse event (AE), Special Situation (SS), Product complaints (PC) in CRM does not constitute a AE/SS/PC reporting to Drug Safety.","sortOrder":1},{"statementId":"a663X00000094MeQAI","statementType":"Note","statementLabel":"The information (in free text fields) must have been obtained legitimately and must be unambiguous, precise and clear. Only write facts, do not speculate","statementLabelText":"The information (in free text fields) must have been obtained legitimately and must be unambiguous, precise and clear. Only write facts, do not speculate","sortOrder":2}] | EG39: false | EJ39: false | EL39: ME | EM39: false | EP39: false | EQ39: ME | ET39: Call | EU39: Marketing | EW39: false | EX39: 0 | EZ39: https://roche-eu-oce--uat.sandbox.lightning.force.com/a2Q69000009Pq8Y | FA39: 1 | FB39: false | FC39: false | FE39: 5 | FF39: false | FG39: 1 | FH39: nemanja.raicevic@roche.com.invalid | FI39: raicevin | FJ39: Core Non Promotional Customer Facing | FK39: false | FL39: false | FO39: Core Non Promotional Customer Facing | FP39: Proactive | FR39: ;Oncology | FT39: Vladimir Todorovic | FU39: Face To Face | FY39: PV/HCO | GC39: Oncology | GE39: Oncology | GF39: true | GK39: false | GL39: ME | GM39: ME | GN39: false | GP39: Europe/Berlin | GR39: Nemanja Raicevic | GV39: Non-Promotional Face To Face | GY39: true | HF39: false
A40: [OCE__Call__c] | B40: a2Q69000009Pq9CEAS | C40: 0053X00000E3yPJQAZ | D40: false | E40: C-00105505 | F40: EUR | G40: 0123X000000wzbXQAQ | H40: 2023-06-16T13:02:11.000+0000 | I40: 0053X00000E3yPJQAZ | J40: 2023-11-14T10:49:55.000+0000 | K40: 0053X00000BBu6fQAD | L40: 2023-11-14T10:49:55.000+0000 | P40: Vladimir Todorovic | Q40: Vladimir Todorovic | R40: [] | S40: [] | U40: 0013X00003gWlD5QAK | V40: LJUBLJANSKA BB | AD40: LJUBLJANSKA BB, Podgorica, ME, 81000 | AE40: 2023-04-28T12:01:00.000+0000 | AI40: Detail Only | AJ40: Face To Face | AL40: Podgorica | AN40: false | AT40: 60 | AV40: 2023-04-28T13:01:00.000+0000 | AW40: 0 | BM40: false | BN40: false | BO40: false | BP40: false | BU40: a1J3X00000DYpEhUAL | BX40: false | BY40: false | CC40: 1 | CD40: 0 | CE40: 0 | CY40: false | CZ40: [{"isAllowAccount":false,"accId":"0013X00003gWlD5QAK"}] | DS40: Submitted | DU40: 2023-06-16T13:02:10.000+0000 | DX40: ME_CORE_TERR_003 | EC40: 81000 | EF40: [{"statementId":"a663X00000094MjQAI","statementType":"Note","statementLabel":"Documenting an Adverse event (AE), Special Situation (SS), Product complaints (PC) in CRM does not constitute a AE/SS/PC reporting to Drug Safety.","statementLabelText":"Documenting an Adverse event (AE), Special Situation (SS), Product complaints (PC) in CRM does not constitute a AE/SS/PC reporting to Drug Safety.","sortOrder":1},{"statementId":"a663X00000094MeQAI","statementType":"Note","statementLabel":"The information (in free text fields) must have been obtained legitimately and must be unambiguous, precise and clear. Only write facts, do not speculate","statementLabelText":"The information (in free text fields) must have been obtained legitimately and must be unambiguous, precise and clear. Only write facts, do not speculate","sortOrder":2}] | EG40: false | EJ40: false | EL40: ME | EM40: false | EP40: false | EQ40: ME | ET40: Call | EU40: Marketing | EW40: true | EX40: 49 | EZ40: https://roche-eu-oce--uat.sandbox.lightning.force.com/a2Q69000009Pq9C | FA40: 1 | FB40: false | FC40: false | FE40: 5 | FF40: false | FG40: 3 | FH40: nemanja.raicevic@roche.com.invalid | FI40: raicevin | FJ40: Core Non Promotional Customer Facing | FK40: false | FL40: false | FO40: Core Non Promotional Customer Facing | FP40: Proactive | FR40: ;Oncology | FT40: Vladimir Todorovic | FU40: Face To Face | FV40: 1 | FY40: PV/HCO | GC40: Oncology | GE40: Oncology | GF40: true | GI40: 2023-06-16T13:02:12.000+0000 | GJ40: Amila Zajmovic | GK40: false | GL40: ME | GM40: ME | GN40: false | GP40: Europe/Berlin | GR40: Nemanja Raicevic | GV40: Non-Promotional Face To Face | GY40: true | HF40: false
A41: [OCE__Call__c] | B41: a2Q69000009Ps7mEAC | C41: 0053X00000E3yPJQAZ | D41: false | E41: C-00108052 | F41: EUR | G41: 0123X000000wzbXQAQ | H41: 2023-06-20T10:58:50.000+0000 | I41: 0053X00000E3yPJQAZ | J41: 2024-06-19T12:21:09.000+0000 | K41: 0057U000001Yt7KQAS | L41: 2024-06-19T12:21:09.000+0000 | P41: Vladimir Todorovic | Q41: Vladimir Todorovic | R41: [] | S41: [] | U41: 0013X00003gWlD5QAK | V41: LJUBLJANSKA BB | AD41: LJUBLJANSKA BB, Podgorica, ME, 81000 | AE41: 2023-05-10T12:00:00.000+0000 | AI41: Detail Only | AJ41: Face To Face | AL41: Podgorica | AN41: false | AT41: 60 | AV41: 2023-05-10T13:00:00.000+0000 | AW41: 0 | BM41: false | BN41: false | BO41: false | BP41: false | BU41: a1J3X00000DYpEhUAL | BX41: false | BY41: false | CB41: Agreement on sponsorship for AROME conference | CC41: 1 | CD41: 0 | CE41: 0 | CY41: false | CZ41: [{"isAllowAccount":false,"accId":"0013X00003gWlD5QAK"}] | DS41: Submitted | DU41: 2023-06-20T10:58:49.000+0000 | DX41: ME_CORE_TERR_003 | EC41: 81000 | EF41: [{"statementId":"a663X00000094MjQAI","statementType":"Note","statementLabel":"Documenting an Adverse event (AE), Special Situation (SS), Product complaints (PC) in CRM does not constitute a AE/SS/PC reporting to Drug Safety.","statementLabelText":"Documenting an Adverse event (AE), Special Situation (SS), Product complaints (PC) in CRM does not constitute a AE/SS/PC reporting to Drug Safety.","sortOrder":1},{"statementId":"a663X00000094MeQAI","statementType":"Note","statementLabel":"The information (in free text fields) must have been obtained legitimately and must be unambiguous, precise and clear. Only write facts, do not speculate","statementLabelText":"The information (in free text fields) must have been obtained legitimately and must be unambiguous, precise and clear. Only write facts, do not speculate","sortOrder":2}] | EG41: false | EJ41: false | EL41: ME | EM41: false | EP41: false | EQ41: ME | ET41: Call | EU41: Marketing | EW41: true | EX41: 41 | EZ41: https://roche-eu-oce--uat.sandbox.lightning.force.com/a2Q69000009Ps7m | FA41: 1 | FB41: false | FC41: false | FE41: 5 | FF41: false | FG41: 1 | FH41: nemanja.raicevic@roche.com.invalid | FI41: raicevin | FJ41: Core Non Promotional Customer Facing | FK41: false | FL41: false | FO41: Core Non Promotional Customer Facing | FP41: Proactive | FR41: ;Oncology | FT41: Vladimir Todorovic | FU41: Face To Face | FY41: PV/HCO | GC41: Oncology | GE41: Oncology | GF41: true | GK41: false | GL41: ME | GM41: ME | GN41: false | GP41: Europe/Berlin | GR41: Nemanja Raicevic | GV41: Non-Promotional Face To Face | GY41: true | HF41: false
A42: [OCE__Call__c] | B42: a2Q69000009PsAgEAK | C42: 0053X00000E3yPJQAZ | D42: false | E42: C-00108111 | F42: EUR | G42: 0123X000000wzbXQAQ | H42: 2023-06-20T11:17:38.000+0000 | I42: 0053X00000E3yPJQAZ | J42: 2024-06-19T12:21:20.000+0000 | K42: 0057U000001Yt7KQAS | L42: 2024-06-19T12:21:20.000+0000 | P42: Vladimir Todorovic | Q42: Vladimir Todorovic | R42: [] | S42: [] | U42: 0013X00003gWlD5QAK | V42: LJUBLJANSKA BB | AD42: LJUBLJANSKA BB, Podgorica, ME, 81000 | AE42: 2023-06-18T23:16:00.000+0000 | AI42: Detail Only | AJ42: Face To Face | AL42: Podgorica | AN42: false | AT42: 60 | AV42: 2023-06-19T00:16:00.000+0000 | AW42: 0 | BM42: false | BN42: false | BO42: false | BP42: false | BU42: a1J3X00000DYpEhUAL | BX42: false | BY42: false | CC42: 1 | CD42: 0 | CE42: 0 | CV42: Agreement on sponsorship for AROME conference | CY42: false | CZ42: [{"isAllowAccount":false,"accId":"0013X00003gWlD5QAK"}] | DS42: Submitted | DU42: 2023-06-20T11:17:37.000+0000 | DX42: ME_CORE_TERR_003 | EC42: 81000 | EF42: [{"statementId":"a663X00000094MjQAI","statementType":"Note","statementLabel":"Documenting an Adverse event (AE), Special Situation (SS), Product complaints (PC) in CRM does not constitute a AE/SS/PC reporting to Drug Safety.","statementLabelText":"Documenting an Adverse event (AE), Special Situation (SS), Product complaints (PC) in CRM does not constitute a AE/SS/PC reporting to Drug Safety.","sortOrder":1},{"statementId":"a663X00000094MeQAI","statementType":"Note","statementLabel":"The information (in free text fields) must have been obtained legitimately and must be unambiguous, precise and clear. Only write facts, do not speculate","statementLabelText":"The information (in free text fields) must have been obtained legitimately and must be unambiguous, precise and clear. Only write facts, do not speculate","sortOrder":2}] | EG42: false | EJ42: false | EL42: ME | EM42: false | EP42: false | EQ42: ME | ET42: Call | EU42: Marketing | EW42: false | EX42: 2 | EZ42: https://roche-eu-oce--uat.sandbox.lightning.force.com/a2Q69000009PsAg | FA42: 1 | FB42: false | FC42: false | FE42: 5 | FF42: false | FG42: 1 | FH42: nemanja.raicevic@roche.com.invalid | FI42: raicevin | FJ42: Core Non Promotional Customer Facing | FK42: false | FL42: false | FO42: Core Non Promotional Customer Facing | FP42: Proactive | FR42: ;Oncology | FT42: Vladimir Todorovic | FU42: Face To Face | FY42: PV/HCO | GC42: Oncology | GE42: Oncology | GF42: true | GK42: false | GL42: ME | GM42: ME | GN42: false | GP42: Europe/Berlin | GR42: Nemanja Raicevic | GV42: Non-Promotional Face To Face | GY42: true | HF42: false
A43: [OCE__Call__c] | B43: a2Q7U000000JflCUAS | C43: 0053X00000E3yPJQAZ | D43: false | E43: C-00046149 | F43: EUR | G43: 0123X000000wzbXQAQ | H43: 2023-02-06T10:41:02.000+0000 | I43: 0053X00000E3yPJQAZ | J43: 2023-12-01T18:25:22.000+0000 | K43: 0053X00000BBu6fQAD | L43: 2023-12-01T18:25:22.000+0000 | P43: Vladimir Todorovic | Q43: Vladimir Todorovic | R43: [] | S43: [] | U43: 0013X00003gWlD5QAK | V43: LJUBLJANSKA BB | AD43: LJUBLJANSKA BB, Podgorica, ME, 81000 | AE43: 2023-01-27T09:30:00.000+0000 | AI43: Detail Only | AJ43: Face To Face | AL43: Podgorica | AN43: false | AT43: 45 | AV43: 2023-01-27T10:15:00.000+0000 | AW43: 0 | BM43: true | BN43: false | BO43: false | BP43: false | BU43: a1J3X00000DYpEhUAL | BX43: false | BY43: false | CC43: 1 | CD43: 0 | CE43: 0 | CY43: false | CZ43: [{"isAllowAccount":false,"accId":"0013X00003gWlD5QAK"}] | DS43: Submitted | DU43: 2023-02-27T14:34:59.000+0000 | DX43: ME_CORE_TERR_003 | EC43: 81000 | EF43: [{"statementId":"a663X00000094MjQAI","statementType":"Note","statementLabel":"Documenting an Adverse event (AE), Special Situation (SS), Product complaints (PC) in CRM does not constitute a AE/SS/PC reporting to Drug Safety.","statementLabelText":"Documenting an Adverse event (AE), Special Situation (SS), Product complaints (PC) in CRM does not constitute a AE/SS/PC reporting to Drug Safety.","sortOrder":1},{"statementId":"a663X00000094MeQAI","statementType":"Note","statementLabel":"The information (in free text fields) must have been obtained legitimately and must be unambiguous, precise and clear. Only write facts, do not speculate","statementLabelText":"The information (in free text fields) must have been obtained legitimately and must be unambiguous, precise and clear. Only write facts, do not speculate","sortOrder":2}] | EG43: false | EJ43: false | EL43: ME | EM43: false | EP43: false | EQ43: ME | ET43: Call | EU43: Marketing | EW43: true | EX43: 31 | EY43: Hepatocellular Carcinoma | EZ43: https://roche-eu-oce--uat.sandbox.lightning.force.com/a2Q7U000000JflC | FA43: 1 | FB43: false | FC43: false | FE43: 5 | FF43: false | FG43: 2 | FH43: nemanja.raicevic@roche.com.invalid | FI43: raicevin | FJ43: Core Non Promotional Customer Facing | FK43: false | FL43: false | FN43: Tecentriq | FO43: Core Non Promotional Customer Facing | FP43: Proactive | FQ43: 1:1 Interaction | FT43: Vladimir Todorovic | FU43: Face To Face | FY43: PV/HCO | GC43: Tecentriq-Hepatocellular Carcinoma | GE43: Tecentriq-Hepatocellular Carcinoma | GF43: true | GK43: false | GL43: ME | GM43: ME | GN43: false | GP43: Europe/Berlin | GR43: Nemanja Raicevic | GV43: Non-Promotional Face To Face | GY43: true | HF43: false
A44: [OCE__Call__c] | B44: a2QSe000006TcG9MAK | C44: 0053X00000E3yNcQAJ | D44: false | E44: C-01393356 | F44: EUR | G44: 0123X000000wzbXQAQ | H44: 2025-09-02T19:21:47.000+0000 | I44: 0053X00000E3yNcQAJ | J44: 2025-09-02T19:25:37.000+0000 | K44: 0053X00000BBu6fQAD | L44: 2025-09-02T19:25:37.000+0000 | P44: Vladimir Todorovic | Q44: Vladimir Todorovic | U44: 0013X00003gWlD5QAK | V44: LJUBLJANSKA BB | AD44: LJUBLJANSKA BB, Podgorica, ME, 81000 | AE44: 2025-09-02T10:00:00.000+0000 | AJ44: Face To Face | AL44: Podgorica | AN44: false | AT44: 45 | AV44: 2025-09-02T10:45:00.000+0000 | BM44: false | BN44: false | BO44: false | BP44: false | BU44: a1J3X00000DYpEhUAL | BX44: false | BY44: false | CC44: 1 | CD44: 0 | CE44: 0 | CY44: false | DS44: Submitted | DU44: 2025-09-02T19:25:32.000+0000 | DX44: ME_CORE_TERR_005 | EC44: 81000 | EF44: [{"statementValidationType":"None","statementValidationResponse":"Skipped","statementType":"Note","statementLabelText":"Documenting Adverse Events (AE), Special Situations (SS), or Product Complaints (PC), in CRM does not constitute AE/SS/PC reporting to Drug Safety.","statementLabel":"Documenting Adverse Events (AE), Special Situations (SS), or Product Complaints (PC), in CRM does not constitute AE/SS/PC reporting to Drug Safety.","statementId":"a6669000007KfNLAA0","sortOrder":1},{"statementValidationType":"None","statementValidationResponse":"Skipped","statementType":"Note","statementLabelText":"The information (in free text fields) must have been obtained legitimately and must be unambiguous, precise and clear. Only write facts, do not speculate","statementLabel":"The information (in free text fields) must have been obtained legitimately and must be unambiguous, precise and clear. Only write facts, do not speculate","statementId":"a6669000007KfNMAA0","sortOrder":2}] | EG44: false | EH44: [ ] | EJ44: false | EL44: ME | EM44: false | EP44: false | EQ44: ME | ET44: Call | EU44: Marketing | EW44: false | EX44: 0 | EY44: Breast Cancer | EZ44: https://roche-eu-oce--uat.sandbox.lightning.force.com/a2QSe000006TcG9 | FA44: 1 | FB44: false | FC44: false | FE44: 5 | FF44: false | FH44: amina.beciragic@roche.com.invalid | FI44: kucevica | FJ44: Core Non Promotional Customer Facing | FK44: false | FL44: false | FN44: Phesgo | FO44: Core Non Promotional Customer Facing | FP44: Proactive | FQ44: 1:1 Interaction | FT44: Vladimir Todorovic | FU44: Face To Face | FY44: PV/HCO | GC44: Phesgo-Breast Cancer | GD44: Not Required | GE44: Phesgo-Breast Cancer | GF44: true | GK44: false | GL44: ME | GM44: ME | GN44: false | GP44: Europe/Berlin | GR44: Amina Beciragic | GV44: Non-Promotional Face To Face | GY44: true | HC44: MD | HF44: false
A45: [OCE__Call__c] | B45: a2QSe000006iFazMAE | C45: 0053X00000E3yNcQAJ | D45: false | E45: C-01443547 | F45: EUR | G45: 0123X000000wzbXQAQ | H45: 2025-09-26T12:08:50.000+0000 | I45: 0053X00000E3yNcQAJ | J45: 2025-09-26T12:12:09.000+0000 | K45: 0053X00000BBu6fQAD | L45: 2025-09-26T12:12:09.000+0000 | P45: Vladimir Todorovic | Q45: Vladimir Todorovic | U45: 0013X00003gWlD5QAK | V45: LJUBLJANSKA BB | AD45: LJUBLJANSKA BB, Podgorica, ME, 81000 | AE45: 2025-09-26T08:45:00.000+0000 | AJ45: Face To Face | AL45: Podgorica | AN45: false | AT45: 30 | AV45: 2025-09-26T09:15:00.000+0000 | BM45: false | BN45: false | BO45: false | BP45: false | BU45: a1J3X00000DYpEhUAL | BX45: false | BY45: false | CC45: 1 | CD45: 0 | CE45: 0 | CY45: false | DS45: Submitted | DU45: 2025-09-26T12:12:04.000+0000 | DX45: ME_CORE_TERR_005 | EC45: 81000 | EF45: [{"statementValidationType":"None","statementValidationResponse":"Skipped","statementType":"Note","statementLabelText":"Documenting Adverse Events (AE), Special Situations (SS), or Product Complaints (PC), in CRM does not constitute AE/SS/PC reporting to Drug Safety.","statementLabel":"Documenting Adverse Events (AE), Special Situations (SS), or Product Complaints (PC), in CRM does not constitute AE/SS/PC reporting to Drug Safety.","statementId":"a6669000007KfNLAA0","sortOrder":1},{"statementValidationType":"None","statementValidationResponse":"Skipped","statementType":"Note","statementLabelText":"The information (in free text fields) must have been obtained legitimately and must be unambiguous, precise and clear. Only write facts, do not speculate","statementLabel":"The information (in free text fields) must have been obtained legitimately and must be unambiguous, precise and clear. Only write facts, do not speculate","statementId":"a6669000007KfNMAA0","sortOrder":2}] | EG45: false | EH45: [ ] | EI45: [ ] | EJ45: false | EL45: ME | EM45: false | EP45: false | EQ45: ME | ET45: Call | EU45: Marketing | EW45: false | EX45: 0 | EY45: Breast Cancer | EZ45: https://roche-eu-oce--uat.sandbox.lightning.force.com/a2QSe000006iFaz | FA45: 1 | FB45: false | FC45: false | FE45: 5 | FF45: false | FG45: 2 | FH45: amina.beciragic@roche.com.invalid | FI45: kucevica | FJ45: Core Non Promotional Customer Facing | FK45: false | FL45: false | FN45: Phesgo | FO45: Core Non Promotional Customer Facing | FP45: Proactive | FQ45: 1:1 Interaction | FT45: Vladimir Todorovic | FU45: Face To Face | FY45: PV/HCO | GC45: Phesgo-Breast Cancer | GD45: Not Required | GE45: Phesgo-Breast Cancer | GF45: true | GK45: false | GL45: ME | GM45: ME | GN45: false | GP45: Europe/Berlin | GR45: Amina Beciragic | GV45: Non-Promotional Face To Face | GY45: true | HC45: MD | HF45: false
A46: [OCE__Call__c] | B46: a2Q69000009PjVhEAK | C46: 0057U000001eKP1QAM | D46: false | E46: C-00100278 | F46: EUR | G46: 0123X000000wzbbQAA | H46: 2023-06-09T11:22:07.000+0000 | I46: 0057U000001eKP1QAM | J46: 2023-12-11T19:44:28.000+0000 | K46: 0053X00000BBu6fQAD | L46: 2023-12-11T19:44:28.000+0000 | P46: Nikola Milasevic | Q46: Nikola Milasevic | R46: [] | S46: [] | U46: 0013X00003gWlD6QAK | V46: LJUBLJANSKA BB | AD46: LJUBLJANSKA BB, Podgorica, ME, 81000 | AE46: 2023-05-04T10:30:00.000+0000 | AI46: Detail Only | AL46: Podgorica | AN46: false | AT46: 30 | AV46: 2023-05-04T11:00:00.000+0000 | AW46: 0 | BM46: false | BN46: false | BO46: false | BP46: false | BU46: a1J3X00000DYpEiUAL | BX46: false | BY46: false | CC46: 1 | CD46: 0 | CE46: 0 | CY46: false | CZ46: [{"isAllowAccount":false,"accId":"0013X00003gWlD6QAK"}] | DS46: Submitted | DU46: 2023-06-09T11:22:07.000+0000 | DX46: ME_CORE_TERR_007 | EC46: 81000 | EF46: [{"statementId":"a663X00000094MjQAI","statementType":"Note","statementLabel":"Documenting an Adverse event (AE), Special Situation (SS), Product complaints (PC) in CRM does not constitute a AE/SS/PC reporting to Drug Safety.","statementLabelText":"Documenting an Adverse event (AE), Special Situation (SS), Product complaints (PC) in CRM does not constitute a AE/SS/PC reporting to Drug Safety.","sortOrder":1},{"statementId":"a663X00000094MeQAI","statementType":"Note","statementLabel":"The information (in free text fields) must have been obtained legitimately and must be unambiguous, precise and clear. Only write facts, do not speculate","statementLabelText":"The information (in free text fields) must have been obtained legitimately and must be unambiguous, precise and clear. Only write facts, do not speculate","sortOrder":2}] | EG46: false | EJ46: false | EL46: ME | EM46: false | EP46: false | EQ46: ME | ET46: Call | EU46: Marketing | EW46: true | EX46: 36 | EZ46: https://roche-eu-oce--uat.sandbox.lightning.force.com/a2Q69000009PjVh | FA46: 1 | FB46: false | FC46: false | FE46: 5 | FF46: false | FG46: 3 | FH46: dijana.stojanovski@roche.com.invalid | FI46: rudovid1 | FJ46: Core Non Promotional Customer Facing | FK46: false | FL46: false | FO46: Core Non Promotional Customer Facing | FP46: Proactive | FR46: ;Oncology | FT46: Nikola Milasevic | FU46: Remote | FV46: 1 | FY46: PV/HCO | GC46: Oncology | GE46: Oncology | GF46: true | GI46: 2023-06-09T11:22:09.000+0000 | GJ46: Nemanja Raicevic | GK46: false | GL46: ME | GM46: ME | GN46: false | GP46: Europe/Berlin | GR46: Dijana Stojanovski | GV46: Non-Promotional Remote | GY46: true | HF46: false
A47: [OCE__Call__c] | B47: a2Q69000009PmbhEAC | C47: 0053X00000E3yPJQAZ | D47: false | E47: C-00102411 | F47: EUR | G47: 0123X000000wzbXQAQ | H47: 2023-06-13T13:29:50.000+0000 | I47: 0053X00000E3yPJQAZ | J47: 2024-06-19T12:14:25.000+0000 | K47: 0057U000001Yt7KQAS | L47: 2024-06-19T12:14:25.000+0000 | P47: Nikola Milasevic | Q47: Nikola Milasevic | R47: [] | S47: [] | U47: 0013X00003gWlD6QAK | V47: LJUBLJANSKA BB | AD47: LJUBLJANSKA BB, Podgorica, ME, 81000 | AE47: 2023-03-16T21:00:00.000+0000 | AI47: Detail Only | AJ47: Face To Face | AL47: Podgorica | AN47: false | AT47: 45 | AV47: 2023-03-16T21:45:00.000+0000 | AW47: 0 | BM47: false | BN47: false | BO47: false | BP47: false | BU47: a1J3X00000DYpEiUAL | BX47: false | BY47: false | CC47: 1 | CD47: 0 | CE47: 0 | CV47: Define type of support | CY47: false | CZ47: [{"isAllowAccount":false,"accId":"0013X00003gWlD6QAK"}] | DS47: Submitted | DU47: 2023-06-13T13:29:49.000+0000 | DX47: ME_CORE_TERR_003 | EC47: 81000 | EF47: [{"statementId":"a663X00000094MjQAI","statementType":"Note","statementLabel":"Documenting an Adverse event (AE), Special Situation (SS), Product complaints (PC) in CRM does not constitute a AE/SS/PC reporting to Drug Safety.","statementLabelText":"Documenting an Adverse event (AE), Special Situation (SS), Product complaints (PC) in CRM does not constitute a AE/SS/PC reporting to Drug Safety.","sortOrder":1},{"statementId":"a663X00000094MeQAI","statementType":"Note","statementLabel":"The information (in free text fields) must have been obtained legitimately and must be unambiguous, precise and clear. Only write facts, do not speculate","statementLabelText":"The information (in free text fields) must have been obtained legitimately and must be unambiguous, precise and clear. Only write facts, do not speculate","sortOrder":2}] | EG47: false | EJ47: false | EL47: ME | EM47: false | EP47: false | EQ47: ME | ET47: Call | EU47: Marketing | EW47: true | EX47: 89 | EZ47: https://roche-eu-oce--uat.sandbox.lightning.force.com/a2Q69000009Pmbh | FA47: 1 | FB47: false | FC47: false | FE47: 5 | FF47: false | FG47: 1 | FH47: nemanja.raicevic@roche.com.invalid | FI47: raicevin | FJ47: Core Non Promotional Customer Facing | FK47: false | FL47: false | FN47: Avastin | FO47: Core Non Promotional Customer Facing | FP47: Proactive | FT47: Nikola Milasevic | FU47: Face To Face | FY47: PV/HCO | GC47: Avastin | GE47: Avastin | GF47: true | GK47: false | GL47: ME | GM47: ME | GN47: false | GP47: Europe/Berlin | GR47: Nemanja Raicevic | GV47: Non-Promotional Face To Face | GY47: true | HF47: false
A48: [OCE__Call__c] | B48: a2Q69000009PmckEAC | C48: 0053X00000E3yPJQAZ | D48: false | E48: C-00102428 | F48: EUR | G48: 0123X000000wzbXQAQ | H48: 2023-06-13T13:38:11.000+0000 | I48: 0053X00000E3yPJQAZ | J48: 2024-06-19T12:14:32.000+0000 | K48: 0057U000001Yt7KQAS | L48: 2024-06-19T12:14:32.000+0000 | P48: Nikola Milasevic | Q48: Nikola Milasevic | R48: [] | S48: [] | U48: 0013X00003gWlD6QAK | V48: LJUBLJANSKA BB | AD48: LJUBLJANSKA BB, Podgorica, ME, 81000 | AE48: 2023-03-03T00:30:00.000+0000 | AI48: Detail Only | AJ48: Face To Face | AL48: Podgorica | AN48: false | AT48: 60 | AV48: 2023-03-03T01:30:00.000+0000 | AW48: 0 | BM48: false | BN48: false | BO48: false | BP48: false | BU48: a1J3X00000DYpEiUAL | BX48: false | BY48: false | CC48: 1 | CD48: 0 | CE48: 0 | CY48: false | CZ48: [{"isAllowAccount":false,"accId":"0013X00003gWlD6QAK"}] | DS48: Submitted | DU48: 2023-06-20T10:52:34.000+0000 | DX48: ME_CORE_TERR_003 | EC48: 81000 | EF48: [{"statementId":"a663X00000094MjQAI","statementType":"Note","statementLabel":"Documenting an Adverse event (AE), Special Situation (SS), Product complaints (PC) in CRM does not constitute a AE/SS/PC reporting to Drug Safety.","statementLabelText":"Documenting an Adverse event (AE), Special Situation (SS), Product complaints (PC) in CRM does not constitute a AE/SS/PC reporting to Drug Safety.","sortOrder":1},{"statementId":"a663X00000094MeQAI","statementType":"Note","statementLabel":"The information (in free text fields) must have been obtained legitimately and must be unambiguous, precise and clear. Only write facts, do not speculate","statementLabelText":"The information (in free text fields) must have been obtained legitimately and must be unambiguous, precise and clear. Only write facts, do not speculate","sortOrder":2}] | EG48: false | EJ48: false | EL48: ME | EM48: false | EP48: false | EQ48: ME | ET48: Call | EU48: Marketing | EW48: true | EX48: 109 | EZ48: https://roche-eu-oce--uat.sandbox.lightning.force.com/a2Q69000009Pmck | FA48: 1 | FB48: false | FC48: false | FE48: 5 | FF48: false | FG48: 1 | FH48: nemanja.raicevic@roche.com.invalid | FI48: raicevin | FJ48: Core Non Promotional Customer Facing | FK48: false | FL48: false | FN48: Avastin | FO48: Core Non Promotional Customer Facing | FP48: Proactive | FT48: Nikola Milasevic | FU48: Face To Face | FY48: PV/HCO | GC48: Avastin | GE48: Avastin | GF48: true | GK48: false | GL48: ME | GM48: ME | GN48: false | GP48: Europe/Berlin | GR48: Nemanja Raicevic | GV48: Non-Promotional Face To Face | GY48: true | HF48: false
A49: [OCE__Call__c] | B49: a2Q69000009Pq6DEAS | C49: 0053X00000E3yPJQAZ | D49: false | E49: C-00105459 | F49: EUR | G49: 0123X000000wzbaQAA | H49: 2023-06-16T12:18:59.000+0000 | I49: 0053X00000E3yPJQAZ | J49: 2024-06-19T12:17:56.000+0000 | K49: 0057U000001Yt7KQAS | L49: 2024-06-19T12:17:56.000+0000 | P49: Nikola Milasevic | Q49: Nikola Milasevic | R49: [] | S49: [] | U49: 0013X00003gWlD6QAK | V49: LJUBLJANSKA BB | AD49: LJUBLJANSKA BB, Podgorica, ME, 81000 | AE49: 2023-04-04T13:18:00.000+0000 | AI49: Detail Only | AJ49: Phone | AL49: Podgorica | AN49: false | AT49: 15 | AV49: 2023-04-04T13:33:00.000+0000 | AW49: 0 | BM49: false | BN49: false | BO49: false | BP49: false | BU49: a1J3X00000DYpEiUAL | BX49: false | BY49: false | CC49: 1 | CD49: 0 | CE49: 0 | CY49: false | CZ49: [{"isAllowAccount":false,"accId":"0013X00003gWlD6QAK"}] | DS49: Submitted | DU49: 2023-06-16T12:18:58.000+0000 | DX49: ME_CORE_TERR_003 | EC49: 81000 | EF49: [{"statementId":"a663X00000094MjQAI","statementType":"Note","statementLabel":"Documenting an Adverse event (AE), Special Situation (SS), Product complaints (PC) in CRM does not constitute a AE/SS/PC reporting to Drug Safety.","statementLabelText":"Documenting an Adverse event (AE), Special Situation (SS), Product complaints (PC) in CRM does not constitute a AE/SS/PC reporting to Drug Safety.","sortOrder":1},{"statementId":"a663X00000094MeQAI","statementType":"Note","statementLabel":"The information (in free text fields) must have been obtained legitimately and must be unambiguous, precise and clear. Only write facts, do not speculate","statementLabelText":"The information (in free text fields) must have been obtained legitimately and must be unambiguous, precise and clear. Only write facts, do not speculate","sortOrder":2}] | EG49: false | EJ49: false | EL49: ME | EM49: false | EP49: false | EQ49: ME | ET49: Call | EU49: Marketing | EW49: true | EX49: 73 | EZ49: https://roche-eu-oce--uat.sandbox.lightning.force.com/a2Q69000009Pq6D | FA49: 1 | FB49: false | FC49: false | FE49: 5 | FF49: false | FG49: 1 | FH49: nemanja.raicevic@roche.com.invalid | FI49: raicevin | FJ49: Core Non Promotional Customer Facing | FK49: false | FL49: false | FO49: Core Non Promotional Customer Facing | FP49: Proactive | FR49: ;Oncology | FT49: Nikola Milasevic | FU49: Phone | FY49: PV/HCO | GC49: Oncology | GE49: Oncology | GF49: true | GK49: false | GL49: ME | GM49: ME | GN49: false | GP49: Europe/Berlin | GR49: Nemanja Raicevic | GV49: Non-Promotional Phone | GY49: true | HF49: false
A50: [OCE__Call__c] | B50: a2Q69000009Pq89EAC | C50: 0053X00000E3yPJQAZ | D50: false | E50: C-00105492 | F50: EUR | G50: 0123X000000wzbdQAA | H50: 2023-06-16T12:49:06.000+0000 | I50: 0053X00000E3yPJQAZ | J50: 2024-06-19T12:17:56.000+0000 | K50: 0057U000001Yt7KQAS | L50: 2024-06-19T12:17:56.000+0000 | P50: Nikola Milasevic | Q50: Nikola Milasevic | R50: [] | S50: [] | U50: 0013X00003gWlD6QAK | V50: LJUBLJANSKA BB | AD50: LJUBLJANSKA BB, Podgorica, ME, 81000 | AE50: 2023-04-19T18:30:00.000+0000 | AI50: Detail Only | AJ50: Face To Face | AL50: Podgorica | AN50: false | AT50: 45 | AV50: 2023-04-19T19:15:00.000+0000 | AW50: 0 | BM50: false | BN50: false | BO50: false | BP50: false | BU50: a1J3X00000DYpEiUAL | BX50: false | BY50: false | CC50: 1 | CD50: 0 | CE50: 0 | CY50: false | CZ50: [{"isAllowAccount":false,"accId":"0013X00003gWlD6QAK"}] | DS50: Submitted | DU50: 2023-06-16T12:49:05.000+0000 | DX50: ME_CORE_TERR_003 | EC50: 81000 | EF50: [{"statementId":"a663X00000094MjQAI","statementType":"Note","statementLabel":"Documenting an Adverse event (AE), Special Situation (SS), Product complaints (PC) in CRM does not constitute a AE/SS/PC reporting to Drug Safety.","statementLabelText":"Documenting an Adverse event (AE), Special Situation (SS), Product complaints (PC) in CRM does not constitute a AE/SS/PC reporting to Drug Safety.","sortOrder":1},{"statementId":"a663X00000094MeQAI","statementType":"Note","statementLabel":"The information (in free text fields) must have been obtained legitimately and must be unambiguous, precise and clear. Only write facts, do not speculate","statementLabelText":"The information (in free text fields) must have been obtained legitimately and must be unambiguous, precise and clear. Only write facts, do not speculate","sortOrder":2}] | EG50: false | EJ50: false | EL50: ME | EM50: false | EP50: false | EQ50: ME | ET50: Call | EU50: Marketing | EW50: true | EX50: 58 | EY50: Metastatic Melanoma | EZ50: https://roche-eu-oce--uat.sandbox.lightning.force.com/a2Q69000009Pq89 | FA50: 1 | FB50: false | FC50: false | FE50: 5 | FF50: false | FG50: 1 | FH50: nemanja.raicevic@roche.com.invalid | FI50: raicevin | FJ50: Core Non Promotional Customer Facing | FK50: false | FL50: false | FN50: Cotellic | FO50: Core Non Promotional Customer Facing | FT50: Nikola Milasevic | FU50: Face To Face | FY50: PV/HCO | GC50: Cotellic-Metastatic Melanoma | GE50: Cotellic-Metastatic Melanoma | GF50: true | GK50: false | GL50: ME | GM50: ME | GN50: false | GP50: Europe/Berlin | GR50: Nemanja Raicevic | GV50: Promotional Face To Face | GY50: true | HF50: false
A51: [OCE__Call__c] | B51: a2Q69000009Pq9REAS | C51: 0053X00000E3yPJQAZ | D51: false | E51: C-00105508 | F51: EUR | G51: 0123X000000wzbXQAQ | H51: 2023-06-16T13:04:54.000+0000 | I51: 0053X00000E3yPJQAZ | J51: 2024-06-19T12:17:56.000+0000 | K51: 0057U000001Yt7KQAS | L51: 2024-06-19T12:17:56.000+0000 | P51: Nikola Milasevic | Q51: Nikola Milasevic | R51: [] | S51: [] | U51: 0013X00003gWlD6QAK | V51: LJUBLJANSKA BB | AD51: LJUBLJANSKA BB, Podgorica, ME, 81000 | AE51: 2023-04-28T08:25:00.000+0000 | AI51: Detail Only | AJ51: Face To Face | AL51: Podgorica | AN51: false | AT51: 45 | AV51: 2023-04-28T09:10:00.000+0000 | AW51: 0 | BM51: false | BN51: false | BO51: false | BP51: false | BU51: a1J3X00000DYpEiUAL | BX51: false | BY51: false | CC51: 1 | CD51: 0 | CE51: 0 | CY51: false | CZ51: [{"isAllowAccount":false,"accId":"0013X00003gWlD6QAK"}] | DS51: Submitted | DU51: 2023-06-16T13:04:53.000+0000 | DX51: ME_CORE_TERR_003 | EC51: 81000 | EF51: [{"statementId":"a663X00000094MjQAI","statementType":"Note","statementLabel":"Documenting an Adverse event (AE), Special Situation (SS), Product complaints (PC) in CRM does not constitute a AE/SS/PC reporting to Drug Safety.","statementLabelText":"Documenting an Adverse event (AE), Special Situation (SS), Product complaints (PC) in CRM does not constitute a AE/SS/PC reporting to Drug Safety.","sortOrder":1},{"statementId":"a663X00000094MeQAI","statementType":"Note","statementLabel":"The information (in free text fields) must have been obtained legitimately and must be unambiguous, precise and clear. Only write facts, do not speculate","statementLabelText":"The information (in free text fields) must have been obtained legitimately and must be unambiguous, precise and clear. Only write facts, do not speculate","sortOrder":2}] | EG51: false | EJ51: false | EL51: ME | EM51: false | EP51: false | EQ51: ME | ET51: Call | EU51: Marketing | EW51: true | EX51: 49 | EZ51: https://roche-eu-oce--uat.sandbox.lightning.force.com/a2Q69000009Pq9R | FA51: 1 | FB51: false | FC51: false | FE51: 5 | FF51: false | FG51: 1 | FH51: nemanja.raicevic@roche.com.invalid | FI51: raicevin | FJ51: Core Non Promotional Customer Facing | FK51: false | FL51: false | FO51: Core Non Promotional Customer Facing | FP51: Proactive | FR51: ;Oncology | FT51: Nikola Milasevic | FU51: Face To Face | FY51: PV/HCO | GC51: Oncology | GE51: Oncology | GF51: true | GK51: false | GL51: ME | GM51: ME | GN51: false | GP51: Europe/Berlin | GR51: Nemanja Raicevic | GV51: Non-Promotional Face To Face | GY51: true | HF51: false
A52: [OCE__Call__c] | B52: a2Q69000009Ps8GEAS | C52: 0053X00000E3yPJQAZ | D52: false | E52: C-00108063 | F52: EUR | G52: 0123X000000wzbXQAQ | H52: 2023-06-20T11:05:41.000+0000 | I52: 0053X00000E3yPJQAZ | J52: 2024-06-19T12:21:15.000+0000 | K52: 0057U000001Yt7KQAS | L52: 2024-06-19T12:21:15.000+0000 | P52: Nikola Milasevic | Q52: Nikola Milasevic | R52: [] | S52: [] | U52: 0013X00003gWlD6QAK | V52: LJUBLJANSKA BB | AD52: LJUBLJANSKA BB, Podgorica, ME, 81000 | AE52: 2023-05-19T07:30:00.000+0000 | AI52: Detail Only | AJ52: Face To Face | AL52: Podgorica | AN52: false | AT52: 30 | AV52: 2023-05-19T08:00:00.000+0000 | AW52: 0 | BM52: false | BN52: false | BO52: false | BP52: false | BU52: a1J3X00000DYpEiUAL | BX52: false | BY52: false | CC52: 1 | CD52: 0 | CE52: 0 | CY52: false | CZ52: [{"isAllowAccount":false,"accId":"0013X00003gWlD6QAK"}] | DS52: Submitted | DU52: 2023-06-20T11:05:40.000+0000 | DX52: ME_CORE_TERR_003 | EC52: 81000 | EF52: [{"statementId":"a663X00000094MjQAI","statementType":"Note","statementLabel":"Documenting an Adverse event (AE), Special Situation (SS), Product complaints (PC) in CRM does not constitute a AE/SS/PC reporting to Drug Safety.","statementLabelText":"Documenting an Adverse event (AE), Special Situation (SS), Product complaints (PC) in CRM does not constitute a AE/SS/PC reporting to Drug Safety.","sortOrder":1},{"statementId":"a663X00000094MeQAI","statementType":"Note","statementLabel":"The information (in free text fields) must have been obtained legitimately and must be unambiguous, precise and clear. Only write facts, do not speculate","statementLabelText":"The information (in free text fields) must have been obtained legitimately and must be unambiguous, precise and clear. Only write facts, do not speculate","sortOrder":2}] | EG52: false | EJ52: false | EL52: ME | EM52: false | EP52: false | EQ52: ME | ET52: Call | EU52: Marketing | EW52: true | EX52: 32 | EZ52: https://roche-eu-oce--uat.sandbox.lightning.force.com/a2Q69000009Ps8G | FA52: 1 | FB52: false | FC52: false | FE52: 5 | FF52: false | FG52: 1 | FH52: nemanja.raicevic@roche.com.invalid | FI52: raicevin | FJ52: Core Non Promotional Customer Facing | FK52: false | FL52: false | FO52: Core Non Promotional Customer Facing | FP52: Proactive | FR52: ;Oncology | FT52: Nikola Milasevic | FU52: Face To Face | FY52: PV/HCO | GC52: Oncology | GE52: Oncology | GF52: true | GK52: false | GL52: ME | GM52: ME | GN52: false | GP52: Europe/Berlin | GR52: Nemanja Raicevic | GV52: Non-Promotional Face To Face | GY52: true | HF52: false
